Workbook
Name L_CATEGORIAS: _LISTAS!$D$4:$D$12
Name L_CERTEZA: _LISTAS!$L$4:$L$6
Name L_DIRECCION: _LISTAS!$P$4:$P$6
Name L_ESTADO: _LISTAS!$E$4:$E$6
Name L_FUNCION: _LISTAS!$J$4:$J$12
Name L_HOJAS: _LISTAS!$A$4:$A$15
Name L_NIVEL_REL: _LISTAS!$O$4:$O$6
Name L_OBLIGATORIO: _LISTAS!$C$4:$C$6
Name L_PAIS: _LISTAS!$I$4:$I$15
Name L_SEGMENTO: _LISTAS!$K$4:$K$12
Name L_SPN: _LISTAS!$R$4:$R$6
Name L_TIER: _LISTAS!$H$4:$H$6
Name L_TIPO_ACTOR: _LISTAS!$M$4:$M$36
Name L_TIPO_CAMBIO: _LISTAS!$F$4:$F$14
Name L_TIPO_RELACION: _LISTAS!$N$4:$N$12
Name L_TIPOS_DATO: _LISTAS!$B$4:$B$9
Name L_VERTICAL: _LISTAS!$G$4:$G$12
Name L_VIS_POI: _LISTAS!$Q$4:$Q$6

Sheet DASHBOARD
A2: Mapa del Ecosistema Deportivo Mexicano 2026 | I2: v1.00.31
A3: PANEL EJECUTIVO · Vista de navegación rápida del workbook | I3: Playbook Sports Intelligence · Confidencial
A5: Panorama del universo
A6: 110 | D6: 114 | G6: 263 | J6: 159
A7: ACTORES ACTIVOS | D7: TIER 1 + TIER 2 | G7: RELACIONES | J7: POIS
A8: 149 totales · 2 desactivados | D8: 51 Tier 1 · 63 Tier 2 | G8: en Mapa de Conexiones
A10: 9 | D10: 33 | G10: 22 | J10: 7
A11: VERTICALES | D11: SUBCAPACIDADES | G11: REGLAS VIGENTES | J11: Clusters de poder
D12: en matriz Amplitud Funcional
A14: Navegar por vertical
A15: Cada vertical abre su ficha detallada. Click en el número con flecha para navegar.
A16: V1 | B16: Rights Owners | D16: 51 → | E16: V2 | F16: Media & Distribution | H16: 23 → | I16: V3 | J16: Commercialization | L16: 29 →
A17: Quien controla los derechos primarios de una competición o evento serial | E17: Quien empaqueta y distribuye contenido deportivo | I17: Sponsors y marcas que monetizan el deporte
A19: V4 | B19: Agencies & Talent | D19: 16 → | E19: V5 | F19: Events & Experiences | H19: 24 → | I19: V6 | J19: Ticketing & Access | L19: 19 →
A20: Agencias de representación, marketing deportivo, hospitality B2B | E20: Operadores de eventos masivos y experiencias deportivas | I20: Plataformas de boleteo primario y Fan ID
A22: V7 | B22: Infrastructure | D22: 27 → | E22: V8 | F22: Sports Tech & Data | H22: 18 → | I22: V9 | J22: Capital & Investment | L22: 22 →
A23: Venues, estadios, arenas con valor estratégico | E23: Tecnología B2B aplicada al deporte: data, analytics, SaaS | I23: Capital deportivo: PE, family offices, fondos
A26: Top 15 actores · Score Compuesto
A27: Combinación 50/50 de Amplitud (presencia cross-vertical) y Profundidad (densidad por vertical activa). Tier 1 resaltado en ámbar.
A28: # | B28: Actor | G28: Tier | H28: Vert. | I28: Tipo Capacidad | K28: Ampl. | L28: Comp.
A29: 1 | B29: A-035 Endeavor / WME Group | G29: T1 | H29: V9 | I29: Multi-cap. | K29: 9 | L29: 0.781
A30: 2 | B30: A-044 FEMSA / Club de Fútbol Monterrey Rayados | G30: T1 | H30: V9 | I30: Multi-cap. | K30: 9 | L30: 0.781
A31: 3 | B31: A-020 CIE / OCESA (V5 Experiencias) | G31: T1 | H31: V5 | I31: Multi-cap. | K31: 7.5 | L31: 0.729
A32: 4 | B32: A-043 Federación Mexicana de Fútbol | G32: T1 | H32: V1 | I32: Especialista | K32: 4 | L32: 0.722
A33: 5 | B33: A-084 Liga MX | G33: T1 | H33: V1 | I33: Especialista | K33: 4 | L33: 0.722
A34: 6 | B34: A-104 Octagon | G34: T2 | H34: V4 | I34: Especialista | K34: 4 | L34: 0.722
A35: 7 | B35: A-059 Grupo Martí / Familia Harp Helú | G35: T1 | H35: V9 | I35: Multi-cap. | K35: 7.5 | L35: 0.651
A36: 8 | B36: A-025 Consejo Mundial de Lucha Libre (CMLL) | G36: T2 | H36: V1 | I36: Especialista | K36: 5.5 | L36: 0.649
A37: 9 | B37: A-083 Liga Mexicana del Pacífico (LMP) | G37: T2 | H37: V1 | I37: Especialista | K37: 5.5 | L37: 0.649
A38: 10 | B38: A-151 Liga BBVA MX Femenil | G38: T1 | H38: V1 | I38: Especialista | K38: 3.5 | L38: 0.632
A39: 11 | B39: A-071 HG Promotores en Deporte y Entretenimiento | G39: T3 | H39: V5 | I39: Especialista | K39: 5 | L39: 0.59
A40: 12 | B40: A-085 LIV Golf League (Mexico City) | G40: T2 | H40: V1 | I40: Especialista | K40: 5 | L40: 0.59
... A43: 15 | B43: A-105 Ollamani, S.A.B. / Grupo Águilas (Club América + Estadi | G43: T1 | H43: V9 | I43: Multi-cap. | K43: 6 | L43: 0.583
A44: → Ranking completo de los 151 actores en hoja AMPLITUD FUNCIONAL
A46: Índice del workbook
A47: Acceso directo a cada hoja del libro con descripción de qué contiene.
A48: Hoja | E48: Contenido | J48: Tipo
A49: UNIVERSO MAESTRO | E49: Catálogo principal de 151 actores con ficha completa | J49: Master · 23 columnas por actor
A50: AMPLITUD FUNCIONAL | E50: Matriz 151 × 33 subcaps con scores Vx, Amplitud, Profundidad y Compuesto | J50: Scoring
A51: MAPA DE CONEXIONES | E51: 263 relaciones tipo A→B (Sponsorship, Inst., Data, Rights, Venue, Ticketing) | J51: Relaciones
A52: POI MAESTRO | E52: 160 personas físicas relevantes vinculadas a actores | J52: POIs
A53: PIEDRAS ANGULARES | E53: Los 10 mandamientos del Mapa: filosofía que precede a las reglas operativas | J53: Filosofía
A54: REGLAS METODOLÓGICAS | E54: 22 reglas que gobiernan inclusión, absorción, scoring y herencia | J54: Metodología
A55: CLUSTERS EJECUTIVOS | E55: 7 agrupaciones temáticas con actor central, conexiones e insight | J55: Síntesis
A56: DICCIONARIO | E56: Catálogo de 38 campos del workbook: una fuente de verdad por concepto | J56: Referencia
A57: CHANGELOG | E57: Trazabilidad versionada de cada cambio desde v1.00 hasta v1.00.31 | J57: Auditoría
A58: FICHAS_V1 a V9 | E58: Vista por vertical: cada actor con presencia en la vertical, ordenado por Score | J58: 229 fichas
A59: Buscar y filtrar actores
A60: La hoja _DASH_DATA contiene una tabla nativa con los 151 actores y filtros por columna. Filtra por Tier, Vertical, Tipo, Tipo de Capacidad o cualquier campo. Ordena por Score Compuesto, Amplitud o Profundidad.
A62: → Abrir tabla filtrable de actores (_DASH_DATA) | G62: Click en cualquier dropdown del header de la tabla para filtrar.
A65: Playbook Sports Intelligence · v1.00.31 · Confidencial · Uso interno

Sheet PIEDRAS ANGULARES
B3: PIEDRAS ANGULARES
B4: Los 10 mandamientos del Mapa
B5: Por qué hacemos esto y qué NO somos. Esto antecede a las 22 reglas metodológicas: las reglas operativas se derivan de aquí.
B8: 01 | C8: Un mapa, no un censo | E8: R-08, S-01, S-02
C9: Incluimos lo que mueve la aguja, no todo lo que existe.
C10: El universo no es exhaustivo. Cada actor cargado tiene que justificar su lugar con señal estratégica diferenciada. Si quitarlo no cambia la lectura del ecosistema, no entra.
B12: 02 | C12: Estructural sobre opinático | E12: M-AF-01 a M-AF-19
C13: Cada actor se evalúa por lo que hace, no por lo que dice que hace.
C14: Las subcapacidades de Amplitud Funcional son binarias, no impresiones. Si un sponsor dice "tenemos activación 360" pero solo paga jersey, no califica activación 360. La evidencia manda sobre el comunicado oficial.
B16: 03 | C16: Capacidad operativa, no facturación | E16: AMPLITUD FUNCIONAL completa
C17: El score mide qué puede hacer un actor, no cuánto factura ni cuánto vale.
C18: No es un ranking financiero. Endeavor y FEMSA empatan en Score Compuesto (0.781) aunque sus revenues son muy distintos. La pregunta del score es: "¿qué cosas puede ejecutar este actor en el ecosistema?", no "¿cuánto dinero mueve?".
B20: 04 | C20: Una sola línea de propiedad | E20: R-01, R-12, R-13, M-AF-01
C21: Si el padre está mapeado, el hijo se hereda. No duplicamos.
C22: Cuando un club, equipo o activo es 100% propiedad de un holding mapeado, no se carga como actor standalone. Su capacidad se hereda al padre y su identidad se preserva en Productos/Propiedades y Notas. Esto evita un universo inflado (Rayados no aparece 3 veces: como club, como FEMSA, como Estadio BBVA).
B24: 05 | C24: Doble eje obligatorio | E24: AMPLITUD FUNCIONAL · cols Amplitud, Profundidad, Compuesto
C25: Amplitud y Profundidad valen lo mismo. Ni holdings diversificados ni especialistas verticales dominan solos.
C26: Sin Profundidad, los holdings arrasan cualquier ranking y los especialistas desaparecen. Octagon (Especialista V4) y Endeavor (Diversificado) tienen Score Compuesto similar porque ambos perfiles son relevantes para el cliente. El doble eje es la decisión metodológica más fundamental del scoring.
B28: 06 | C28: Las relaciones tienen dirección | E28: M-01, REL-01 a REL-03
C29: A→B describe quién hace qué a quién. No son grafos simétricos por default.
C30: En Sponsorship, A es la marca y B la propiedad esponsoreada. En Ownership, A es el padre y B el hijo. En Rights/Media, A es el rights holder y B el broadcaster. La direccionalidad cambia la lectura: invertirla puede cambiar el sentido del cluster. Solo las membresías simétricas (JVs) usan A↔B.
B32: 07 | C32: Trazabilidad sobre conclusión | E32: CHANGELOG · REGLAS METODOLÓGICAS · campo Fuente en MC
C33: Cada celda se justifica. Cada cambio queda en CHANGELOG.
C34: No hay celda sin fuente. No hay decisión sin regla detrás. No hay versión sin entrada en CHANGELOG. Esto permite que el sistema sobreviva al autor: se puede persona puede entrar en 6 meses y reconstruir por qué cada decisión es como es.
B36: 08 | C36: El mapa es un sistema vivo | E36: CHANGELOG · campo Notas de propiedad
C37: Cada versión es snapshot, no verdad eterna. La validez depende de la fecha.
C38: En 2025-2026 el ecosistema cambió más que en los 10 años anteriores: General Atlantic entró a Ollamani, Apollo cerró Atlético Madrid, 4 clubes Liga MX cambiaron de dueño, Wasserman se rebrandeó a THE·TEAM. Un mapa "para siempre" sería un mapa falso. La versión vigente al cierre de v1.00.30 es la verdad del 11 de mayo de 2026, no la del próximo trimestre.
B40: 09 | C40: Verificación antes de elegancia | E40: campo Certeza · M-AF-19
C41: Una fuente única es flag amarillo, no celda lista.
C42: El campo Certeza distingue Verificado (2+ fuentes), Fuente única (pendiente cross-check) y Desactivado. Una afirmación no sustituye verificación. Si no podemos contrastar, lo decimos: "Fuente única".
B44: 10 | C44: Inteligencia accionable, no decoración | E44: Toda la arquitectura del workbook
C45: Cada deliverable existe porque cambia una decisión.
C46: Ningún slide, gráfico, hoja o ficha se construye "porque queda bien". Cada elemento del workbook tiene un sentido y valor agreagado.
B51: Las 22 reglas metodológicas de operación se derivan de estos 10 principios. Si una regla nueva contradice un mandamiento, el mandamiento gana. Si dos mandamientos parecen contradecirse, gana el de menor número.

Sheet DICCIONARIO
A1: ◼ PLAYBOOK | B1: DICCIONARIO DE CAMPOS
A2: Playbook Sports Intelligence | B2: Lista canónica de campos del workbook · Una sola fuente de verdad por concepto
A3: Playbook_Mapeo_v1.00.xlsx · Mapa del Ecosistema Deportivo Mexicano 2026 · CONFIDENCIAL · Uso interno
A5: Campo | B5: Hoja origen | C5: Tipo de dato | D5: Valores permitidos | E5: Obligatorio | F5: Descripción | G5: Criterio de asignación | H5: Notas
A6: ↓ Catálogo completo de campos del workbook. Una sola fuente de verdad por concepto. Para cualquier conflicto entre hojas, este diccionario prevalece.
A7: ID | B7: UNIVERSO MAESTRO | C7: Texto | D7: A-001 a A-XXX (4 dígitos) | E7: Sí | F7: Identificador único e inmutable del actor en el workbook. | G7: Asignación secuencial al cargar. Una vez asignado NO se reutiliza si el actor se desactiva. | H7: Convención: A- prefijo + 3 dígitos. Inmutable.
A8: ID Vertical | B8: UNIVERSO MAESTRO | C8: Texto | D8: V1-001 a V9-XXX | E8: Sí | F8: Identificador secundario del actor en su vertical primaria. | G8: Asignado en el orden de carga dentro de la vertical primaria. | H8: Permite cruce rápido con FICHAS_Vx. Inmutable.
A9: Nombre | B9: UNIVERSO MAESTRO | C9: Texto | D9: — | E9: Sí | F9: Nombre canónico del actor como aparece en comunicaciones oficiales. | G9: Usar el nombre legal o el más conocido públicamente. Para holdings: nombre del holding + activo principal entre paréntesis. | H9: Ejemplo: Ollamani, S.A.B. / Grupo Águilas (Club América + Estadio Banorte)
A10: Vertical Primaria | B10: UNIVERSO MAESTRO | C10: Lista | D10: V1, V2, V3, V4, V5, V6, V7, V8, V9 | E10: Sí | F10: Vertical funcional principal donde el actor concentra su actividad operativa. | G10: Regla T-01: la vertical donde tiene mayor Score (puntajes 1.0 / 0.5 / 0) en las subcaps de esa vertical. Empate: la primera por orden V1→V9. | H10: Solo UNA. Las demás presencias se documentan vía Etiquetas Secundarias.
A11: Etiquetas Secundarias | B11: UNIVERSO MAESTRO | C11: Lista (multi) | D11: V1, V2, V3, V4, V5, V6, V7, V8, V9 | E11: No | F11: Verticales adicionales donde el actor tiene presencia operativa (Score ≥ 0.5). | G11: Auto-derivable de AMPLITUD FUNCIONAL. Se documenta para visibilidad rápida sin abrir AF. | H11: Separadas por coma. Ejemplo: V5, V7
A12: Tipo | B12: UNIVERSO MAESTRO | C12: Lista | D12: L_TIPO_ACTOR (33 valores) | E12: Sí | F12: Categoría operativa del actor (Holding, Club, Liga, Sponsor, Federación, etc). | G12: Asignación por naturaleza primaria del actor. | H12: Ver _LISTAS columna M para catálogo completo.
A13: Tier | B13: UNIVERSO MAESTRO | C13: Lista | D13: Tier 1, Tier 2, Tier 3 | E13: Sí | F13: Nivel de relevancia estratégica del actor en el ecosistema. | G13: Tier 1: actor dominante en su vertical / Tier 2: actor relevante con escala / Tier 3: actor menor con señal estratégica diferenciada (regla R-08). | H13: 51 Tier 1, 63 Tier 2, resto Tier 3.
A14: País | B14: UNIVERSO MAESTRO | C14: Lista | D14: México, USA, España, Brasil, etc. | E14: Sí | F14: País de origen del HQ corporativo del actor. | G14: Para multinacionales: país del HQ global, no de la oficina MX. | H14: Apollo Sports Capital = USA (aunque opera ASL en MX).
A15: Ciudad | B15: UNIVERSO MAESTRO | C15: Texto | D15: — | E15: No | F15: Ciudad del HQ operativo en México (cuando aplica). | G15: Para multinacionales sin oficina MX: dejar vacío.
A16: Rol | B16: UNIVERSO MAESTRO | C16: Texto | D16: — | E16: No | F16: Síntesis de una línea de qué hace el actor. | G16: Empezar con verbo de acción (opera, produce, distribuye, monetiza, regula...). Max 100 chars. | H16: Se usa en Overview de fichas y dashboards.
A17: Sector | B17: UNIVERSO MAESTRO | C17: Texto | D17: — | E17: No | F17: Sector de mercado donde opera el actor. | G17: Usar nomenclatura GICS o equivalente: Sports Media, Consumer Brands, Financial Services, Private Equity, etc. | H17: Diferenciar Sector (Consumer Brands) de Tipo (Sponsor).
A18: Descripción | B18: UNIVERSO MAESTRO | C18: Texto largo | D18: — | E18: Sí | F18: Párrafo de 2-4 líneas explicando qué hace el actor, su escala y su relevancia para el ecosistema MX. | G18: Información factual verificable. Sin opiniones ni adjetivos sin sustento. Cerrar con dato de escala (USD, % market share, # de propiedades, etc.) cuando se tenga. | H18: Es la primera fuente para el Overview de fichas.
A19: Por qué importa | B19: UNIVERSO MAESTRO | C19: Texto largo | D19: — | E19: No | F19: Síntesis de relevancia estratégica: ¿qué pasaría si este actor desapareciera mañana? | G19: Pensar en el contrafáctico. Si hay sustitutos directos en el ecosistema MX, el actor es menos crítico. | H19: Útil para priorización en deliverables al cliente.
A20: Productos / Propiedades | B20: UNIVERSO MAESTRO | C20: Texto largo | D20: — | E20: Sí | F20: Lista de propiedades distintivas, productos o subsidiarias del actor. | G20: Separar con · (middle dot). Incluir naming sponsors, eventos seriales, venues operados, marcas controladas. Para holdings: incluir club varonil + femenil cuando aplique (R-13). | H20: Es el campo más usado en el Dashboard y FICHAS.
A21: Estructura corporativa | B21: UNIVERSO MAESTRO | C21: Texto | D21: — | E21: No | F21: Forma legal del actor: S.A.B., S.A. de C.V., LLC, Foundation, Family Office, etc. | G21: Tomar del registro mercantil o documento corporativo público.
A22: Notas de propiedad | B22: UNIVERSO MAESTRO | C22: Texto largo | D22: — | E22: No | F22: Notas sobre estructura de ownership, cambios accionarios recientes, controlling shareholders. | G22: Cuando aplica regla R-12/R-13: incluir marker explícito ej. [R-13: Propiedad cross-género...]. Cuando hay venta en proceso: marcar [VENTA EN PROCESO] con fecha esperada de cierre. | H22: Campo crítico para tracking de cambios estructurales 2025-2026.
A23: Web | B23: UNIVERSO MAESTRO | C23: URL | D23: — | E23: No | F23: Sitio web oficial del actor. | G23: URL completa con https://. Usar dominio corporativo no marketing.
A24: Certeza | B24: UNIVERSO MAESTRO | C24: Lista | D24: Verificado, Fuente única, Desactivado | E24: Sí | F24: Nivel de validación de la información del actor. | G24: Verificado: dos fuentes mínimo. Fuente única: información de un solo origen, marcar para validar. Desactivado: actor removido del scope pero mantenido para trazabilidad. | H24: En v1.00.29: 2 actores Desactivados (Hard Rock Stadium, CAA Sports MX).
A25: Visualizable | B25: UNIVERSO MAESTRO | C25: Lista | D25: Sí, No | E25: Sí | F25: Si el actor se incluye en visualizaciones (bubble map, network) y dashboards. | G25: No: para actores Desactivados o que se mantienen para trazabilidad histórica sin querer comunicarlos. | H25: 110 visualizables de 151 totales.
A26: Score V1 a V9 | B26: AMPLITUD FUNCIONAL | C26: Numérico | D26: 0 a 4 (suma de subcaps) | E26: Calc | F26: Promedio de las subcapacidades de cada vertical para el actor. | G26: Cada vertical tiene 3-6 subcaps. Suma de scores 1.0/0.5/0 dividido entre número de subcaps activas. | H26: Calculado automáticamente desde la matriz 151×33.
A27: Amplitud | B27: AMPLITUD FUNCIONAL | C27: Numérico | D27: 0 a 9 | E27: Calc | F27: Suma simple de los 9 scores Vx. | G27: Cuanto más alto, mayor presencia cross-vertical. | H27: Holdings diversificados dominan este score.
A28: Profundidad | B28: AMPLITUD FUNCIONAL | C28: Numérico | D28: 0 a 1 | E28: Calc | F28: Amplitud dividida entre número de verticales con presencia > 0. | G28: Cuanto más alto, mayor concentración funcional en pocas verticales. | H28: Especialistas dominan este score.
A29: Compuesto | B29: AMPLITUD FUNCIONAL | C29: Numérico | D29: 0 a 1 | E29: Calc | F29: Combinación normalizada 50/50 de Amplitud y Profundidad contra el max observado. | G29: Es el score de referencia para rankings. Balancea ancho y profundidad. | H29: Top: Endeavor 0.781, FEMSA 0.781, OCESA 0.729.
A30: Tipo Capacidad | B30: AMPLITUD FUNCIONAL | C30: Calc | D30: Especialista / Multi-capacidad / Diversificado | E30: Calc | F30: Categoría auto-derivada por número de verticales con presencia (Score Vx ≥ 1). | G30: Especialista: 1-2 verticales. Multi-capacidad: 3-4. Diversificado: 5+. | H30: En v1.00.29: 129 Especialistas, 16 Multi-capacidad, 0 Diversificado.
A31: ID Relación | B31: MAPA DE CONEXIONES | C31: Texto | D31: R-001 a R-XXX | E31: Sí | F31: Identificador único e inmutable de la relación. | G31: Asignación secuencial al cargar. No reutilizable si la relación se elimina.
A32: Actor A | B32: MAPA DE CONEXIONES | C32: Texto | D32: ID de UM | E32: Sí | F32: Identificador del actor del lado activo de la relación. | G32: Regla M-01: dirección A→B donde A es el agente, B el receptor. | H32: Sponsorship A=marca, B=propiedad esponsoreada. Ownership A=padre, B=hijo.
A33: Actor B | B33: MAPA DE CONEXIONES | C33: Texto | D33: ID de UM | E33: Sí | F33: Identificador del actor del lado receptor. | G33: Ver M-01.
A34: Tipo de relación | B34: MAPA DE CONEXIONES | C34: Lista | D34: L_TIPO_RELACION (8 valores) | E34: Sí | F34: Tipo canónico: Sponsorship, Institutional/Regulatory, Rights/Media, Venue/Operations, Ticketing/Access, Agency/Intermediation, Ownership/Control, Data/Fan Intelligence, Strategic/Operational. | G34: Asignación según naturaleza primaria de la relación. Si hay dos tipos: crear dos relaciones separadas. | H34: Top 3 en v1.00.30: Sponsorship 71, Inst./Reg 39, Data/Fan 29.
A35: Nivel | B35: MAPA DE CONEXIONES | C35: Lista | D35: R1, R2, R3 | E35: Sí | F35: Nivel de validación / certeza de la relación. | G35: R1: dos fuentes mínimo + relación pública. R2: una fuente confiable o relación pública pero no documentada en detalle. R3: inferida lógicamente, pendiente verificación.
A36: Dirección | B36: MAPA DE CONEXIONES | C36: Lista | D36: A→B, A↔B | E36: Sí | F36: Direccionalidad de la relación. | G36: A→B: una dirección clara. A↔B: bidireccional simétrica (raro, solo en JVs o membresías).
A37: Descripción | B37: MAPA DE CONEXIONES | C37: Texto largo | D37: — | E37: Sí | F37: Qué es exactamente la relación: contrato, alianza, propiedad, etc. | G37: Empezar con sustantivo concreto. Incluir cifra (USD, %, fechas) cuando exista.
A38: Por qué importa | B38: MAPA DE CONEXIONES | C38: Texto largo | D38: — | E38: No | F38: Relevancia estratégica de la relación. | G38: Pensar en el contrafáctico: ¿qué cambia si la relación se rompe?
A39: Fuente | B39: MAPA DE CONEXIONES | C39: Texto | D39: — | E39: No | F39: Referencias bibliográficas, URLs o documentos de respaldo. | G39: Comunicados oficiales, prensa especializada (ESPN, Sportico, Forbes), filings (BMV, SEC).
A40: ID POI | B40: POI MAESTRO | C40: Texto | D40: P-001 a P-XXX | E40: Sí | F40: Identificador único de la persona física. | G40: Asignación secuencial. Inmutable.
A41: Actor asociado | B41: POI MAESTRO | C41: Texto | D41: ID de UM | E41: Sí | F41: Actor al que está vinculado el POI. | G41: Si el POI está vinculado a 2+ actores, crear entradas separadas o documentar en Notas.
A42: Tier POI | B42: POI MAESTRO | C42: Lista | D42: Tier 1, Tier 2, Tier 3 | E42: Sí | F42: Nivel de poder de decisión. | G42: Tier 1: decisor último (CEO, dueño, presidente). Tier 2: operativo clave con autoridad presupuestal. Tier 3: relevante con visibilidad pública sin poder de decisión final.
A43: ID Regla | B43: REGLAS METODOLÓGICAS | C43: Texto | D43: M-XX, R-XX, E-XX, T-XX, V-XX, P-XX, REL-XX, S-XX, SAT-XX, M-AF-XX | E43: Sí | F43: Identificador único de la regla. | G43: Prefijo según categoría: M=Master, R=Consolidación, E=Excepción, T=Vertical/Tier, V=Validación, P=POI, REL=Relación, S=Scope, SAT=Saturación, M-AF=Calificación AF. | H43: 22 reglas vigentes en v1.00.30.

Sheet UNIVERSO MAESTRO
A1: ◼ PLAYBOOK | B1: UNIVERSO MAESTRO
A2: Playbook Sports Intelligence | B2: Base de datos canónica de actores · Una fila por actor activo · Fuente de verdad del workbook
A3: Playbook_Mapeo_v1.00.xlsx · Mapa del Ecosistema Deportivo Mexicano 2026 · CONFIDENCIAL · Uso interno
A5: ID Maestro | B5: ID Vertical | C5: Nombre del actor | D5: Vertical primaria | E5: Etiquetas secundarias | F5: Tipo de actor | G5: Tier | H5: País de origen | I5: Ciudad / base operativa MX | J5: Función comercial principal | K5: Segmento deportivo prioritario | L5: Qué hace realmente | M5: Por qué importa | N5: Known For | O5: Productos / propiedades | P5: Notas de propiedad | Q5: Sitio web | R5: Nivel de certeza | S5: Flag / Fuentes | T5: Visualizable en mapa ejecutivo
A6: A-016 | B6: V1-001 | C6: Canelo Promotions / Saúl Álvarez | D6: V1 | E6: V4 · V3 | F6: Promoción / Boxing promotion | G6: Tier 1 | H6: México | I6: San Diego, CA / Guadalajara | J6: Controla propiedad / capital | K6: Boxeo | L6: El atleta individual de mayor valor comercial de México. DAZN como broadcaster exclusivo. Hennessy, Tecate, Michelob Ultra y Oakley como sponsors principales. GGG vs Canelo generó más de USD 160M en PPV en EE.UU. | M6: Canelo es el activo deportivo individual más valioso de México. Su modelo de gestión 360° (Reynoso como manager-entrenador-promotor) es único en el boxeo mundial. Los ingresos por pelea superan el revenue anual de muchos clubes Liga MX. | N6: Canelo Promotions (boxeo) · Canelo Espectáculos · Canelo Store (retail) · Canelo Technologies (app I Can) · Canelo Energy (4 gasolineras Jalisco) · Upper (80 tiendas conveniencia) · SSA Inmobiliaria · SSA Capitales · VMC Drinks (tequila) · Yaoca (rehidratante) · CA (residuos/agua) · Línea autobuses Jalisco · Taquería El Pastor del Rica | O6: Canelo Media · No Boxing No Life · Saúl "Canelo" Álvarez (atleta franquicia) | P6: Vehículo comercial de Saúl Álvarez. Producción de contenido (Canelo Media), promoción de peleas (No Boxing No Life), gestión de derechos del atleta. [v1.00.29: conglomerado ampliado a 12+ empresas según ESPN/Forbes/El Heraldo. Promotora propia desde 2021 tras separación Golden Boy. Fortuna estimada USD 275M Forbes 2025.] | Q6: canelo.tv | R6: Verificado | T6: =IF(G6="","",IF(OR(G6="Tier 3"),"No",IF(AND(S6<>"",OR(ISNUMBER(SEARCH("OFAC",S6)),ISNUMBER(SEARCH("penal",S6)),ISNUMBER(SEARCH("rojo pendiente",S6)))),"Revisar","Sí"))) -> Sí
A7: A-017 | B7: V1-002 | C7: Capitanes de Ciudad de México (NBA G-League) | D7: V1 | E7: V7 · V9 | F7: Club basketball / NBA G-League | G7: Tier 2 | H7: México | I7: CDMX | L7: Compite en NBA G-League. Único equipo NBA-affiliated en LATAM. | M7: Plataforma para introducir baloncesto NBA-grade en MX. Operación Arena CDMX (sub-arrendamiento). | N7: Capitanes de Ciudad de México (NBA G-League) · Arena Ciudad de México (home games) · Programa Capitanes Academy · Affiliate de Oklahoma City Thunder (NBA) | P7: [v1.00.29: única franquicia G-League fuera EE.UU./Canadá. Filial NBA G-League directamente operada por NBA Properties; juega en Arena CDMX (Avalanz A-056).] | Q7: capitanescdmx.com | R7: Verificado | T7: =IF(G7="","",IF(OR(G7="Tier 3"),"No",IF(AND(S7<>"",OR(ISNUMBER(SEARCH("OFAC",S7)),ISNUMBER(SEARCH("penal",S7)),ISNUMBER(SEARCH("rojo pendiente",S7)))),"Revisar","Sí"))) -> Sí
A8: A-019 | B8: V1-003 | C8: Charros de Jalisco (LMB + LMP) | D8: V1 | E8: V7 | F8: Club LMB / Béisbol profesional | G8: Tier 2 | H8: México | I8: Guadalajara | K8: Béisbol | L8: Doble franquicia LMB verano y LMP invierno. Sede Estadio Panamericano (Zapopan). | M8: Charros Jalisco: única franquicia con doble temporada activa. Campeón LMP 2018-19. Mercado GDL. | N8: Charros de Jalisco beisbol varonil (LMB Banorte verano + LMP invierno) · Charros de Jalisco Femenil softbol (LMS) · Estadio Panamericano (Zapopan) · Academia formativa | P8: [v1.00.29: doble temporada LMB (verano) + LMP (invierno). Campeón LMS 2024 (softbol femenil). Sociedad familia Salcido.] | Q8: charrosbeisbol.com | R8: Verificado | T8: =IF(G8="","",IF(OR(G8="Tier 3"),"No",IF(AND(S8<>"",OR(ISNUMBER(SEARCH("OFAC",S8)),ISNUMBER(SEARCH("penal",S8)),ISNUMBER(SEARCH("rojo pendiente",S8)))),"Revisar","Sí"))) -> Sí
A9: A-021 | B9: V1-004 | C9: Club Necaxa | D9: V1 | E9: V3 · V7 | F9: Club Liga MX | G9: Tier 3 | H9: México | I9: Aguascalientes | J9: Controla propiedad / capital | K9: Fútbol | L9: Club con modelo de ownership mixto que incluye celebridades del deporte norteamericano como accionistas. Broadcaster: Claro Sports (compartido). Segunda Spectrum (Genius Sports) como proveedor de tracking de jugadores. | M9: Primer club Liga MX con tracking de jugadores de nivel NBA. Accionistas celebrity del deporte norteamericano. Presencia en el radar del mercado norteamericano. | N9: Accionistas celebrity norteamericanos; Segunda Spectrum (first tracking Liga MX de nivel NBA) · Necaxa Femenil | P9: [R-13: Propiedad cross-género: el equipo femenil se mapea como propiedad dentro de este actor, no como actor standalone separado.] | Q9: necaxa.com | R9: Verificado | T9: sí
A10: A-022 | B10: V1-005 | C10: Club Toluca | D10: V1 | E10: V3 · V7 | F10: Club Liga MX | G10: Tier 1 | H10: México | I10: Toluca, Estado de México | J10: Controla propiedad / capital | K10: Fútbol | L10: BICAMPEÓN 2025: Clausura 2025 (11° título, rompió sequía 15 años) y Apertura 2025 (12° título, vs Tigres en penales 9-8). Empata a Chivas como segundo club más ganador de Liga MX. | M10: Bicampeón Liga MX 2025 bajo DT Turco Mohamed. Primer DT extranjero con 4 títulos en 4 equipos distintos de Liga MX. Campeones Cup 2025 vs LA Galaxy. Paulinho como fichaje más caro de su historia. | N10: Toluca FC (varonil + Diablas Femenil) · Estadio Nemesio Diez (La Bombonera) · Academia AGA Toluca · Sede WC26 secundaria (entrenamientos selecciones) | P10: [R-13: Propiedad cross-género: el equipo femenil se mapea como propiedad dentro de este actor, no como actor standalone separado.] [v1.00.29: bicampeón Liga MX 2023 + 2024. Operación bajo familia Martínez-Cinta; vínculo histórico con familia Harp Helú (A-059).] | Q10: toluca.com.mx | R10: Verificado | T10: =IF(G10="","",IF(OR(G10="Tier 3"),"No",IF(AND(S10<>"",OR(ISNUMBER(SEARCH("OFAC",S10)),ISNUMBER(SEARCH("penal",S10)),ISNUMBER(SEARCH("rojo pendiente",S10)))),"Revisar","Sí"))) -> Sí
A11: A-025 | B11: V1-006 | C11: Consejo Mundial de Lucha Libre (CMLL) | D11: V1 | E11: V7 | F11: Lucha libre / Wrestling promotion | G11: Tier 2 | H11: México | I11: CDMX + Guadalajara | L11: Lucha libre tradicional, viernes y domingos en Arena México. Empresa más antigua del mundo en su giro. | M11: Cathedral de la lucha libre. Doble venue propio (Arena México + Arena Coliseo GDL). Sin TKO ownership: independiente. | N11: Función Sábado Arena México · Función Domingo Arena Coliseo · Arena Puebla (martes) · Arena Coliseo Guadalajara · Anniversary Show · Sin Salida · Homenaje a Dos Leyendas · Juicio Final · Cuadrilateral CMLL · Reality Estrellas del Ring | O11: Arena México · Arena Coliseo (CDMX) · Arena Puebla · Programación weekly Viernes Espectacular | P11: Federación de lucha libre profesional más antigua del mundo (1933). Opera 3 arenas propias y programación weekly. Distinta de AAA (que está consolidada en Endeavor). [v1.00.29: empresa familiar Roldán desde 1933. Liga propia, opera 4 arenas. Alianza con New Japan Pro Wrestling.] | Q11: cmll.com | R11: Verificado | T11: =IF(G12="","",IF(OR(G12="Tier 3"),"No",IF(AND(S12<>"",OR(ISNUMBER(SEARCH("OFAC",S12)),ISNUMBER(SEARCH("penal",S12)),ISNUMBER(SEARCH("rojo pendiente",S12)))),"Revisar","Sí"))) -> Sí
A12: A-026 | B12: V1-007 | C12: Consejo Municipal del Deporte de Guadalajara (COMUDE GDL) | D12: V1 | E12: V5 · V6 | F12: Institución pública deportiva | G12: Tier 1 | H12: México | I12: Guadalajara, Jalisco | J12: Controla propiedad / capital | K12: Running / Wellness | L12: Rights holder y presidente del comité organizador del Medio Maratón Internacional Guadalajara Electrolit (XL edición 2026: 23,000 participantes, WA Platinum Label, Patrimonio Cultural Inmaterial de Guadalajara) y del Maratón Internacional Guadalajara Skarch (XLI edición 2025: 4,000 participantes). Equivalente funcional al INDEPORTE para la Ciudad de México pero en el ámbito municipal de Guadalajara. | M12: Gatekeeper institucional de los dos eventos de running con mayor convocatoria de Guadalajara. El Medio Maratón GDL Electrolit con WA Platinum Label y 23,000 participantes es más relevante técnicamente que el Maratón CDMX (WA Gold Label). | N12: Rights holder Medio Maratón Internacional Guadalajara Electrolit (WA Platinum Label, Patrimonio Cultural Inmaterial, 23,000 participantes); rights holder Maratón Internacional Guadalajara Skarch | R12: Verificado | T12: =IF(G13="","",IF(OR(G13="Tier 3"),"No",IF(AND(S13<>"",OR(ISNUMBER(SEARCH("OFAC",S13)),ISNUMBER(SEARCH("penal",S13)),ISNUMBER(SEARCH("rojo pendiente",S13)))),"Revisar","Sí"))) -> Sí
A13: A-027 | B13: V1-008 | C13: Copa Mundial FIFA 2026 en México | D13: V1 | E13: V7 · V5 | F13: Evento / Torneo con derechos propios | G13: Tier 1 | H13: Suiza | I13: Ciudad de México / Guadalajara / Monterrey | J13: Controla propiedad / capital | K13: Eventos premium | L13: El evento deportivo más monetizado de la historia celebrado en México. 13 partidos en tres sedes (Banorte-CDMX: 5, Akron-GDL: 4, BBVA-MTY: 4). El partido inaugural (11 jun-2026) enfrenta a México vs Sudáfrica en el Estadio Banorte con 83,000 espectadores. FIFA controla todos los ingresos directos de hospitalidad, ticketing y derechos globales. | M13: Genera la mayor derrama económica de evento deportivo en la historia de México. Restructura todo el ecosistema de sponsors, ticketing, medios y venues durante may-jul 2026. Cataliza USD 3,866M+ en inversión en infraestructura deportiva. | N13: 13 partidos en MX; partido inaugural México vs Sudáfrica (Banorte, 11 jun-2026); USD 3,866M+ inversión infraestructura | Q13: fifa.com/worldcup | R13: Verificado | T13: =IF(G14="","",IF(OR(G14="Tier 3"),"No",IF(AND(S14<>"",OR(ISNUMBER(SEARCH("OFAC",S14)),ISNUMBER(SEARCH("penal",S14)),ISNUMBER(SEARCH("rojo pendiente",S14)))),"Revisar","Sí"))) -> Sí
A14: A-029 | B14: V1-009 | C14: Cruz Azul FC | D14: V1 | E14: V3 · V7 | F14: Club Liga MX | G14: Tier 2 | H14: México | I14: Ciudad de México | J14: Controla propiedad / capital | K14: Fútbol | L14: Modelo de sociedad cooperativa sin dueño único — el único en Liga MX. Busca estadio propio a largo plazo. | M14: Modelo de ownership cooperativo único en Liga MX (sin dueño persona física o empresa). | N14: Sociedad cooperativa única Liga MX · Cruz Azul Femenil (Estadio Centenario Cuernavaca local Clausura 2026) | P14: [R-13: Propiedad cross-género: el equipo femenil se mapea como propiedad dentro de este actor, no como actor standalone separado.] | Q14: cruzazul.com.mx | R14: Verificado | T14: sí
A15: A-043 | B15: V1-010 | C15: Federación Mexicana de Fútbol | D15: V1 | E15: V4 · V3 | F15: Federación deportiva | G15: Tier 1 | H15: México | I15: Ciudad de México | J15: Controla propiedad / capital | K15: Fútbol | L15: Organiza a las selecciones nacionales mexicanas (varonil, femenil, sub-23, sub-20, futsal). Negocia y otorga derechos de transmisión de partidos de la Selección. Certifica árbitros, clubes y competiciones. Opera el CITEC para tecnología deportiva. Comisionado: Mikel Arriola. | M15: Rights holder de la Selección Mexicana de Fútbol, el activo deportivo con mayor valor de patrocinio en México. Sus contratos (Adidas USD 290M/10 años, AT&T telecom exclusivo, Amazon triple deal, TEAM Marketing derechos globales, Netflix Concacaf) definen el piso del ecosistema comercial. | N15: Rights holder El Tri; Adidas USD 290M/10 años hasta 2034; TEAM Marketing derechos globales 2026-34; Genius Sports SAOT | Q15: fmf.mx | R15: Verificado | T15: =IF(G16="","",IF(OR(G16="Tier 3"),"No",IF(AND(S16<>"",OR(ISNUMBER(SEARCH("OFAC",S16)),ISNUMBER(SEARCH("penal",S16)),ISNUMBER(SEARCH("rojo pendiente",S16)))),"Revisar","Sí"))) -> Sí
A16: A-052 | B16: V1-011 | C16: Global Champions Tour — LGCT México | D16: V1 | E16: V3 · V5 | F16: Evento / Torneo con derechos propios | G16: Tier 2 | H16: Otros | I16: Ciudad de México | J16: Controla propiedad / capital | K16: Eventos premium | L16: Organiza la etapa México del Global Champions Tour y la Global Champions League en el Estadio GNP Seguros, CDMX. GNP Seguros como presenting partner desde 2023. Francisco Pasquel/Oxer Sports como promotor local. Contrato extendido hasta 2033. | M16: El único evento ecuestre de élite en México y uno de los más rentables del circuito. La extensión hasta 2033 fue motivada en parte por la llegada de la Premier Jumping League (anunciada mar-abr 2026, inicio 2027) al mercado. | N16: LGCT contrato extendido hasta 2033; GNP Seguros presenting; único ecuestre élite en México | Q16: globalchampionsseries.com | R16: Verificado | T16: =IF(G18="","",IF(OR(G18="Tier 3"),"No",IF(AND(S18<>"",OR(ISNUMBER(SEARCH("OFAC",S18)),ISNUMBER(SEARCH("penal",S18)),ISNUMBER(SEARCH("rojo pendiente",S18)))),"Revisar","Sí"))) -> Sí
A17: A-055 | B17: V1-012 | C17: Gran Premio de México — Fórmula 1 | D17: V1 | E17: V4 · V3 | F17: Evento / Torneo con derechos propios | G17: Tier 1 | H17: Reino Unido | I17: Ciudad de México (Autódromo Hermanos Rodríguez) | J17: Controla propiedad / capital | K17: Motorsport | L17: Contrato extendido abr-2025 para 2026-2028. Fideicomiso privado de ~100 empresas paga fee F1 a Liberty Media (~USD 40-45M/año). Récord 2024: 404,958 asistentes en el fin de semana. Derrama estimada 2025: MXN 20,892M. Costo operativo: ~USD 72M/año. | M17: Evento deportivo más monetizado del país. El único en el mundo con fideicomiso privado multi-empresa para financiar el fee del rights holder. Formula One Group retiene todos los derechos globales de transmisión y hospitality (vía F1 Experiences). | N17: Derrama MXN 137,000M acumulada 2015-2024; récord 404,958 asistentes 2024; fideicomiso privado ~100 empresas | Q17: formula1.com | R17: Verificado | T17: sí
A18: A-075 | B18: V1-013 | C18: INDEPORTE — Instituto del Deporte de la Ciudad de México | D18: V1 | E18: V5 · V6 | F18: Institución pública deportiva | G18: Tier 1 | H18: México | I18: Ciudad de México (Av. División del Norte 2333) | J18: Controla propiedad / capital | K18: Running / Wellness | L18: Rights holder institucional y presidente del comité organizador del Maratón CDMX Telcel (XLIII edición 2026, WA Gold Label, ~30,000 inscritos) y del Medio Maratón CDMX BBVA (XIX edición 2026, AIMS certificado, ~30,000 inscritos). Opera las plataformas de registro oficial (maraton.cdmx.gob.mx y 21k.cdmx.gob.mx). Negocia y otorga los naming rights de los eventos a sponsors. | M18: Controla el inventario comercial de los dos eventos de running más convocados de México: 60,000+ registros combinados. La negociación de title sponsorship (BBVA, Telcel) pasa por INDEPORTE como rights holder. | N18: Rights holder Maratón CDMX Telcel (WA Gold Label); rights holder Medio Maratón CDMX BBVA; plataformas oficiales 21k.cdmx.gob.mx y maraton.cdmx.gob.mx | Q18: indeporte.cdmx.gob.mx | R18: Verificado | T18: =IF(G20="","",IF(OR(G20="Tier 3"),"No",IF(AND(S20<>"",OR(ISNUMBER(SEARCH("OFAC",S20)),ISNUMBER(SEARCH("penal",S20)),ISNUMBER(SEARCH("rojo pendiente",S20)))),"Revisar","Sí"))) -> Sí
A19: A-083 | B19: V1-014 | C19: Liga Mexicana del Pacífico (LMP) | D19: V1 | E19: V2 | F19: Club LMB / Béisbol profesional | G19: Tier 2 | H19: México | I19: Sede LMP (Hermosillo) | K19: Béisbol | L19: Organiza temporada béisbol invernal oct-feb. Campeón clasifica a Serie del Caribe. | M19: Una de las 2 ligas pro de béisbol en MX (junto con LMB verano). Plataforma para Serie del Caribe (representa MX). | N19: LMP temporada invierno (octubre-enero) · Caribbean Series (con Cuba, RD, PR, VEN, Colombia, Panamá) · 10 clubes (Charros, Tomateros, Naranjeros, Yaquis, Águilas, Sultanes Pacífico, Mayos, Cañeros, Venados, Jaiberos) · Acuerdo televisivo ESPN Latin America | P19: [v1.00.29: liga premier de invierno LATAM. Representa MX en Serie del Caribe MLB Pathway. CEO Omar Canizales.] | Q19: lmp.mx | R19: Verificado | T19: =IF(G21="","",IF(OR(G21="Tier 3"),"No",IF(AND(S21<>"",OR(ISNUMBER(SEARCH("OFAC",S21)),ISNUMBER(SEARCH("penal",S21)),ISNUMBER(SEARCH("rojo pendiente",S21)))),"Revisar","Sí"))) -> Sí
A20: A-084 | B20: V1-015 | C20: Liga MX | D20: V1 | E20: V9 · V4 | F20: Evento / Torneo con derechos propios | G20: Tier 1 | H20: México | I20: Ciudad de México | J20: Controla propiedad / capital | K20: Fútbol | L20: Organiza el torneo de fútbol profesional más importante de México. Desde abr-2026 aprobó modelo de gobernanza como AC independiente (23-abr-2026); constitución jurídica formal proyectada para julio 2026 — a mayo-2026 NO está formalmente constituida. Modelo: Premier League / LaLiga. 4 comités estratégicos: Deportivo, Comercial, Inversión, Certificación y Ética. | M20: La separación jurídica FMF-Liga MX es el evento de gobernanza más importante en décadas. Abre ventana real a centralización comercial valorada en USD 480M+ anuales. Gestiona los contratos con BBVA (title), Caliente.mx (casa de apuestas oficial), Genius Sports (datos) y TEAM Marketing (derechos globales selecciones). | N20: Liga BBVA MX varonil (Apertura/Clausura) · Liga MX Femenil (A-151 vía R-06) · Campeón de Campeones · Leagues Cup (con MLS) · eLiga MX (esports oficial) · Liga de Expansión MX (Ascenso suspendido) · Asamblea de Dueños | P20: [v1.00.29: presidente Mikel Arriola. Proceso 2026 de eliminación multipropiedad: Atlas, Querétaro, Mazatlán, León vendidos. Asamblea aprobó llegada Atlante (Escalante).] | Q20: ligamx.net | R20: Verificado | S20: Separación jurídica FMF-Liga MX abr-2026; candidatura Iturbide a presidente (Fuente única) | FECHA CORREGIDA: la asamblea fue el 23-abr-2026 (Asamblea Ordinaria de Dueños, Toluca), no '23-24'. Votación unánime de los 18 clubes confirmada por Reforma, Infobae, El Universal, ESPN. | T20: Sí
A21: A-085 | B21: V1-016 | C21: LIV Golf League (Mexico City) | D21: V1 | E21: V9 · V5 | F21: Evento / Torneo con derechos propios | G21: Tier 2 | H21: Arabia Saudita | I21: Ciudad de México (sede) | J21: Controla propiedad / capital | K21: Eventos premium | L21: Liga premium de golf disruptiva financiada por PIF (Saudi Public Investment Fund). Etapa Mexico City se juega anualmente en el Club de Golf Chapultepec. Primera edición MX 2023, recurrente desde entonces. Modelo de torneo con team play + individual play + premio prize $25M USD por evento. | M21: Único evento premium internacional V1 cuyo control de capital pasa directamente por PIF (V9-021). Su presencia en MX vincula el ecosistema deportivo mexicano con capital soberano saudí. Sede CDMX la convierte en stop premium de golf global cuando PGA Tour MX se juega en Vidanta Vallarta. | N21: LIV Golf México City (Club de Golf Chapultepec) · Anual ene-feb · Etapa LIV Tour Global · Patrocinio HSBC, Aramco, Riyadh Air | P21: Sede operativa Club de Golf Chapultepec; controlado 100% por PIF [v1.00.29: rebautizada en 2024-25 como LIV Golf México (de Mayakoba a Chapultepec). Backers Public Investment Fund Saudi Arabia.] | Q21: livgolf.com | R21: Verificado | T21: =IF(G23="","",IF(OR(G23="Tier 3"),"No",IF(AND(S23<>"",OR(ISNUMBER(SEARCH("OFAC",S23)),ISNUMBER(SEARCH("penal",S23)),ISNUMBER(SEARCH("rojo pendiente",S23)))),"Revisar","Sí"))) -> Sí
A22: A-087 | B22: V1-017 | C22: Maratón de la Ciudad de México Telcel | D22: V1 | E22: V6 | F22: Evento / Torneo con derechos propios | G22: Tier 1 | H22: México | I22: Ciudad de México (salida: CU/UNAM; meta: Zócalo) | J22: Controla audiencia | K22: Running / Wellness | L22: Organiza el maratón de 42K más grande de México por inscritos (~30,000) y el único con etiqueta WA Gold Label en el país. Edición 2026 (XLIII): 30 de agosto, salida desde Insurgentes/CU, meta en el Zócalo. Incluye serial preparatorio de carreras coordinado por INDEPORTE. | M22: Único WA Gold Label de México. Mayor evento de running por masa crítica: 30,000 corredores activos. Telcel lleva más de 10 años como title sponsor. | N22: Único WA Gold Label México; XLIII edición 2026 (30 ago); ~30,000 inscritos; Telcel title sponsor 10+ años; salida CU, meta Zócalo | O22: Maratón anual CDMX (42K) · Eventos satélite (medio maratón, 10K) | P22: Evento operado por INDEPORTE Ciudad de México con title sponsor Telcel. Producción ejecutiva: Emoción Deportiva. | Q22: maraton.cdmx.gob.mx | R22: Verificado | T22: sí
A23: A-088 | B23: V1-018 | C23: Maratón Powerade Monterrey | D23: V1 | E23: V6 | F23: Evento / Torneo con derechos propios | G23: Tier 2 | H23: México | I23: Monterrey, Nuevo León (Parque Fundidora, salida y meta) | J23: Controla audiencia | K23: Running / Wellness | L23: Organiza el segundo maratón de México por número de participantes (8,300 en edición 2025). 42K, certificado AIMS, clasificatorio Boston, aval FMAA e IAAF. 19 ediciones. Title sponsor: Powerade (vía Coca-Cola V3-025). Presentado con Brooks Running México. Operado por comité privado independiente. | M23: El segundo maratón de México por participación. A diferencia del Maratón CDMX (propiedad pública) y el Medio Maratón GDL (propiedad municipal), el Maratón Powerade Monterrey es propiedad de un comité privado: el modelo de acceso para sponsors es distinto. | N23: Segundo maratón de México por participantes (8,300 en 2025); 19 ediciones; AIMS clasificatorio Boston; Powerade title sponsor vía Coca-Cola; Brooks Running México presenting | O23: Maratón Monterrey 42K (anual) | P23: Title sponsor Powerade (The Coca-Cola Company). Operación local Asociación de Atletismo de Nuevo León. | Q23: maratonmonterrey.mx | R23: Verificado | T23: sí
A24: A-092 | B24: V1-019 | C24: Medio Maratón de la Ciudad de México BBVA | D24: V1 | E24: V6 | F24: Evento / Torneo con derechos propios | G24: Tier 1 | H24: México | I24: Ciudad de México (ruta nueva 2026: salida Hemiciclo a Juárez; meta Ángel de la Independencia) | J24: Controla audiencia | K24: Running / Wellness | L24: Organiza el medio maratón de 21K más grande de México por inscritos (~30,000), con certificación AIMS y avales de la FMAA y World Athletics. Expo de 3 días en WTC CDMX (100,000 visitantes en 2025). Edición 2026: XIX, julio 2026. Estrena ruta nueva. | M24: 30,000 corredores inscritos y Expo con 100,000 visitantes convierten al evento en el mayor punto de contacto de marca en running de CDMX por densidad de interacción. BBVA documentado como title sponsor en la ficha V3-001 del tracker. | N24: XIX edición 2026 con ruta nueva; Expo 100,000 visitantes WTC CDMX; BBVA title sponsor; ~30,000 inscritos; AIMS certificado | O24: Medio Maratón CDMX 21K (anual) · Eventos satélite | P24: Title sponsor BBVA. Operación INDEPORTE CDMX. Producción Emoción Deportiva. | Q24: 21k.cdmx.gob.mx | R24: Verificado | T24: sí
A25: A-093 | B25: V1-020 | C25: Medio Maratón Internacional Guadalajara Electrolit | D25: V1 | E25: V6 | F25: Evento / Torneo con derechos propios | G25: Tier 1 | H25: México | I25: Guadalajara, Jalisco (meta: Zona Minerva) | J25: Controla audiencia | K25: Running / Wellness | L25: Organiza el mayor evento de running de Guadalajara: 23,000 participantes (cupo ampliado, inscripciones agotadas en dic-2025), WA Platinum Label (máxima certificación WA, superior al Gold Label del Maratón CDMX), clasificatorio para Campeonato Mundial de Medio Maratón. Patrimonio Cultural Inmaterial del Municipio de Guadalajara. 40 ediciones consecutivas. | M25: El evento de running con mayor certificación técnica de México (Platinum Label vs Gold Label del Maratón CDMX). Electrolit construyó su dominio en el segmento de bebidas deportivas en parte a través del naming de este evento. | N25: WA Platinum Label (único en México); 23,000 participantes, cupo agotado en dic-2025; 40 ediciones; Electrolit title sponsor; Patrimonio Cultural Inmaterial Guadalajara | O25: Medio Maratón GDL 21K (anual) · Eventos satélite | P25: Title sponsor Electrolit (Grupo PiSA). Operación local Comude Guadalajara. | R25: Verificado | S25: | Confirmado: este evento es el referido en correcciones como "21K Guadalajara". Mismo evento, nomenclatura consolidada en "Medio Maratón Internacional Guadalajara Electrolit". | T25: sí
A26: A-098 | B26: V1-021 | C26: Naranjeros de Hermosillo (LMP) | D26: V1 | E26: V7 | F26: Club LMB / Béisbol profesional | G26: Tier 3 | H26: México | I26: Hermosillo | K26: Béisbol | L26: Compite en LMP invernal. Sede Estadio Sonora. | M26: Naranjeros: plurihistórico Serie del Caribe. Tradición LMP Sonora. | N26: Estadio Sonora; Serie del Caribe múltiples | Q26: naranjeros.com.mx | R26: Verificado | T26: =IF(G28="","",IF(OR(G28="Tier 3"),"No",IF(AND(S28<>"",OR(ISNUMBER(SEARCH("OFAC",S28)),ISNUMBER(SEARCH("penal",S28)),ISNUMBER(SEARCH("rojo pendiente",S28)))),"Revisar","Sí"))) -> Sí
A27: A-102 | B27: V1-022 | C27: NFL México City Games | D27: V1 | E27: V3 · V7 | F27: Evento / Torneo con derechos propios | G27: Tier 2 | H27: EUA | I27: Ciudad de México (Estadio Banorte) | J27: Controla propiedad / capital | K27: Eventos premium | L27: Organiza partidos de temporada regular de la NFL en el Estadio Banorte. El acuerdo 2026-2028 confirma al Banorte como venue NFL para tres temporadas consecutivas con los 49ers como equipo local. NFL México City Games 2026 será el primer partido de la NFL en el Estadio Banorte reabierto. | M27: El evento internacional con mayor valor de patrocinio por edición después del GP México. La estructura 2026-2028 con los 49ers ancla al Banorte como venue internacional de primer nivel y valida la inversión de Ollamani/General Atlantic. | N27: Acuerdo 2026-2028 Estadio Banorte con 49ers; Banorte presenting partner NFL México; primer NFL en Banorte reabierto | Q27: nfl.com/international | R27: Verificado | T27: =IF(G30="","",IF(OR(G30="Tier 3"),"No",IF(AND(S30<>"",OR(ISNUMBER(SEARCH("OFAC",S30)),ISNUMBER(SEARCH("penal",S30)),ISNUMBER(SEARCH("rojo pendiente",S30)))),"Revisar","Sí"))) -> Sí
A28: A-115 | B28: V1-023 | C28: Pumas UNAM | D28: V1 | E28: V3 · V7 | F28: Club Liga MX | G28: Tier 2 | H28: México | I28: Ciudad de México | J28: Controla propiedad / capital | K28: Fútbol | L28: Su identidad y base de fans CDMX son su principal activo comercial. | M28: Único club Liga MX de propiedad pública universitaria. Base de fans universitaria en la capital. | N28: Propiedad UNAM; Estadio Olímpico Universitario patrimonio UNESCO; identidad universitaria única · Pumas UNAM Femenil | P28: [R-13: Propiedad cross-género: el equipo femenil se mapea como propiedad dentro de este actor, no como actor standalone separado.] | Q28: pumasfútbol.mx | R28: Verificado | T28: =IF(G33="","",IF(OR(G33="Tier 3"),"No",IF(AND(S33<>"",OR(ISNUMBER(SEARCH("OFAC",S33)),ISNUMBER(SEARCH("penal",S33)),ISNUMBER(SEARCH("rojo pendiente",S33)))),"Revisar","Sí"))) -> No
A29: A-123 | B29: V1-024 | C29: Selección Mexicana de Fútbol | D29: V1 | E29: V7 · V3 | F29: Selección nacional | G29: Tier 1 | H29: México | I29: Ciudad de México | J29: Controla propiedad / capital | K29: Fútbol | L29: Compite internacionalmente en FIFA, CONCACAF y eventos de preparación. Genera el mayor volumen de audiencia puntual del ecosistema deportivo mexicano. Sus partidos de clasificación mundialista, amistosos y participaciones en Copa Oro y Copa América son el producto con mayor demanda de patrocinio del mercado. | M29: La SNM es el activo de mayor concentración de patrocinios en un solo producto deportivo de México: Adidas (kit USD 290M/10 años), AT&T (telecom exclusivo), Amazon (triple deal mar-2025), Caliente.mx (oct-2025), Maggi/Nestlé, Uber/Uber Eats, Coca-Cola. Co-anfitrión WC26: sede inaugural en Estadio Banorte (partido México-Sudáfrica, 11 jun-2026). | N29: Selección Mexicana Mayor varonil (El Tri) · Selecciones juveniles Sub-15/Sub-17/Sub-20/Sub-23 · Tour por EE.UU. via SUM (6 fuegos/año hasta 2028) · Patrocinio adidas kit (extensión hasta 2034) · Sede WC26 país anfitrión (Banorte, BBVA, Akron + Coliseo GNP Zapopan) | P29: [v1.00.29: bajo FMF (A-043). DT Javier Aguirre. Selección juega 3-de-cada-4 partidos en EE.UU. desde 2023 vía contrato SUM hasta 2028.] | Q29: fmf.mx | R29: Verificado | T29: =IF(G34="","",IF(OR(G34="Tier 3"),"No",IF(AND(S34<>"",OR(ISNUMBER(SEARCH("OFAC",S34)),ISNUMBER(SEARCH("penal",S34)),ISNUMBER(SEARCH("rojo pendiente",S34)))),"Revisar","Sí"))) -> No
A30: A-124 | B30: V1-025 | C30: Selección Mexicana Femenil | D30: V1 | E30: V3 · V4 | F30: Selección nacional | G30: Tier 2 | H30: México | I30: Ciudad de México | J30: Controla propiedad / capital | K30: Fútbol | L30: Genera el inventario comercial del segmento femenil del ecosistema deportivo mexicano junto con la Liga MX Femenil. Amazon, AT&T y Scotiabank firmaron acuerdos específicos de patrocinio femenil. | M30: Activo con crecimiento acelerado de patrocinios femeniles. El triple deal Amazon incluye Liga MX Femenil. Scotiabank pivotó a ecosistema femenil Concacaf + Chivas fuerzas básicas. Primera Sub-20 femenil clasificada a Mundial Sub-20 en dos ediciones. | N30: Triple deal Amazon (Tri + Liga MX + Liga MX Femenil); Scotiabank pivot femenil; crecimiento acelerado patrocinios | Q30: fmf.mx | R30: Verificado | T30: =IF(G35="","",IF(OR(G35="Tier 3"),"No",IF(AND(S35<>"",OR(ISNUMBER(SEARCH("OFAC",S35)),ISNUMBER(SEARCH("penal",S35)),ISNUMBER(SEARCH("rojo pendiente",S35)))),"Revisar","Sí"))) -> Sí
A31: A-133 | B31: V1-026 | C31: Sultanes de Monterrey (LMB) | D31: V1 | E31: V7 | F31: Club LMB / Béisbol profesional | G31: Tier 2 | H31: México | I31: Monterrey | K31: Béisbol | L31: Compite en LMB. Sede Estadio Monterrey con naming Walmart desde 2024. | M31: Sultanes: institución LMB norte. Único naming Walmart en deporte profesional MX. | N31: Sultanes Monterrey LMB Banorte (varonil verano) · Sultanes Monterrey Softball (LMS femenil) · Estadio Mobil Super (Palacio Sultán) · Academia formativa · Calendario 87 ediciones LMB | O31: Walmart Park | P31: 1 propiedades absorbidas. Control operativo verificado en auditoría Padres/Hijos v3. Walmart Park: dueño legal Walmart México, operación Sultanes vía concesión. [v1.00.29: doble franquicia LMB beisbol + LMS softball. Estadio renombrado Mobil Super (ex Walmart Park). Bajo familia Maíz / Grupo Pesa.] | Q31: sultanes.com.mx | R31: Verificado | T31: sí
A32: A-138 | B32: V1-027 | C32: Tomateros de Culiacán (LMP) | D32: V1 | E32: V7 | F32: Club LMB / Béisbol profesional | G32: Tier 3 | H32: México | I32: Culiacán | K32: Béisbol | L32: Compite en LMP invernal. Sede Estadio Tomateros. | M32: Tomateros: equipo más popular invernal Sinaloa. Campeón LMP recurrente. | N32: Estadio Tomateros; campeones LMP múltiples | Q32: tomaterosdeculiacan.com | R32: Verificado | T32: =IF(G38="","",IF(OR(G38="Tier 3"),"No",IF(AND(S38<>"",OR(ISNUMBER(SEARCH("OFAC",S38)),ISNUMBER(SEARCH("penal",S38)),ISNUMBER(SEARCH("rojo pendiente",S38)))),"Revisar","Sí"))) -> Sí
A33: A-139 | B33: V1-028 | C33: Toros de Tijuana (LMB) | D33: V1 | E33: V7 · V3 | F33: Club LMB / Béisbol profesional | G33: Tier 3 | H33: México | I33: Tijuana | K33: Béisbol | L33: Compite en LMB. Sede Estadio Chevron (naming desde 2018). | M33: Toros Tijuana: única franquicia LMB frontera norte. Naming Chevron. | N33: Estadio Chevron desde 2018 | Q33: torosdetijuana.com | R33: Verificado | T33: =IF(G39="","",IF(OR(G39="Tier 3"),"No",IF(AND(S39<>"",OR(ISNUMBER(SEARCH("OFAC",S39)),ISNUMBER(SEARCH("penal",S39)),ISNUMBER(SEARCH("rojo pendiente",S39)))),"Revisar","Sí"))) -> Sí
A34: A-141 | B34: V1-029 | C34: Venados de Mazatlán (LMP) | D34: V1 | E34: V7 | F34: Club LMB / Béisbol profesional | G34: Tier 3 | H34: México | I34: Mazatlán | K34: Béisbol | L34: Compite en LMP invernal. Sede Estadio Teodoro Mariscal. | M34: Venados: plurihistórico Serie del Caribe. Tradición LMP Sinaloa. | N34: Serie del Caribe múltiples; Estadio Teodoro Mariscal | Q34: venados.com.mx | R34: Verificado | T34: =IF(G40="","",IF(OR(G40="Tier 3"),"No",IF(AND(S40<>"",OR(ISNUMBER(SEARCH("OFAC",S40)),ISNUMBER(SEARCH("penal",S40)),ISNUMBER(SEARCH("rojo pendiente",S40)))),"Revisar","Sí"))) -> Sí
A35: A-143 | B35: V1-030 | C35: Victum Sports México (HYROX México) | D35: V1 | E35: V5 | F35: Evento / Torneo con derechos propios | G35: Tier 2 | H35: México | I35: Ciudad de México (Santa Fe) | J35: Controla propiedad / capital | K35: Running / Wellness | L35: Organiza y opera la serie de eventos HYROX en México bajo licencia exclusiva de HYROX World GmbH (Hamburgo). Temporada 2025/2026: 6 eventos en 6 ciudades (CDMX, GDL, MTY, Acapulco, Cancún, Puebla). Gestiona la relación con gimnasios gym partner locales. 152,000 seguidores en Instagram (@hyroxmx). Licencia exclusiva M: Victum es rights holder mexicano por contrato con HYROX World GmbH. | M35: HYROX es el formato de fitness competitivo de mayor crecimiento global post-2020. Victum llevó HYROX a México de la misma forma que lo hizo en España: primero licencia exclusiva, luego escalado de eventos. Smart Fit como naming partner de toda la temporada. | N35: Licenciatario exclusivo HYROX en México (y previamente Iberia); 6 eventos/temporada en 6 ciudades; Smart Fit como naming partner temporada 25/26; fundadores Álvaro Taracena y Jan Peters; RFC: VSM240815SP6 | O35: HYROX México | P35: 1 propiedades absorbidas. Control operativo verificado en auditoría Padres/Hijos v3. | Q35: hyrox.mx | R35: Verificado | T35: =IF(G41="","",IF(OR(G41="Tier 3"),"No",IF(AND(S41<>"",OR(ISNUMBER(SEARCH("OFAC",S41)),ISNUMBER(SEARCH("penal",S41)),ISNUMBER(SEARCH("rojo pendiente",S41)))),"Revisar","Sí"))) -> No
A36: A-147 | B36: V1-031 | C36: World Boxing Council (WBC) — sede CDMX | D36: V1 | F36: Federación deportiva | G36: Tier 2 | H36: México | I36: CDMX (sede) | K36: Boxeo | L36: Sancionar peleas y rankings boxeo profesional mundial. Otorga cinturón verde WBC. | M36: Una de las 4 federaciones principales mundo (WBC, WBA, IBF, WBO). Sede CDMX desde 1963. Mauricio Sulaimán presidente. | N36: World Boxing Council titulación · Convention anual · Diploma y cinturón verde-oro · Rankings mundiales · WBC Cares (fundación) · WBC Muay Thai · WBC MMA · sede oficial Ciudad de México | O36: Sanción peleas título WBC · Convenciones anuales · Programa Clean Boxing | P36: Organismo regulador internacional de boxeo, sede en CDMX. Mauricio Sulaimán presidente. Sanciona ~70% de peleas profesionales globales. [v1.00.29: presidente Mauricio Sulaimán Saldívar. Único de los 4 sancionadores con sede MX (vs WBA/IBF/WBO).] | Q36: wbcboxing.com | R36: Verificado | T36: =IF(G42="","",IF(OR(G42="Tier 3"),"No",IF(AND(S42<>"",OR(ISNUMBER(SEARCH("OFAC",S42)),ISNUMBER(SEARCH("penal",S42)),ISNUMBER(SEARCH("rojo pendiente",S42)))),"Revisar","Sí"))) -> Sí
A37: A-150 | B37: V1-032 | C37: Kings League Mexico (ex Kings League Americas) / Kings League Openbank Mexico | D37: V1 | E37: V2 · V6 | F37: Evento / Torneo con derechos propios | G37: Tier 2 | H37: España (Kosmos / Gerard Piqué) | I37: Ciudad de México (Cupra Arena, MX) + Estadio BBVA (Final Four 2025) | J37: Produce y comercializa torneo | K37: Fútbol 7 / Esports / Creator economy | L37: Liga de fútbol 7-vs-7 fundada por Gerard Piqué en 2022. Edición Americas / Mexico debutó ene-2024 con 12 equipos presididos por streamers y futbolistas (Miguel Layún presidente). Sponsors confirmados: Santander/Openbank (title), Bimbo, Sportium, McDonalds, Adidas. Broadcasters MX: Twitch, YouTube, Televisa, ESPN/Disney+. Final Four 2025 en Estadio BBVA (Porcinos FC campeón). Para 2026 DAZN compró rights globales solo en mercados específicos (Spain, Italy, Germany domestic), no MX directamente. | M37: Modelo creator-led + digital-first sin precedente en MX: bypass del ecosistema Liga MX clásico, captación de audiencia joven via Twitch/YouTube. Caso de uso para Gustavo en V6 (whitelabel ticketing, vínculo FANKI a verificar) y V2 (modelo digital-first sin TV tradicional dominante). | N37: Kings League Americas (rebrand Mexico 2025) · Openbank/Santander title · Piqué/Kosmos founder · Layún Pres. MX · Final Four BBVA Monterrey | O37: Liga propia (rights holder) | P37: Holding global Kosmos Sports & Gerard Piqué. Operación local con licenciatarios y sponsors regionales. CEO global Kings League: Djamel Agaoua. Presidente liga MX/Americas: Miguel Layún. | Q37: kingsleague.pro/en/americas | R37: Verificado | T37: Sí
A38: A-151 | B38: V1-033 | C38: Liga BBVA MX Femenil | D38: V1 | E38: V2 | F38: Federación deportiva | G38: Tier 1 | H38: México | I38: Ciudad de México | J38: Empaqueta competición | K38: Fútbol femenil | L38: Liga MX Femenil (oficialmente Liga BBVA MX Femenil) fundada en 2017, asociación de miembros con 18 clubes que reflejan la estructura de la Liga MX varonil. Aplica regla R-06/E-02 (membresía constitutiva, no absorción) y R-13 (clubes femeniles como propiedades dentro de holdings existentes). En el workbook 17 de 18 clubes femeniles se cubren vía herencia desde el holding o club varonil padre ya mapeado; FC Juárez Bravas se excluye bajo E-07 (huérfano sin contraparte varonil mapeada, propietario Grupo Multimedios no figura en UM). Naming sponsor BBVA. Régimen de derechos centralizado vs Liga MX varonil (caso por revisar bajo M-AF-05). En contexto Mundial Femenino 2027 co-anfitrión MX-USA, el activo crece en relevancia. | M38: Activo en alza pre-Mundial Femenino 2027 (MX co-anfitrión confirmado). Régimen de derechos televisivos y comerciales tiene espacio para centralización (decisión Asamblea pendiente). Caso V1 con potencial de crecimiento en visibilidad para todos los holdings padres ya mapeados. | N38: Liga BBVA MX Femenil · 17 clubes-miembros cubiertos vía herencia de holdings (R-13) · FC Juárez Bravas excluida (E-07) · Sponsor titular BBVA · Mundial Femenino 2027 catalizador | O38: Asociación de miembros (no holding, regla R-06) | P38: Asociación de miembros bajo el paraguas de FMF y Liga MX AC. Los 18 clubes son miembros (no hijos consolidados). Aplica R-06 (membresía no absorción), E-02 (excepción Liga MX vs clubes), R-13 (propiedades cross-género en holdings) y E-07 (exclusión femeniles huérfanos). 17 de 18 clubes mapeados vía herencia de actores padre existentes. | Q38: ligamxfemenil.net | R38: Verificado | T38: Sí
A39: A-004 | B39: V2-001 | C39: Amazon Prime Video | D39: V2 | E39: V1 · V3 | F39: Plataforma streaming | G39: Tier 2 | H39: EUA | I39: Ciudad de México | J39: Controla audiencia | K39: Fútbol | L39: Primer OTT global con acuerdo exclusivo de un club Liga MX. También firmó triple deal de patrocinio (Tri + Liga MX + Liga MX Femenil) desde mar-2025 vía Amazon/AWS. NBA y NFL TNF en Prime Video México. | M39: El acuerdo Chivas-Amazon reescribió el modelo de broadcasting local y fijó un benchmark que presiona al alza todos los contratos club-por-club. El triple deal de patrocinio inauguró la era del tech-as-sponsor en el ecosistema. | N39: Segunda plataforma de streaming mas grande en el mundo. | Q39: primevideo.com | R39: Verificado | S39: https://www.aboutamazon.mx/noticias/entretenimiento/amazon-prime-chivas-guadalajara | T39: =IF(G39="","",IF(OR(G39="Tier 3"),"No",IF(AND(S39<>"",OR(ISNUMBER(SEARCH("OFAC",S39)),ISNUMBER(SEARCH("penal",S39)),ISNUMBER(SEARCH("rojo pendiente",S39)))),"Revisar","Sí"))) -> Sí
A40: A-006 | B40: V2-002 | C40: Apple TV (Leagues Cup MLS-Liga MX) | D40: V2 | E40: V1 · V4 | F40: Plataforma streaming | G40: Tier 2 | H40: EUA | I40: Sin base operativa permanente MX | J40: Controla audiencia | K40: Fútbol | L40: Broadcaster exclusivo de la Leagues Cup (torneo MLS vs Liga MX) en EE.UU. y México desde 2023. Apple TV capturó el torneo crossborder más relevante del fútbol norteamericano. Modelo de suscripción sin publicidad. | M40: La Leagues Cup bajo Apple TV representa el primer acuerdo de gran escala de un tech giant en el fútbol de liga de la región. El acceso bajo paywall fragmenta la audiencia del torneo más relevante del fútbol binacional. | N40: Stremer De Apple | Q40: tv.apple.com | R40: Verificado | S40: https://mexico.as.com/futbol/futbol-mexicano/leagues-cup-transmitira-a-traves-de-apple-tv-en-mexico-n/ | T40: =IF(G40="","",IF(OR(G40="Tier 3"),"No",IF(AND(S40<>"",OR(ISNUMBER(SEARCH("OFAC",S40)),ISNUMBER(SEARCH("penal",S40)),ISNUMBER(SEARCH("rojo pendiente",S40)))),"Revisar","Sí"))) -> Sí
A41: A-011 | B41: V2-003 | C41: Better Collective / Futbol Sites / Bolavip | D41: V2 | E41: V2 · V4 | F41: Medio digital deportivo | G41: Tier 3 | H41: Otros | I41: Ciudad de México / Buenos Aires | J41: Controla audiencia | K41: Fútbol | L41: Better Collective adquirió Futbol Sites (que incluye Bolavip, Transfermarkt LatAm, y otros portales nativos digitales) para construir la mayor red de media deportiva nativa digital de LatAm. Bolavip como portal de contenido fútbol en español. | M41: Único nativo digital con escala industrial en LatAm. La integración Better Collective-Futbol Sites crea el mayor portafolio de media deportiva digital en español de la región. | N41: Único nativo digital escala industrial LatAm; Better Collective (BETCO) dueño; Bolavip + Futbol Sites | Q41: bolavip.com · bettercollective.com | R41: Verificado | T41: =IF(G41="","",IF(OR(G41="Tier 3"),"No",IF(AND(S41<>"",OR(ISNUMBER(SEARCH("OFAC",S41)),ISNUMBER(SEARCH("penal",S41)),ISNUMBER(SEARCH("rojo pendiente",S41)))),"Revisar","Sí"))) -> No
A42: A-014 | B42: V2-004 | C42: Box to Box Films (LATAM operations) | D42: V2 | F42: Productora de contenido deportivo | G42: Tier 2 | H42: Reino Unido | I42: Londres + MX (LATAM) | L42: Productora detrás de F1 Drive to Survive. Partnership exclusivo mundial con Canelo Media. | M42: Definió el storytelling sports moderno. Trae estándar premium a LATAM via Canelo Media. | N42: Drive to Survive (F1, Netflix) · Six Nations: Full Contact (rugby) · Sprint (atletismo) · The Test (cricket) · Operaciones LATAM con producción deportiva premium · Acuerdos con F1 y otras propiedades | P42: [v1.00.29: productora docu-series deportivas estilo "Drive to Survive". Ampliando operaciones LATAM con foco MX como mercado emisor + sede de eventos F1.] | Q42: boxtoboxfilms.com | R42: Verificado | T42: =IF(G42="","",IF(OR(G42="Tier 3"),"No",IF(AND(S42<>"",OR(ISNUMBER(SEARCH("OFAC",S42)),ISNUMBER(SEARCH("penal",S42)),ISNUMBER(SEARCH("rojo pendiente",S42)))),"Revisar","Sí"))) -> Sí
A43: A-031 | B43: V2-005 | C43: DAZN México | D43: V2 | E43: V1 · V4 | F43: Plataforma streaming | G43: Tier 2 | H43: Reino Unido | I43: Ciudad de México (operación) | J43: Controla audiencia | K43: Eventos premium | L43: Broadcaster exclusivo de Canelo Álvarez en México y EE.UU. Derechos de boxeo premium global. Adquirió sublicencia del FIFA Club World Cup 2025 de TelevisaUnivision. DAZN es el único OTT con distribución exclusiva del activo deportivo individual más valioso de México. | M43: Sin Canelo, DAZN pierde su producto premium en México. El activo Canelo generó más de USD 160M por pelea en PPV en EE.UU. Único broadcaster que rompe la dicotomía TUDN/FOX/Amazon en el mercado premium. | N43: Broadcaster exclusivo Canelo Álvarez; >USD 160M por pelea Canelo; boxeo premium global | Q43: dazn.com | R43: Verificado | S43: [P6-E P6-DT] Vis=Sí pero sin R1/R2 cargadas. Pendiente de carga en próximo ciclo. Conservar visualizable porque es benchmark relevante para Aldo (revisar caso a caso). | T43: =IF(G44="","",IF(OR(G44="Tier 3"),"No",IF(AND(S44<>"",OR(ISNUMBER(SEARCH("OFAC",S44)),ISNUMBER(SEARCH("penal",S44)),ISNUMBER(SEARCH("rojo pendiente",S44)))),"Revisar","Sí"))) -> Sí
A44: A-036 | B44: V2-006 | C44: ESPN / Disney+ México | D44: V2 | E44: V1 · V3 | F44: Broadcaster TV de paga | G44: Tier 2 | H44: EUA | I44: Ciudad de México (operación LatAm) | J44: Controla audiencia | K44: Multideporte | L44: ESPN como canal deportivo de TV de paga con derechos de Liga MX (algunos clubes), NBA México, NFL y Champions League (a partir de 2027). Bundle ViX+Disney+ desde jun-2025 (MXN 199/mes) crea nueva sinergia con TelevisaUnivision en el mercado mexicano. | M44: Bundle ViX+Disney+ es la alianza de distribución más relevante del ecosistema streaming en México 2025-2026. ESPN retiene derechos deportivos premium que complementan el portafolio de ViX. | N44: Bundle ViX+Disney+ (jun-2025); derechos NBA, NFL, Champions League; ESPN canal deportivo TV de paga | Q44: espn.com.mx · disneyplus.com | R44: Verificado | T44: =IF(G45="","",IF(OR(G45="Tier 3"),"No",IF(AND(S45<>"",OR(ISNUMBER(SEARCH("OFAC",S45)),ISNUMBER(SEARCH("penal",S45)),ISNUMBER(SEARCH("rojo pendiente",S45)))),"Revisar","Sí"))) -> Sí
A45: A-047 | B45: V2-007 | C45: Fox Corporation / FOX One / Tubi México | D45: V2 | E45: V1 · V3 | F45: Broadcaster TV de paga | G45: Tier 1 | H45: EUA | I45: Ciudad de México (operación MX) | J45: Controla audiencia | K45: Multideporte | L45: Entró directamente al mercado mexicano comprando Caliente TV (jun-2025). Opera triple stack: Tubi México (AVOD, hereda audiencia Caliente TV), FOX One (SVOD, derechos Liga MX: Pachuca, Tigres, Juárez, Mazatlán y otros), canal lineal. Reemplaza a Fox Sports México/Lauman que colapsa entre multas y pérdida de licencia. | M45: El tercer actor en tamaño del ecosistema de medios deportivos mexicano. Su entrada vía Caliente TV (jun-2025) reconfiguró el mapa de derechos de Liga MX en TV de paga. La sinergia FOX-Caliplay (apuestas) es la primera integración media-apuestas del ecosistema. | N45: Compra Caliente TV jun-2025; triple stack Tubi+FOX One+lineal; derechos Pachuca, Tigres, Juárez; sinergia media-apuestas con Caliplay | Q45: foxcorporation.com · foxone.mx · tubitv.com | R45: Verificado | T45: =IF(G47="","",IF(OR(G47="Tier 3"),"No",IF(AND(S47<>"",OR(ISNUMBER(SEARCH("OFAC",S47)),ISNUMBER(SEARCH("penal",S47)),ISNUMBER(SEARCH("rojo pendiente",S47)))),"Revisar","Sí"))) -> No
A46: A-048 | B46: V2-008 | C46: Fox Sports México / Grupo Lauman | D46: V2 | E46: V2 · V1 | F46: Broadcaster TV de paga | G46: Tier 3 | H46: México | I46: Ciudad de México | J46: Controla audiencia | K46: Fútbol | L46: Canal deportivo de TV de paga que operó como brazo de distribución de Fox Sports LatAm en México. En proceso de salida del mercado (nov-2026) tras multas de la autoridad regulatoria y pérdida de la licencia de marca Fox Sports ante el avance directo de Fox Corporation (Tubi/FOX One). | M46: Su desaparición reordena el mapa de TV de paga deportiva en México, acelerando la concentración en TUDN/ViX, Amazon, Netflix y Fox Corporation directa. | N46: Canal en colapso nov-2026; multas regulatorias; desplazado por Fox Corporation directa (Tubi + FOX One) | Q46: foxsports.mx | R46: Verificado | S46: En colapso — salida del mercado estimada nov-2026. Multas y pérdida licencia de marca Fox Sports. Desplazado por Fox Corporation directa. | T46: =IF(G48="","",IF(OR(G48="Tier 3"),"No",IF(AND(S48<>"",OR(ISNUMBER(SEARCH("OFAC",S48)),ISNUMBER(SEARCH("penal",S48)),ISNUMBER(SEARCH("rojo pendiente",S48)))),"Revisar","Sí"))) -> No
A47: A-090 | B47: V2-009 | C47: Max / HBO Max Warner Bros. Discovery | D47: V2 | E47: V1 · V4 | F47: Plataforma streaming | G47: Tier 3 | H47: EUA | I47: Sin base operativa permanente MX | J47: Controla audiencia | K47: Fútbol | L47: Uno de los broadcasters de la UEFA Champions League en México (compartida). Derechos europeos de fútbol de clubes como ancla deportiva en el mercado mexicano. | M47: La Champions League es el producto europeo con mayor audiencia en México. Max compite con ESPN/Disney+ en el segmento de fútbol europeo de élite. | N47: UEFA Champions League compartida en MX; WBD como broadcaster europeo de élite | Q47: max.com | R47: Verificado | T47: =IF(G49="","",IF(OR(G49="Tier 3"),"No",IF(AND(S49<>"",OR(ISNUMBER(SEARCH("OFAC",S49)),ISNUMBER(SEARCH("penal",S49)),ISNUMBER(SEARCH("rojo pendiente",S49)))),"Revisar","Sí"))) -> Sí
A48: A-094 | B48: V2-010 | C48: Mediotiempo | D48: V2 | E48: V2 | F48: Medio digital deportivo | G48: Tier 3 | H48: México | I48: Monterrey, Nuevo León | J48: Controla audiencia | K48: Fútbol | L48: Portal deportivo digital con enfoque en fútbol mexicano. Fuente de referencia editorial para el ecosistema. Propiedad compartida entre Grupo Multimedios (noreste) y Milenio. | M48: Referente editorial digital del ecosistema deportivo mexicano. Fuente primaria de cobertura de Liga MX para audiencias digitales. | N48: Portal deportivo referente Liga MX; propiedad Multimedios-Milenio; audiencia digital masiva | Q48: mediotiempo.com | R48: Verificado | T48: =IF(G50="","",IF(OR(G50="Tier 3"),"No",IF(AND(S50<>"",OR(ISNUMBER(SEARCH("OFAC",S50)),ISNUMBER(SEARCH("penal",S50)),ISNUMBER(SEARCH("rojo pendiente",S50)))),"Revisar","Sí"))) -> No
A49: A-100 | B49: V2-011 | C49: Netflix México | D49: V2 | E49: V1 · V3 | F49: Plataforma streaming | G49: Tier 2 | H49: EUA | I49: Ciudad de México | J49: Controla audiencia | K49: Fútbol | L49: Firmó el 14 de abril de 2026 el primer acuerdo exclusivo país-México con Concacaf: Copa Oro y Nations League Finals 2027-2029. Coloca a la Selección Mexicana detrás de paywall en torneos masivos por primera vez en la historia. VP Carolina Leconte como arquitecta del deal. | M49: El deal Netflix-Concacaf es el evento de disrupción más reciente del ecosistema de medios deportivos mexicano. Pone la Selección Mexicana (en torneos CONCACAF) detrás de paywall por primera vez, forzando al aficionado a suscribirse o perder acceso. | N49: Primer deal deportivo exclusivo Concacaf en MX (abr-2026); Copa Oro + Nations League Finals 2027-29; El Tri detrás de paywall CONCACAF | Q49: netflix.com | R49: Verificado | T49: =IF(G52="","",IF(OR(G52="Tier 3"),"No",IF(AND(S52<>"",OR(ISNUMBER(SEARCH("OFAC",S52)),ISNUMBER(SEARCH("penal",S52)),ISNUMBER(SEARCH("rojo pendiente",S52)))),"Revisar","Sí"))) -> No
A50: A-109 | B50: V2-012 | C50: Paramount+ / Pluto TV | D50: V2 | E50: V1 · V5 | F50: Plataforma streaming | G50: Tier 3 | H50: EUA | I50: Sin base operativa permanente MX | J50: Controla audiencia | K50: Eventos premium | L50: Broadcaster exclusivo de UFC en Latinoamérica desde oct-2025. La alianza UFC-Paramount+ desplazó a ESPN/Disney como broadcaster de las peleas en México. Pluto TV como canal AVOD gratuito complementario. | M50: El deal UFC-Paramount+ reconfiguró el mapa de derechos de MMA en LatAm. Paramount+ posiciona a UFC como su ancla deportiva en la región. | N50: UFC LatAm exclusivo desde oct-2025; desplazó a ESPN/Disney en MMA; Pluto TV AVOD gratuito | Q50: paramountplus.com · pluto.tv | R50: Verificado | T50: =IF(G53="","",IF(OR(G53="Tier 3"),"No",IF(AND(S53<>"",OR(ISNUMBER(SEARCH("OFAC",S53)),ISNUMBER(SEARCH("penal",S53)),ISNUMBER(SEARCH("rojo pendiente",S53)))),"Revisar","Sí"))) -> Sí
A51: A-118 | B51: V2-013 | C51: Récord | D51: V2 | E51: V2 | F51: Medio digital deportivo | G51: Tier 3 | H51: México | I51: Ciudad de México | J51: Controla audiencia | K51: Fútbol | L51: Diario deportivo de referencia en México. Cobertura especializada de fútbol, boxeo y otros deportes. Combina presencia impresa y digital. | M51: Referente editorial deportivo en CDMX. Fuente primaria de noticias de transferencias y mercado para el ecosistema. | N51: Diario deportivo referente CDMX; fuente primaria mercado transferencias; Grupo Notmusa | Q51: record.com.mx | R51: Verificado | T51: =IF(G56="","",IF(OR(G56="Tier 3"),"No",IF(AND(S56<>"",OR(ISNUMBER(SEARCH("OFAC",S56)),ISNUMBER(SEARCH("penal",S56)),ISNUMBER(SEARCH("rojo pendiente",S56)))),"Revisar","Sí"))) -> Sí
A52: A-127 | B52: V2-014 | C52: Sky Sports México / NBCUniversal | D52: V2 | E52: V1 · V3 | F52: Broadcaster TV de paga | G52: Tier 3 | H52: EUA / México | I52: Ciudad de México | J52: Controla audiencia | K52: Motorsport | L52: Broadcaster de Fórmula 1 en México desde el GP de Singapur 2025 hasta 2028. El acuerdo fue ganado en el ciclo de renovación de derechos de F1 en el mercado latinoamericano. | M52: Único broadcaster de F1 con cobertura completa del Gran Premio de México 2025-2028. Compite con la distribución libre de F1 en plataformas digitales. | N52: Derechos F1 México 2025-2028 desde GP Singapur; único broadcaster TV paga F1 MX | Q52: sky.com.mx | R52: Verificado | T52: =IF(G57="","",IF(OR(G57="Tier 3"),"No",IF(AND(S57<>"",OR(ISNUMBER(SEARCH("OFAC",S57)),ISNUMBER(SEARCH("penal",S57)),ISNUMBER(SEARCH("rojo pendiente",S57)))),"Revisar","Sí"))) -> Sí
A53: A-137 | B53: V9-024 | C53: TelevisaUnivision | D53: V2 | E53: V9 | F53: Holding diversificado | G53: Tier 2 | H53: EUA / México | I53: Ciudad de México / Nueva York | J53: Controla audiencia | K53: Fútbol | L53: Sin participaciones accionarias en clubes Liga MX ni en la liga. Solo derechos de transmisión vía TUDN, Canal 5 y N9ve (7 equipos Liga MX). Renovó derechos NFL México feb-2026. Streaming Liga MX vía ViX (stack Akta). | M53: Como broadcaster de 7 de los 18 clubes Liga MX, su estructura de derechos fragmentada es el obstáculo principal para la centralización comercial. La crisis TV Azteca (concurso mercantil) puede forzar una redistribución de derechos que beneficie a TelevisaUnivision. | N53: TUDN/ViX 7 clubes Liga MX · Sin equity en clubes · Renovación derechos NFL México feb-2026 | O53: izzi · Gran Fondo Adolfo Lagos izzi Kardias · TUDN / ViX | P53: 3 propiedades absorbidas. izzi: 100% accionario | Q53: televisaunivision.com | R53: Verificado | T53: =IF(G59="","",IF(OR(G59="Tier 3"),"No",IF(AND(S59<>"",OR(ISNUMBER(SEARCH("OFAC",S59)),ISNUMBER(SEARCH("penal",S59)),ISNUMBER(SEARCH("rojo pendiente",S59)))),"Revisar","Sí"))) -> Sí
A54: A-148 | B54: V2-015 | C54: YouTube (Alphabet/Google) | D54: V2 | E54: V8 | F54: Plataforma streaming | G54: Tier 1 | H54: Otros | I54: Global | L54: Distribución contenido video globalmente. Canales oficiales clubes Liga MX. Highlights, fan content. Transmisión de FutFem Donde Sea de la Liga MX Femenil | M54: Plataforma #1 video mundo. NFL Sunday Ticket. En MX: canales clubes, contenido user-generated, YouTube TV. | N54: YouTube plataforma · YouTube TV · YouTube Premium · YouTube Music · YouTube Shorts · YouTube CMS para rights holders · Acuerdos de rights con Kings League (transmisión oficial canal Twitch+YouTube) · Programas verificados con marcas deportivas | P54: [v1.00.29: subsidiaria de Alphabet/Google. Principal canal de distribución para creator-led leagues (Kings League MX) y contenido fan-made deportes.] | Q54: youtube.com | R54: Verificado | T54: =IF(G60="","",IF(OR(G60="Tier 3"),"No",IF(AND(S60<>"",OR(ISNUMBER(SEARCH("OFAC",S60)),ISNUMBER(SEARCH("penal",S60)),ISNUMBER(SEARCH("rojo pendiente",S60)))),"Revisar","Sí"))) -> Sí
A55: A-001 | B55: V3-001 | C55: adidas | D55: V3 | E55: V1 · V3 | F55: Marca / Sponsor corporativo | G55: Tier 1 | H55: Alemania | I55: Ciudad de México (operación MX) | J55: Pone dinero | K55: Fútbol | L55: Renovó con FMF hasta 2034 (10 años, USD 290M el deal de kit más grande de la historia del fútbol mexicano). Reemplazó a Nike en Club América en jul-2025. Kit de Tigres UANL. DG México: Jorge Dionne. | M55: El deal FMF-Adidas (USD 290M/10 años) es el contrato de kit más grande de la historia del fútbol mexicano. | N55: Kit FMF hasta 2034 (monto no confirmado oficialmente; reportado por fuentes secundarias); reemplazó a Nike en Club América jul-2025; kit Tigres UANL | Q55: adidas.com.mx | R55: Fuente única | S55: MONTO USD 290M no verificado en fuentes primarias (FMF/Adidas/SBJ/Sportico no reportaron cifra oficial). https://www.marketingregistrado.com/futbol/2024/mexico-adidas-renovaron-alianza-diez-anos-42793/ | T55: =IF(G55="","",IF(OR(G55="Tier 3"),"No",IF(AND(S55<>"",OR(ISNUMBER(SEARCH("OFAC",S55)),ISNUMBER(SEARCH("penal",S55)),ISNUMBER(SEARCH("rojo pendiente",S55)))),"Revisar","Sí"))) -> Sí
A56: A-003 | B56: V3-002 | C56: Amazon / AWS | D56: V3 | E56: V1 · V2 | F56: Marca / Sponsor corporativo | G56: Tier 2 | H56: EUA | I56: Ciudad de México | J56: Pone dinero | K56: Fútbol | L56: Primer triple deal de tech giant en el ecosistema deportivo mexicano: patrocinio simultáneo de la Selección Mexicana, Liga MX y Liga MX Femenil desde mar-2025. Combinado con Amazon Prime Video como broadcaster exclusivo de Chivas. | M56: Amazon inauguró la era del tech-as-sponsor en el ecosistema deportivo mexicano. La doble presencia (sponsor + broadcaster) en Chivas y Selección es el modelo más integrado del mercado. | N56: Triple deal Tri + Liga MX + Liga MX Femenil (mar-2025); primer tech giant sponsor ecosistema MX; doble rol sponsor+broadcaster | Q56: amazon.com.mx · aws.amazon.com | R56: Verificado | S56: https://www.aboutamazon.mx/noticias/noticias-de-la-compania/amazon-mexico-patrocinador-seleccion-nacional | T56: =IF(G56="","",IF(OR(G56="Tier 3"),"No",IF(AND(S56<>"",OR(ISNUMBER(SEARCH("OFAC",S56)),ISNUMBER(SEARCH("penal",S56)),ISNUMBER(SEARCH("rojo pendiente",S56)))),"Revisar","Sí"))) -> Sí
A57: A-008 | B57: V3-003 | C57: AT&T México | D57: V3 | E57: V1 · V3 | F57: Marca / Sponsor corporativo | G57: Tier 2 | H57: EUA / México | I57: Ciudad de México | J57: Pone dinero | K57: Fútbol | L57: Patrocinador de telecomunicaciones exclusivo de la Selección Mexicana desde 2019 hasta 2027. En proceso de venta corporativa de AT&T México. La transacción puede impactar la continuidad del deal con la FMF post-2027. Adicionalmente: proveedor venue WC26 (función V8 secundaria de telecom para sedes mundialistas). | M57: El deal AT&T-Selección (exclusivo telecom hasta 2027) es el contrato de telecomunicaciones más relevante del ecosistema. La venta corporativa de AT&T México introduce incertidumbre sobre su continuidad post-2027. | N57: Telecom exclusivo Selección Mexicana 2019-2027; proceso venta corporativa AT&T México | Q57: att.com.mx | R57: Verificado | S57: En proceso de venta corporativa de AT&T México. La transacción puede impactar el deal con la Selección post-2027. | T57: =IF(G57="","",IF(OR(G57="Tier 3"),"No",IF(AND(S57<>"",OR(ISNUMBER(SEARCH("OFAC",S57)),ISNUMBER(SEARCH("penal",S57)),ISNUMBER(SEARCH("rojo pendiente",S57)))),"Revisar","Sí"))) -> Sí
A58: A-009 | B58: V3-004 | C58: Banorte / Grupo Financiero Banorte | D58: V3 | E58: V7 · V9 | F58: Marca / Sponsor corporativo | G58: Tier 1 | H58: México | I58: Monterrey, NL / Ciudad de México | J58: Pone dinero | K58: Multideporte | L58: Rebautizó el Estadio Azteca como Estadio Banorte combinando deuda estructurada (MXN 2,100M + MXN 468M IVA = MXN 2,568M a 12 años) con naming rights. NFL México City Games presenting partner 2016-2028. Socio LGCT México. | M58: La operación Banorte-Ollamani es la más sofisticada del ecosistema: naming del estadio más icónico + deuda estructurada + presenting NFL México. Sin equivalente en el mercado mexicano. Inversión estimada >USD 30-50M anuales. | N58: Naming Estadio Banorte (histórico ex-Azteca); deuda MXN 2,568M con Ollamani; presenting NFL México City Games | Q58: banorte.com | R58: Fuente única | S58: Durante WC26 el Estadio se llama 'Estadio Ciudad de México' (reglas FIFA). Banorte pierde visibilidad de naming en el evento de mayor audiencia. | RENOVACIÓN BBVA jul-2025: plausible y consistente con ciclo Mundial, pero comunicados oficiales verificables más recientes alcanzan el ciclo 2026-27. Confirmar internamente con BBVA México antes de circular externamente. | T58: =IF(G58="","",IF(OR(G58="Tier 3"),"No",IF(AND(S58<>"",OR(ISNUMBER(SEARCH("OFAC",S58)),ISNUMBER(SEARCH("penal",S58)),ISNUMBER(SEARCH("rojo pendiente",S58)))),"Revisar","Sí"))) -> Sí
A59: A-010 | B59: V3-005 | C59: BBVA México | D59: V3 | E59: V7 · V1 | F59: Marca / Sponsor corporativo | G59: Tier 1 | H59: Otros | I59: Ciudad de México | J59: Pone dinero | K59: Fútbol | L59: Financia la visibilidad de marca más transversal del fútbol mexicano: title de Liga BBVA MX (varonil, femenil y Expansión desde 2016), naming del Estadio BBVA de Rayados (desde 2015), jersey sponsor de Rayados. Doble renovación en jul-2025. | M59: Único patrocinador con naming simultáneo de liga y estadio. Estrategia declarada: 'banco del deporte'. Doble renovación jul-2025: Liga MX hasta 2028, Estadio BBVA hasta 2030. Inversión deportiva estimada USD 35-55M anuales. | N59: Title sponsor Liga BBVA MX (varonil+femenil+Expansión) desde 2016; naming Estadio BBVA hasta 2030; doble renovación jul-2025 | Q59: bbva.mx | R59: Verificado | T59: =IF(G59="","",IF(OR(G59="Tier 3"),"No",IF(AND(S59<>"",OR(ISNUMBER(SEARCH("OFAC",S59)),ISNUMBER(SEARCH("penal",S59)),ISNUMBER(SEARCH("rojo pendiente",S59)))),"Revisar","Sí"))) -> Sí
A60: A-012 | B60: V3-006 | C60: Bimbo | D60: V3 | E60: V1 · V3 | F60: Marca / Sponsor corporativo | G60: Tier 2 | H60: México | I60: Ciudad de México | J60: Pone dinero | K60: Fútbol | L60: Regresó al jersey del Club América para la temporada 2025-26 después de una pausa. Sponsor histórico del fútbol mexicano. | M60: El regreso de Bimbo al jersey del América es la señal más clara del incremento del inventario comercial del activo post-General Atlantic. Bimbo es un sponsor con historial de largo plazo en el ecosistema. | N60: Regreso jersey Club América 2025-26; sponsor histórico fútbol mexicano; mayor panificadora del mundo | Q60: grupobimbo.com | R60: Verificado | T60: =IF(G60="","",IF(OR(G60="Tier 3"),"No",IF(AND(S60<>"",OR(ISNUMBER(SEARCH("OFAC",S60)),ISNUMBER(SEARCH("penal",S60)),ISNUMBER(SEARCH("rojo pendiente",S60)))),"Revisar","Sí"))) -> Sí
A61: A-023 | B61: V3-007 | C61: Coca-Cola México / Coca-Cola FEMSA | D61: V3 | E61: V1 · V3 | F61: Marca / Sponsor corporativo | G61: Tier 2 | H61: EUA / México | I61: Ciudad de México | J61: Pone dinero | K61: Fútbol | L61: Socio FIFA de Tier 1 global, lo que le garantiza presencia exclusiva en categoría bebidas no alcohólicas en los 13 partidos del WC26 en México. Sponsor de la Selección Mexicana y de Liga MX. Coca-Cola FEMSA opera la distribución y parte de los derechos de marca en México. | M61: La categoría exclusiva de bebidas no alcohólicas en WC26 es la activación de mayor alcance disponible en México 2026. La doble estructura Coca-Cola/Coca-Cola FEMSA crea sinergias entre el sponsor global y la distribución local. | N61: Socio FIFA Tier 1 global; exclusivo bebidas no alcohólicas WC26; Selección + Liga MX | O61: Coca-Cola · Powerade · Ciel · Sprite (portfolio sponsorship deportivo) | P61: Coca-Cola FEMSA es embotelladora más grande del mundo del Sistema Coca-Cola. Coca-Cola Company global controla la marca; FEMSA controla la distribución MX. | Q61: coca-cola.com.mx | R61: Verificado | T61: =IF(G62="","",IF(OR(G62="Tier 3"),"No",IF(AND(S62<>"",OR(ISNUMBER(SEARCH("OFAC",S62)),ISNUMBER(SEARCH("penal",S62)),ISNUMBER(SEARCH("rojo pendiente",S62)))),"Revisar","Sí"))) -> Sí
A62: A-024 | B62: V3-008 | C62: Codere Online | D62: V3 | E62: V1 · V3 | F62: Marca / Sponsor corporativo | G62: Tier 2 | H62: España | I62: Ciudad de México / Monterrey | J62: Pone dinero | K62: Fútbol | L62: Jersey sponsor de Rayados de Monterrey (hasta 2029) y Rayadas femenil. Sponsor en LMB. Segundo operador de apuestas con presencia estructural en el ecosistema tras Caliente.mx. | M62: La concentración de jersey de Rayados (activo FEMSA, el club corporativo más sólido) con Codere como sponsor da al operador español la asociación de mayor calidad institucional en el segmento de apuestas. | N62: Jersey Rayados hasta 2029; jersey Rayadas femenil; LMB; segundo operador apuestas estructural | Q62: codere.mx | R62: Verificado | T62: =IF(G63="","",IF(OR(G63="Tier 3"),"No",IF(AND(S63<>"",OR(ISNUMBER(SEARCH("OFAC",S63)),ISNUMBER(SEARCH("penal",S63)),ISNUMBER(SEARCH("rojo pendiente",S63)))),"Revisar","Sí"))) -> Sí
A63: A-028 | B63: V3-009 | C63: Corona / Grupo Modelo — AB InBev | D63: V3 | E63: V1 · V3 | F63: Marca / Sponsor corporativo | G63: Tier 2 | H63: Otros | I63: Ciudad de México | J63: Pone dinero | K63: Fútbol | L63: Cerveza oficial de la Selección Mexicana de Fútbol desde 2006 — el patrocinio de bebidas alcohólicas más longevo del ecosistema. Cassiano De Stefano como director de marketing. | M63: La relación Selección-Corona es uno de los deals de bebidas alcohólicas más longevo del fútbol mexicano (20 años). Corona es la cerveza más reconocida globalmente entre las marcas mexicanas. | N63: Cerveza oficial Selección Mexicana desde 2006 (20 años); uno de los deals de bebidas más longevo del fútbol MX | Q63: corona.com.mx | R63: Verificado | T63: =IF(G64="","",IF(OR(G64="Tier 3"),"No",IF(AND(S64<>"",OR(ISNUMBER(SEARCH("OFAC",S64)),ISNUMBER(SEARCH("penal",S64)),ISNUMBER(SEARCH("rojo pendiente",S64)))),"Revisar","Sí"))) -> Sí
A64: A-033 | B64: V3-010 | C64: Electrolit / Grupo PiSA | D64: V3 | E64: V1 · V3 | F64: Marca / Sponsor corporativo | G64: Tier 2 | H64: México | I64: Guadalajara, Jalisco | J64: Pone dinero | K64: Multideporte | L64: Bebida oficial de 8+ clubes Liga MX y >30 patrocinios activos en el ecosistema deportivo mexicano. Electrolit reposicionó el suero de rehidratación oral como bebida deportiva premium, disrumpiendo a Gatorade y Powerade. | M64: El mayor patrocinador de bebidas deportivas del ecosistema mexicano por volumen de acuerdos activos (>30). Disrumpió el duopolio Gatorade-Powerade en el segmento premium de bebidas deportivas. | N64: >30 patrocinios deportivos activos México; 8+ clubes Liga MX; disrumpió duopolio Gatorade-Powerade | Q64: electrolit.com.mx | R64: Verificado | T64: Sí
A65: A-053 | B65: V3-011 | C65: GNP Seguros / Grupo BAL | D65: V3 | E65: V9 | F65: Marca / Sponsor corporativo | G65: Tier 1 | H65: México | I65: Ciudad de México | J65: Pone dinero | K65: Multideporte | L65: Aseguradora del Grupo BAL (Familia Baillères) con presencia estructural en sponsorship deportivo mexicano. Title sponsor del Estadio GNP Seguros (ex Foro Sol) en concesión con CIE/OCESA. Sponsor del Maratón Banorte. Cobertura de seguros para múltiples eventos deportivos. | M65: Único sponsor V3 mexicano con naming rights de venue premium del país (Estadio GNP Seguros). Integra capital aseguradora con presencia simultánea en venue, running y eventos puntuales. Cross-link a Grupo BAL (V9-010) como holding patrimonial. | N65: Estadio GNP Seguros CDMX (naming, ex Foro Sol) · Coliseo GNP Seguros Zapopan (naming) · Arena GNP Acapulco (naming) · Foro GNP Mérida · Auditorio GNP Puebla · Abierto GNP Seguros Monterrey (WTA 250) · Maratón GNP MTY · Pulso GNP (festival OCESA) · GNP México naming portfolio (5+ venues simultáneos) | P65: Sponsor del portafolio Grupo BAL (Familia Baillères) | Consolidación inversa v1.00.13: BAL (ex A-057) absorbido en A-053 por R-01 (BAL única exposición sports es vía GNP); A-053 queda como actor canónico de la línea GNP/BAL. [v1.00.29: estrategia de naming agresiva con OCESA: cubre CDMX + GDL + Acapulco + Mérida + Puebla. Grupo BAL (Bailleres) holding aseguradora.] | Q65: gnp.com.mx | R65: Verificado | T65: =IF(G67="","",IF(OR(G67="Tier 3"),"No",IF(AND(S67<>"",OR(ISNUMBER(SEARCH("OFAC",S67)),ISNUMBER(SEARCH("penal",S67)),ISNUMBER(SEARCH("rojo pendiente",S67)))),"Revisar","Sí"))) -> No
A66: A-070 | B66: V3-012 | C66: Heineken México | D66: V3 | E66: V1 · V3 | F66: Marca / Sponsor corporativo | G66: Tier 2 | H66: Otros | I66: Ciudad de México | J66: Pone dinero | K66: Motorsport | L66: Title sponsor del Gran Premio de México F1 (Heineken Gran Premio de México, antes Gran Premio de México a secas). Socio del fideicomiso privado del GP México. Heineken es el title sponsor global de F1 (partnership con Liberty Media). | M66: La combinación de title local (GP México) + partnership global F1 (Heineken es el title partner global) le da a Heineken México la mayor cobertura de patrocinio F1 en el mercado nacional. | N66: Title GP México F1; socio fideicomiso privado GP México; partnership global F1 (title partner global Liberty Media) | Q66: heineken.com.mx | R66: Verificado | T66: =IF(G68="","",IF(OR(G68="Tier 3"),"No",IF(AND(S68<>"",OR(ISNUMBER(SEARCH("OFAC",S68)),ISNUMBER(SEARCH("penal",S68)),ISNUMBER(SEARCH("rojo pendiente",S68)))),"Revisar","Sí"))) -> No
A67: A-072 | B67: V3-013 | C67: Hisense | D67: V3 | E67: V1 · V3 | F67: Marca / Sponsor corporativo | G67: Tier 3 | H67: Otros | I67: Sin base operativa MX | J67: Pone dinero | K67: Eventos premium | L67: Patrocinador FIFA de Tier 1 global para el WC26, lo que le garantiza visibilidad en los 13 partidos del WC26 en México (estadios, transmisiones, hospitality). No tiene patrocinio directo con la FMF, Liga MX ni clubes mexicanos. | M67: La presencia de Hisense en México es exclusivamente vía el deal FIFA global. No tiene activación local directa. Su visibilidad en los 13 partidos en México es parte del deal global. | N67: Partner FIFA Tier 1 global WC26; visibilidad en 13 partidos MX; sin deal directo FMF ni Liga MX | Q67: hisense.com.mx | R67: Verificado | S67: Excluido P9.1 — depuración Tier 3 baja huella | T67: =IF(G69="","",IF(OR(G69="Tier 3"),"No",IF(AND(S69<>"",OR(ISNUMBER(SEARCH("OFAC",S69)),ISNUMBER(SEARCH("penal",S69)),ISNUMBER(SEARCH("rojo pendiente",S69)))),"Revisar","Sí"))) -> No
A68: A-082 | B68: V3-014 | C68: Libertad Financiera | D68: V3 | E68: V1 · V3 | F68: Marca / Sponsor corporativo | G68: Tier 3 | H68: México | I68: San Luis Potosí | J68: Pone dinero | K68: Fútbol | L68: Firmó los naming rights del estadio del Atlético de San Luis desde ene-2026. Primer acuerdo de naming de estadio Liga MX para una fintech mexicana. | M68: Primer fintech mexicana con naming rights de estadio Liga MX. El acuerdo con Atlético de San Luis (propiedad del Atlético de Madrid/Apollo) crea una relación sponsor-activo transnacional inusual. | N68: Primer fintech MX con naming estadio Liga MX (Atlético San Luis ene-2026); actor deportivo emergente | O68: Ticketmaster México · Estadio GNP Seguros (Ex Foro Sol) · Autódromo Hermanos Rodríguez · Palacio de los Deportes | P68: 4 propiedades absorbidas. Control operativo verificado en auditoría Padres/Hijos v3. | R68: Fuente única | T68: =IF(G70="","",IF(OR(G70="Tier 3"),"No",IF(AND(S70<>"",OR(ISNUMBER(SEARCH("OFAC",S70)),ISNUMBER(SEARCH("penal",S70)),ISNUMBER(SEARCH("rojo pendiente",S70)))),"Revisar","Sí"))) -> No
A69: A-086 | B69: V3-015 | C69: Maggi / Nestlé | D69: V3 | E69: V1 · V3 | F69: Marca / Sponsor corporativo | G69: Tier 3 | H69: Suiza | I69: Ciudad de México | J69: Pone dinero | K69: Fútbol | L69: Alianza oficial entre Maggi/Nestlé y la FMF desde abr-2025 hasta dic-2026. Cubre la ventana del WC26 en México. Activaciones de marca vinculadas a la Selección Mexicana. | M69: Maggi inaugura la categoría de alimentos procesados como sponsor de la Selección Mexicana en la ventana mundialista. Deal de corto plazo (21 meses) pero estratégicamente posicionado alrededor del WC26. | N69: Alianza FMF abr-2025 a dic-2026; cobertura mundialista; primera categoría alimentos procesados Selección | Q69: nestle.com.mx | R69: Verificado | T69: =IF(G71="","",IF(OR(G71="Tier 3"),"No",IF(AND(S71<>"",OR(ISNUMBER(SEARCH("OFAC",S71)),ISNUMBER(SEARCH("penal",S71)),ISNUMBER(SEARCH("rojo pendiente",S71)))),"Revisar","Sí"))) -> No
A70: A-089 | B70: V3-016 | C70: Mattel de México SA de CV | D70: V3 | F70: Marca / Sponsor corporativo | G70: Tier 3 | H70: EUA / México | I70: Ciudad de México | J70: Pone dinero | K70: Running / Wellness | L70: Licencia la marca Barbie para la Barbie Run México, evento de running organizado por ASdeporte. Edición 2024 (primera en México): CDMX y Monterrey. Edición 2025: CDMX (23 nov, 15,000 participantes esperados), Guadalajara y Monterrey. 40,000+ participantes acumulados en LATAM. | M70: Primer caso verificado en el ecosistema Running/Wellness mexicano de una empresa de entretenimiento/IP (no telecom, no bebidas deportivas, no financiero) usando el running como plataforma de activación de marca a escala de 15,000 participantes. | N70: Licenciante Barbie Run México (2024-2025); 15,000 participantes CDMX 2025; multi-sede LATAM (40,000+ acumulados); marca Barbie como IP licenciada en evento deportivo masivo | Q70: mattel.com/es-mx | R70: Verificado | T70: =IF(G72="","",IF(OR(G72="Tier 3"),"No",IF(AND(S72<>"",OR(ISNUMBER(SEARCH("OFAC",S72)),ISNUMBER(SEARCH("penal",S72)),ISNUMBER(SEARCH("rojo pendiente",S72)))),"Revisar","Sí"))) -> No
A71: A-095 | B71: V3-017 | C71: Mercado Pago / MercadoLibre | D71: V3 | E71: V1 · V3 | F71: Marca / Sponsor corporativo | G71: Tier 3 | H71: Otros | I71: Ciudad de México | J71: Pone dinero | K71: Fútbol | L71: Jersey sponsor de Chivas en la temporada 2024-25. No tiene deal formal con Liga MX. La posición de Mercado Pago en Chivas (el club con mayor fandom popular de México) es estratégicamente valiosa. | M71: Mercado Pago en Chivas es la fintech con mayor alcance de marca en el ecosistema de clubes mexicanos. Deal formal Liga MX pendiente de confirmación. | N71: Jersey Chivas 2024-25; fintech con mayor alcance Liga MX; deal formal Liga MX pendiente | Q71: mercadopago.com.mx | R71: Fuente única | T71: =IF(G73="","",IF(OR(G73="Tier 3"),"No",IF(AND(S73<>"",OR(ISNUMBER(SEARCH("OFAC",S73)),ISNUMBER(SEARCH("penal",S73)),ISNUMBER(SEARCH("rojo pendiente",S73)))),"Revisar","Sí"))) -> Sí
A72: A-101 | B72: V3-018 | C72: New Balance | D72: V3 | E72: V1 · V3 | F72: Marca / Sponsor corporativo | G72: Tier 3 | H72: EUA | I72: Sin base operativa MX | J72: Pone dinero | K72: Fútbol | L72: Kit técnico del Club Toluca (bicampeón Liga MX 2025). Reemplazó a Under Armour en 2023. El bicampeonato de Toluca en 2025 eleva significativamente el perfil de New Balance en el mercado mexicano. | M72: El bicampeonato de Toluca posiciona a New Balance en el ecosistema como el kit de los campeones 2025. Potencial palanca para expandir contratos en Liga MX. | N72: Kit Toluca bicampeón 2025; reemplazó Under Armour 2023; en ascenso en Liga MX | Q72: newbalance.com.mx | R72: Verificado | T72: =IF(G75="","",IF(OR(G75="Tier 3"),"No",IF(AND(S75<>"",OR(ISNUMBER(SEARCH("OFAC",S75)),ISNUMBER(SEARCH("penal",S75)),ISNUMBER(SEARCH("rojo pendiente",S75)))),"Revisar","Sí"))) -> Sí
A73: A-103 | B73: V3-019 | C73: Nike | D73: V3 | E73: V1 · V3 | F73: Marca / Sponsor corporativo | G73: Tier 2 | H73: EUA | I73: Ciudad de México | J73: Pone dinero | K73: Fútbol | L73: Perdió el kit del Club América frente a Adidas en jul-2025. Recuperaría el kit de Chivas en jul-2026 (Puma sale). Presencia decreciente en Liga MX. Nike mantiene Pumas UNAM y recupera Chivas. | M73: La pérdida del América (por Adidas) y la transición en Chivas (sale Puma, entra Nike jul-2026) redefinen el mapa de kit deals del fútbol mexicano. Nike queda en segundo lugar detrás de Adidas en el ecosistema. | N73: Pierde América jul-2025 (vs Adidas); recuperaría Chivas jul-2026; en repliegue estratégico Liga MX | Q73: nike.com.mx | R73: Verificado | S73: En repliegue estratégico. Pérdida de América (jul-2025) es el mayor retroceso de Nike en el fútbol mexicano en una década. | T73: sí
A74: A-106 | B74: V3-020 | C74: OXXO / FEMSA Comercio | D74: V3 | E74: V1 · V3 | F74: Marca / Sponsor corporativo | G74: Tier 3 | H74: México | I74: Monterrey, NL | J74: Pone dinero | K74: Fútbol | L74: Sin deal formal activo confirmado con Liga MX ni con la Selección. La escala de OXXO (>22,000 tiendas en México) y su pertenencia a FEMSA (propietaria de Rayados) lo hacen un patrocinador potencial estructural. | M74: La escala de distribución de OXXO (>22,000 puntos de venta) y su pertenencia a FEMSA (propietaria de Rayados) crean la posibilidad de un deal de distribution/activation masivo sin precedente. Sin evidencia de negociación activa. | N74: Sin deal formal activo; >22,000 tiendas; FEMSA (propietaria Rayados) como matriz; potencial estructural | O74: Red OXXO (~21,000 tiendas MX) · OXXO Sport (entradas y merchandising) · Patrocinios deportivos masivos | P74: Subsidiaria 100% FEMSA. Brazo de retail con presencia en sponsorship deportivo via inventory de tiendas + patrocinios directos (Liga MX, eventos). | Q74: oxxo.com | R74: Inferido por patrón | S74: Consolidado P9.1 → V9-008 FEMSA | T74: sí
A75: A-114 | B75: V3-021 | C75: Puma | D75: V3 | E75: V1 · V3 | F75: Marca / Sponsor corporativo | G75: Tier 2 | H75: Alemania | I75: Ciudad de México | J75: Pone dinero | K75: Fútbol | L75: Kit de Rayados de Monterrey (hasta 2029) y Pumas UNAM (desde 2026-27). Sale de Chivas en jul-2026 (Nike entra). Puma mantiene presencia en dos activos relevantes del ecosistema. | M75: Puma pierde Chivas (activo de fandom masivo) pero retiene Rayados (corporativo FEMSA) y añade Pumas UNAM. El balance net de su portafolio mejora en calidad institucional aunque pierde en volumen de audiencia. | N75: Kit Rayados hasta 2029; Pumas UNAM desde 2026-27; sale Chivas jul-2026 (entra Nike) | Q75: puma.com | R75: Verificado | T75: =IF(G80="","",IF(OR(G80="Tier 3"),"No",IF(AND(S80<>"",OR(ISNUMBER(SEARCH("OFAC",S80)),ISNUMBER(SEARCH("penal",S80)),ISNUMBER(SEARCH("rojo pendiente",S80)))),"Revisar","Sí"))) -> No
A76: A-121 | B76: V3-022 | C76: Scotiabank | D76: V3 | E76: V1 · V3 | F76: Marca / Sponsor corporativo | G76: Tier 3 | H76: Otros | I76: Ciudad de México | J76: Pone dinero | K76: Fútbol | L76: Pivotó estratégicamente al ecosistema femenil: Concacaf (derechos femeniles) y Chivas fuerzas básicas (desarrollo). Sale del ecosistema varonil de Liga MX. La estrategia de género es su diferenciador en un ecosistema dominado por sponsorship varonil. | M76: Scotiabank es el único banco extranjero con estrategia deportiva exclusivamente femenil en México. Su pivot reposiciona la marca en un segmento con crecimiento acelerado de inversión. | N76: Pivot exclusivo a ecosistema femenil Concacaf + Chivas fuerzas básicas; único banco extranjero con estrategia femenil MX | Q76: scotiabank.com.mx | R76: Verificado | T76: sí
A77: A-126 | B77: V3-023 | C77: Skechers | D77: V3 | E77: V1 · V3 | F77: Marca / Sponsor corporativo | G77: Tier 3 | H77: EUA | I77: Sin base operativa MX | J77: Pone dinero | K77: Fútbol | L77: Kit técnico del Club Pachuca desde jul-2025 — el primer contrato de kit con un club de fútbol profesional en la historia de Skechers a nivel global. Pachuca es el primer club de fútbol en el portafolio de Skechers. | M77: Un acuerdo sin precedente en el mercado de kit deals: una marca de calzado/athletic sin historia en fútbol firma su primer contrato global en Liga MX. Club Pachuca como laboratorio de expansión al fútbol para Skechers. | N77: Primer kit club fútbol global Skechers (Pachuca jul-2025); hito sin precedente en mercado de kit deals | Q77: skechers.com.mx | R77: Verificado | T77: =IF(G82="","",IF(OR(G82="Tier 3"),"No",IF(AND(S82<>"",OR(ISNUMBER(SEARCH("OFAC",S82)),ISNUMBER(SEARCH("penal",S82)),ISNUMBER(SEARCH("rojo pendiente",S82)))),"Revisar","Sí"))) -> Sí
A78: A-128 | B78: V3-024 | C78: Smart Fit México | D78: V3 | F78: Marca / Sponsor corporativo | G78: Tier 2 | H78: Brasil | I78: Ciudad de México (hub operativo México) | J78: Pone dinero | K78: Running / Wellness | L78: Opera la red de gimnasios de bajo costo más grande de México (395+ sucursales, 1 millón+ usuarios). Es el naming partner de toda la temporada HYROX México 2025/2026 ('Smart Fit HYROX [ciudad]'), lo que la convierte en el sponsor deportivo activo de mayor escala en el segmento fitness competitivo en México. | M78: La alianza Smart Fit-HYROX es el deal de sponsorship deportivo más estratégico del segmento fitness mexicano en 2025-2026: Smart Fit usa HYROX para posicionarse como el gimnasio de los corredores competitivos, mientras HYROX usa la red de 395 gimnasios para adquirir participantes. | N78: 395+ gimnasios en México; 1 millón+ usuarios; naming partner HYROX México temporada 25/26; gym partner oficial HYROX; segundo mercado global de Smart Fit (25% de sus gimnasios) | Q78: smartfit.com.mx | R78: Verificado | T78: =IF(G84="","",IF(OR(G84="Tier 3"),"No",IF(AND(S84<>"",OR(ISNUMBER(SEARCH("OFAC",S84)),ISNUMBER(SEARCH("penal",S84)),ISNUMBER(SEARCH("rojo pendiente",S84)))),"Revisar","Sí"))) -> No
A79: A-136 | B79: V3-025 | C79: Tecate / Cuauhtémoc Moctezuma | D79: V3 | E79: V1 · V3 | F79: Marca / Sponsor corporativo | G79: Tier 3 | H79: Otros | I79: Monterrey, NL | J79: Pone dinero | K79: Fútbol | L79: Cerveza oficial de Liga MX (varonil y femenil). Sponsor del ecosistema de boxeo mexicano (Canelo adjacente). Tecate coexiste con Corona/Modelo en el ecosistema como la marca cervecera de liga. | M79: Tecate capturó el title de cerveza oficial de Liga MX mientras Corona mantiene la Selección. Comparte con Heineken (GP México) el duopolio de cervezas premium en el ecosistema deportivo mexicano. | N79: Cerveza oficial Liga MX varonil + femenil; sponsor boxeo MX; subsidiaria Heineken | Q79: tecate.com.mx | R79: Verificado | T79: sí
A80: A-140 | B80: V3-026 | C80: Uber / Uber Eats | D80: V3 | E80: V1 · V3 | F80: Marca / Sponsor corporativo | G80: Tier 3 | H80: EUA | I80: Ciudad de México | J80: Pone dinero | K80: Fútbol | L80: Triple deal oficial desde oct-2025: Selección Mexicana, Liga MX y Liga MX Femenil. Combinado con activaciones de Uber Eats en matchdays. Segundo tech giant (después de Amazon) con triple deal en el ecosistema. | M80: El triple deal Uber consolida la tendencia de tech giants como sponsors sistémicos del ecosistema deportivo mexicano (Amazon desde mar-2025, Uber desde oct-2025). Ambos eligieron el mismo modelo de patrocinio triple. | N80: Triple deal FMF + Liga MX + Liga MX Femenil (oct-2025); segundo tech giant triple deal después de Amazon | Q80: uber.com.mx | R80: Verificado | T80: =IF(G86="","",IF(OR(G86="Tier 3"),"No",IF(AND(S86<>"",OR(ISNUMBER(SEARCH("OFAC",S86)),ISNUMBER(SEARCH("penal",S86)),ISNUMBER(SEARCH("rojo pendiente",S86)))),"Revisar","Sí"))) -> Sí
A81: A-144 | B81: V3-027 | C81: Viva Aerobus + Volaris (fusión dic-2025) | D81: V3 | E81: V1 · V3 | F81: Marca / Sponsor corporativo | G81: Tier 2 | H81: México | I81: Monterrey (Viva) / Ciudad de México (Volaris) | J81: Pone dinero | K81: Fútbol | L81: Viva Aerobus como aerolínea oficial de la Selección Mexicana. Volaris como sponsor de Pumas UNAM y Club Toluca. La fusión dic-2025 unificará en una sola estructura los patrocinios de El Tri, Pumas y Toluca, obligando a renegociar exclusividades post-Mundial. | M81: La fusión Viva-Volaris concentrará todos los patrocinios de aerolíneas del ecosistema en una sola entidad, creando un actor con poder de negociación inédito en el segmento. La renegociación de exclusividades post-WC26 es un evento de mercado relevante. | N81: Acuerdo de fusión firmado dic-2025 (cierre regulatorio pendiente 2026); Selección Mexicana oficial (Viva) + Pumas + Toluca (Volaris); holding resultante: Grupo Más Vuelos | Q81: vivaaerobus.com · volaris.com | R81: Fuente única | S81: Fusión anunciada 18-dic-2025 (Form 6-K SEC); accionistas Volaris aprobaron 25-mar-2026; cierre regulatorio pendiente. Renegociación de exclusividades post-WC26 obligatoria. Volaris en proceso de delisting NYSE. El holding resultante se llamará Grupo Más Vuelos — dato no recogido en versión anterior. | T81: =IF(G87="","",IF(OR(G87="Tier 3"),"No",IF(AND(S87<>"",OR(ISNUMBER(SEARCH("OFAC",S87)),ISNUMBER(SEARCH("penal",S87)),ISNUMBER(SEARCH("rojo pendiente",S87)))),"Revisar","Sí"))) -> Sí
A82: A-145 | B82: V3-028 | C82: Walmart México | D82: V3 | E82: V7 | F82: Marca / Sponsor corporativo | G82: Tier 2 | H82: Otros | I82: México | K82: Béisbol | L82: Walmart México retail. Naming Walmart Park (Estadio Sultanes Monterrey) desde 2024. En pláticas con América para patrocinio. | M82: Único naming retail en deporte profesional MX. Activación con béisbol LMB norte. | N82: Walmart Park ex (antes Sultanes Stadium, renombrado a Mobil Super 2025) · Patrocinio LMB (segment sponsor) · Bodega Aurrera Wellness · Programa de impulso al deporte amateur · Walmart Carrera 21K · Sams Club deportivos | P82: [v1.00.29: aprovecha 2,800 unidades en MX para activación sponsorship deportivo. Ex naming Walmart Park hasta 2025.] | Q82: walmartmexico.com | R82: Verificado | T82: =IF(G88="","",IF(OR(G88="Tier 3"),"No",IF(AND(S88<>"",OR(ISNUMBER(SEARCH("OFAC",S88)),ISNUMBER(SEARCH("penal",S88)),ISNUMBER(SEARCH("rojo pendiente",S88)))),"Revisar","Sí"))) -> Sí
A83: A-077 | B83: V4-002 | C83: Jump SMS (Jump Sportainment Solutions) | D83: V4 | F83: Consultora estratégica | G83: Tier 3 | H83: México | I83: CDMX | J83: Intermedia dinero | K83: Multideporte | L83: Diagnóstico/selección propiedades; valuación tangible/intangible patrocinio y naming; reportes ROI con eye-tracker y ROO con IA; estrategia multimedia. | M83: Produce inteligencia pública sobre mercado mexicano de patrocinios. Referente editorial ESPN, Forbes, El Economista. | N83: Análisis anual patrocinios Liga MX; valuación naming rights | Q83: jump-sms.com | R83: Verificado | T83: Sí
A84: A-099 | B84: V4-003 | C84: Neta Agencia Deportiva | D84: V4 | F84: Agencia full-service | G84: Tier 3 | H84: México | I84: CDMX / Puebla | J84: Intermedia dinero | K84: Multideporte | L84: Relaciones públicas olímpicos/paralímpicos; gestión patrocinios; organización Deportium Puebla; activaciones BTL; programa Nutre tu Empresa; Valencia CF Soccer Camp México. | M84: Única agencia mexicana con congreso consolidado de industria (Deportium, 6 ediciones). Puerta marcas con olímpicos. | N84: Deportium congreso; representación olímpicos; Valencia CF Soccer Camp MX | Q84: netaagenciadeportiva.com | R84: Verificado | T84: sí
A85: A-104 | B85: V4-004 | C85: Octagon | D85: V4 | F85: Agencia full-service | G85: Tier 2 | H85: EUA | I85: CDMX (presencia confirmada pero footprint modesto) | J85: Intermedia dinero | K85: Tenis | L85: Consultoría de patrocinios, representación de atletas y gestión global de derechos WTA. | M85: Agencia global WTA con relación con GS Sports y HG Promotores para licencias femeniles México. | N85: Octagon Talent Representation · Octagon Sponsorship · Octagon Hospitality · Octagon Events · Octagon Sports Marketing México (oficina CDMX) · Carteras deportes MX (golf, tenis, ciclismo) | P85: [v1.00.29: subsidiaria de Interpublic Group. Operación México desde 2015. Especializada en hospitality y sponsorship execution.] | Q85: octagon.com | R85: Verificado | S85: P4-CIERRE: V4-W01 (Octagon MX fútbol unidad) fusionado en este actor. Octagon opera en México con unidad especializada en fútbol/talento. V4-W01 ID no asignar. | T85: sí
A86: A-111 | B86: V4-005 | C86: Pitz Group | D86: V4 | F86: Agencia full-service | G86: Tier 1 | H86: México | I86: CDMX — Bosques de las Lomas | J86: Intermedia dinero | K86: Fútbol | L86: Representación 360° futbolistas: contratos, transferencias, asesoría jurídica/fiscal, imagen. Opera en MX, ES, IT, CH, UY, PA, UK. | M86: Market-maker del traspaso mexicano; >50 jugadores MX representados; sanción FIFA ago-2025 en curso. | N86: Pitz Group sports marketing · Pitz Hospitality · Pitz Brand Activation · Operaciones Liga MX + GP México · Acuerdos sponsorship Liga MX | P86: [v1.00.29: agencia mexicana, especializada en activaciones deportivas Liga MX.] | Q86: pitzgroup.com | R86: Verificado | S86: Sanción FIFA contra dueño López Martínez ago-2025; amparo federal en curso | T86: =IF(G89="","",IF(OR(G89="Tier 3"),"No",IF(AND(S89<>"",OR(ISNUMBER(SEARCH("OFAC",S89)),ISNUMBER(SEARCH("penal",S89)),ISNUMBER(SEARCH("rojo pendiente",S89)))),"Revisar","Sí"))) -> Sí
A87: A-112 | B87: V4-006 | C87: Promofut S.A. de C.V. | D87: V4 | F87: Agencia talent / representación | G87: Tier 1 | H87: México | I87: CDMX | J87: Intermedia dinero | K87: Fútbol | L87: Administración contratos, negociación traspasos Europa/MLS, representación DTs, gestión imagen. | M87: Históricamente agencia #1 del fútbol mexicano; top 3 en 2026 con 27-44 jugadores Liga MX. | N87: Promofut representación jugadores futbol · Cartera mexicana premium (jugadores Liga MX + Selección) · Operación traspasos internacionales · Acuerdos con clubes europeos | P87: [v1.00.29: agencia tradicional de representación de futbolistas mexicanos.] | Q87: promofut.com.mx | R87: Verificado | S87: Controversia red influencia Chivas/fuerzas básicas; reputación deteriorada | T87: =IF(G91="","",IF(OR(G91="Tier 3"),"No",IF(AND(S91<>"",OR(ISNUMBER(SEARCH("OFAC",S91)),ISNUMBER(SEARCH("penal",S91)),ISNUMBER(SEARCH("rojo pendiente",S91)))),"Revisar","Sí"))) -> Sí
A88: A-116 | B88: V4-008 | C88: Relevent (Relevent Sports Group) | D88: V4 | F88: Agencia rights sales | G88: Tier 2 | H88: EUA | I88: Nueva York (operación México vía JV LaLiga NA) | J88: Intermedia dinero | K88: Fútbol | L88: Via LaLiga North America (JV 50/50): gestiona derechos audiovisuales LaLiga en México, soporte a SKY Sports, activación comercial, producción en Guadalajara. | M88: Settlement Relevent-USSF 2025 abre camino Liga MX oficial en EE.UU.; Ross controla Hard Rock Stadium. | N88: Soccer Champions Tour USA · Leagues Cup (con MLS y Liga MX) · NWSL Acceso comercial · Acuerdo derechos LaLiga en USA · Relevent Sports Asia · The Sports Property Group | P88: [v1.00.29: relación clave con Liga MX vía Leagues Cup. Propiedad familia Hard Rock/Stephen Ross (matriz Apollo desde 2023 vía Apollo Sports).] | Q88: relevent.com | R88: Verificado | T88: sí
A89: A-129 | B89: V4-009 | C89: Soccer Media Solutions (SMS) | D89: V4 | F89: Agencia rights sales | G89: Tier 2 | H89: México | I89: Cuajimalpa, CDMX | J89: Intermedia dinero | K89: Fútbol | L89: Revende: inserciones virtuales en transmisiones TV Azteca; publicidad cancha en Selección/Liga MX; paquetes patrocinio ligados a propiedades TV Azteca. | M89: Gatekeeper comercial de pantallas/canchas en ecosistema FMF-TV Azteca; dos décadas de exclusividad. | N89: Exclusividad inserciones virtuales TV Azteca; inventario cancha Selección Mexicana | Q89: soccer-ms.com | publicidadencanchasdefutbol.com | R89: Verificado | T89: =IF(G95="","",IF(OR(G95="Tier 3"),"No",IF(AND(S95<>"",OR(ISNUMBER(SEARCH("OFAC",S95)),ISNUMBER(SEARCH("penal",S95)),ISNUMBER(SEARCH("rojo pendiente",S95)))),"Revisar","Sí"))) -> Sí
A90: A-130 | B90: V4-010 | C90: Sportfive | D90: V4 | F90: Agencia rights sales | G90: Tier 3 | H90: Alemania | I90: CDMX (presencia mencionada en prensa) | J90: Intermedia dinero | K90: Fútbol | L90: Venta de derechos, consultoría de patrocinios y activación para propiedades deportivas en LatAm. | M90: Relaciones con clubes Liga MX mencionadas en prensa; sin estructura pública verificada | N90: Lagardère legacy; relaciones Liga MX | Q90: sportfive.com | R90: Fuente única | T90: =IF(G96="","",IF(OR(G96="Tier 3"),"No",IF(AND(S96<>"",OR(ISNUMBER(SEARCH("OFAC",S96)),ISNUMBER(SEARCH("penal",S96)),ISNUMBER(SEARCH("rojo pendiente",S96)))),"Revisar","Sí"))) -> Sí
A91: A-131 | B91: V4-011 | C91: StayPro | D91: V4 | F91: Agencia talent / representación | G91: Tier 2 | H91: México | I91: CDMX | J91: Intermedia dinero | K91: Multideporte | L91: Agencia mexicana de representación comercial de futbolistas y creadores de contenido. Fundada 2015 en CDMX por Rafael Coronel y Patrycja Giemza. Representa exclusivamente a Héctor Herrera, Edson Álvarez, Diego Reyes, Carlos Rodríguez, Nailea Vidrio, Jana Gutiérrez, Alondra González en fútbol; Paco de Miguel, Chingu Amiga, Los Chicaneros y otros en creators (división StayOnSocial). Lanzó división StayPro OnTheField en 2024 para representación integral de atletas. | M91: Agencia #1 de representación comercial de futbolistas mexicanos. Más de 2,500 campañas con marcas globales ejecutadas. Modelo full-service: gestión de contratos publicitarios, asesoría de imagen, manejo de crisis, asesoría legal, RRPP, post-career planning. | N91: Agencia mexicana de talent management líder en LATAM con sede en Polanco CDMX y EUA. | Q91: stayprogroup.com | R91: Fuente única | S91: [P6-E P6-DT] Vis=Sí pero sin R1/R2 cargadas. Pendiente de carga en próximo ciclo. Conservar visualizable porque es benchmark relevante para Aldo (revisar caso a caso). | T91: =IF(G97="","",IF(OR(G97="Tier 3"),"No",IF(AND(S97<>"",OR(ISNUMBER(SEARCH("OFAC",S97)),ISNUMBER(SEARCH("penal",S97)),ISNUMBER(SEARCH("rojo pendiente",S97)))),"Revisar","Sí"))) -> Revisar
A92: A-134 | B92: V4-012 | C92: SUM (Soccer United Marketing) | D92: V4 | F92: Agencia rights sales | G92: Tier 1 | H92: EUA | I92: Nueva York / operación México | J92: Intermedia dinero | K92: Fútbol | L92: Comercializa Liga MX en EE.UU.; gestiona Leagues Cup y Campeones Cup; rights intermediary entre Liga MX y mercado norteamericano. | M92: Intermediario histórico de Liga MX en el mercado hispano de EE.UU. | N92: Comercial rights MLS · Comercial rights Selección Mexicana en USA (extendido hasta 2028) · 6 amistosos El Tri/año en USA · Promoción de tours · Co-organización Leagues Cup · Marketing CONCACAF y CONMEBOL Copa América Centenario 2016 | P92: [v1.00.29: brazo comercial de MLS, equity de todos los dueños MLS. Contrato exclusivo con FMF para mercado USA hasta 2028 (renovado 2022).] | Q92: sumworldwide.com | R92: Verificado | T92: sí
A93: A-135 | B93: V4-013 | C93: TEAM Marketing AG | D93: V4 | F93: Agencia rights sales | G93: Tier 2 | H93: Suiza | I93: Lucerna (operación remota CDMX) | J93: Intermedia dinero | K93: Fútbol | L93: Consultoría en desarrollo/valuación de conceptos de derechos; venta exclusiva derechos globales medios selecciones mexicanas para ciclos 2026-30 y 2030-34. | M93: Controla canal de entrada de broadcasters extranjeros hacia la Selección Mexicana; primer intermediario europeo de primer orden en LatAm. | N93: TEAM Marketing AG (sede Suiza) · Comercialización Champions League · Comercialización Europa League · Conference League · Coordinación sponsorship UEFA · Cobertura LATAM tier global | P93: [v1.00.29: agencia exclusiva UEFA para comercialización Champions/Europa/Conference. Pieza clave para marcas MX que activan en torneos UEFA.] | Q93: team.ch | R93: Verificado | T93: sí
A94: A-146 | B94: V4-014 | C94: Wasserman / THE·TEAM México | D94: V4 | E94: V5 | F94: Agencia talent / representación | G94: Tier 1 | H94: Otros | I94: Santa Fe, CDMX | J94: Intermedia dinero | K94: Multideporte | L94: Activa para SF 49ers en México (Academia Fundación 49ers, Watch Party MTY, partnerships Fox Sports/Radio Fórmula); representación futbolistas vía Rodrigo Morales; consultoría de marca. Adicionalmente opera Wasserman Events (división de eventos Golf desde mar-2026, función V5 secundaria de operación de eventos premium con anclaje USA / LATAM). | M94: Punto de contacto local de la agencia global dominante; pivote rumbo WC26 y NFL México. | N94: THE·TEAM Sports + Music + Entertainment (rebrand mar-2026) · MF Sports (ex Wasserman Boxing, vendido) · 25% stake Misfits Boxing · Representación atletas MX (Memo Ochoa, Raúl Jiménez, Edson Álvarez) · Sponsorship/naming rights consulting | P94: [v1.00.29: Casey Wasserman anunció venta de la compañía feb-2026. Rebrand a THE·TEAM mar-2026 vía Moelis. Wasserman Boxing vendido y renombrado MF Sports. Empresa en proceso de venta completa.] | Q94: the.team | R94: Verificado | T94: =IF(G100="","",IF(OR(G100="Tier 3"),"No",IF(AND(S100<>"",OR(ISNUMBER(SEARCH("OFAC",S100)),ISNUMBER(SEARCH("penal",S100)),ISNUMBER(SEARCH("rojo pendiente",S100)))),"Revisar","Sí"))) -> Sí
A95: A-007 | B95: V5-001 | C95: ASdeporte (Asdeporte SA de CV) | D95: V5 | E95: V1 · V6 | F95: Operador de eventos / experiencias | G95: Tier 2 | H95: México | I95: Ciudad de México | J95: Controla experiencia | K95: Running / Wellness | L95: Dos funciones simultáneas: (1) rights holder de eventos propios: ASTri Veracruz (triatlón más grande de LATAM), Circuito de las Estaciones, L'Etape México by Tour de France, Woman Up, Tune Up, 3Kids; (2) operador logístico de franquicias globales: Rock'n'Roll Mexico City para The IRONMAN Group. Plataforma digital propia con más de 1 millón de usuarios registrados, app, membresía Plus y sistema de inscripciones. | M95: Mayor organizador privado de Running/Wellness en México por volumen (90,000+ atletas/año). Nodo operativo indispensable para franquicias globales de endurance: Rock'n'Roll, IRONMAN, Spartan Race no operan en México sin infraestructura local de ASdeporte. | N95: ASTri Veracruz (triatlón más grande de LATAM); Rock'n'Roll Mexico City (operador local de The IRONMAN Group); L'Etape México by Tour de France; 1 millón+ usuarios registrados; 90,000+ atletas/año | O95: Rock'n'Roll Mexico City Running Series · Spartan Race México · IRONMAN México (Cozumel + Campeche) · Barbie Run México | P95: Operador líder de eventos running y obstacle course en México. Maneja licencias internacionales (Rock'n'Roll, Spartan, IRONMAN) bajo arrangements regionales. | Q95: asdeporte.com | R95: Verificado | S95: Conflicto de interés documentado (Vice, Proceso oct-2025): fundadores Antonio y David Álvarez Martínez son accionistas de ASdeporte y tuvieron roles directivos en la Federación Mexicana de Triatlón (FMTri), que contrató a ASdeporte con recursos públicos (MXN 15.8M, 2011-2015). | T95: =IF(G95="","",IF(OR(G95="Tier 3"),"No",IF(AND(S95<>"",OR(ISNUMBER(SEARCH("OFAC",S95)),ISNUMBER(SEARCH("penal",S95)),ISNUMBER(SEARCH("rojo pendiente",S95)))),"Revisar","Sí"))) -> Sí
A96: A-020 | B96: V5-002 | C96: CIE / OCESA (V5 Experiencias) | D96: V5 | E96: V7 · V6 | F96: Operador hospitality | G96: Tier 1 | H96: México | I96: CDMX | J96: Activa dinero | K96: Eventos premium | L96: Opera GP México F1; Experiencias+; JV OVG Hospitality F&B; Estadio GNP, AHR, Palacio Deportes, Centro Citibanamex; vende Paddock Club con F1 Experiences. | M96: Único gatekeeper con permiso venue federal/local, rights holder internacional y canal ticketing unificado para el evento más rentable del país. | N96: Vive Latino · Corona Capital · EDC México · Tecate Emblema · Arre · Pulso GNP · Coca-Cola Flow Fest · Estadio GNP Seguros (operación) · Palacio de los Deportes (operación) · Coliseo GNP Zapopan (lease 10 años) · Arena CDMX (operación) · Maratón CDMX · Ticketmaster México · Tours internacionales · Hospitality | O96: Estadio GNP Seguros (concesión, ex Foro Sol) · Autódromo Hermanos Rodríguez (concesión) · Palacio de los Deportes (concesión) · Ticketmaster México (75% post Live Nation ago-2025) · Estadio GNP Seguros (ex Foro Sol) | P96: Operación bajo concesión: Estadio GNP, Autódromo y Palacio son propiedad legal del Gobierno CDMX (Fideicomiso). CIE/OCESA es operador comercial. Ticketmaster México integrado vía Live Nation 75% OCESA (ago-2025). [v1.00.29: portafolio 7 festivales mayores + 4 venues operados. Modelo OCESA+GNP replicado a GDL en 2026. CEO Alejandro Soberón.] | Q96: cie.com.mx | ocesa.com.mx | R96: Verificado | T96: =IF(G96="","",IF(OR(G96="Tier 3"),"No",IF(AND(S96<>"",OR(ISNUMBER(SEARCH("OFAC",S96)),ISNUMBER(SEARCH("penal",S96)),ISNUMBER(SEARCH("rojo pendiente",S96)))),"Revisar","Sí"))) -> Sí
A97: A-034 | B97: V5-003 | C97: Elevate Sports Ventures | D97: V5 | E97: V7 · V1 | F97: Agencia full-service | G97: Tier 2 | H97: EUA | I97: CDMX (experience center) / Monterrey (Estadio Banorte) | J97: Controla experiencia | K97: Fútbol | L97: Diseña, vende y opera la capa premium del Estadio Banorte (contrato 10 años con Ollamani, jul-2025): Tunnel Club, Super Seats, Corner Club, Locker Club, Chairman's Club, Suites. | M97: Inaugura modelo NFL/NBA 'premium seating as product' en Liga MX; opera venue inaugural WC26 (11 jun). Define estándar que Liga MX emulará. | N97: Primer modelo premium seating Liga MX; Estadio Banorte WC26 sede inaugural; conexión 49ers | Q97: elevatesv.com | R97: Verificado | S97: Disputa legal activa palcohabientes; denuncia penal 17-sep-2025 | T97: =IF(G98="","",IF(OR(G98="Tier 3"),"No",IF(AND(S98<>"",OR(ISNUMBER(SEARCH("OFAC",S98)),ISNUMBER(SEARCH("penal",S98)),ISNUMBER(SEARCH("rojo pendiente",S98)))),"Revisar","Sí"))) -> Sí
A98: A-040 | B98: V5-004 | C98: F1 Experiences / QuintEvents | D98: V5 | E98: V4 · V7 | F98: Operador hospitality | G98: Tier 2 | H98: EUA | I98: Nueva York / CDMX (operación GP) | J98: Controla experiencia | K98: Motorsport | L98: Vende Paddock Club, F1 Experiences Suite, Team Suites (Red Bull, Ferrari, Mercedes, Aston Martin, Alpine), Champions Club para los 24 GPs incluido GP México. | M98: Único canal oficial Paddock Club y Team Suites para GP México. Mayor margen por cliente en el evento más rentable del país. | N98: F1 Experiences Mexico GP (paquetes oficiales) · F1 Paddock Club hospitality · F1 Fan Experiences · NASCAR Hospitality · NHL/NFL/PGA hospitality · Acuerdo exclusivo con F1 (Formula One Management) | P98: [v1.00.29: subsidiaria Endeavor (A-035). Único proveedor oficial F1 hospitality global.] | Q98: f1experiences.com | R98: Verificado | T98: =IF(G99="","",IF(OR(G99="Tier 3"),"No",IF(AND(S99<>"",OR(ISNUMBER(SEARCH("OFAC",S99)),ISNUMBER(SEARCH("penal",S99)),ISNUMBER(SEARCH("rojo pendiente",S99)))),"Revisar","Sí"))) -> Sí
A99: A-049 | B99: V5-005 | C99: Fuse Mexico (Omnicom Media Group) | D99: V5 | E99: V2 · V4 | F99: Agencia full-service | G99: Tier 2 | H99: Otros | I99: CDMX | J99: Controla experiencia | K99: Multideporte | L99: Consultoría de patrocinios, activaciones BTL, PR deportiva, eventos experienciales y medición ROI. Lanzamiento México feb-2026 coincidiendo con ramp-up WC26+F1+NBA+lucha libre. | M99: Única agencia global sport-marketing recién instalada en México justo antes del ciclo WC26+F1+NFL Banorte. | N99: Fuse Mexico (Omnicom Media Group) · Activaciones deportivas marcas multinacionales · Asociación con Olympic Games · Programas multi-anual brand partnership | P99: [v1.00.29: agencia full-service sponsorship marketing parte de Omnicom Media Group.] | Q99: fuse-uk.com | R99: Verificado | T99: =IF(G101="","",IF(OR(G101="Tier 3"),"No",IF(AND(S101<>"",OR(ISNUMBER(SEARCH("OFAC",S101)),ISNUMBER(SEARCH("penal",S101)),ISNUMBER(SEARCH("rojo pendiente",S101)))),"Revisar","Sí"))) -> Sí
A100: A-060 | B100: V5-006 | C100: Grupo Mundomex | D100: V5 | E100: V6 · V4 | F100: Operador hospitality | G100: Tier 2 | H100: México | I100: Polanco, CDMX | J100: Controla experiencia | K100: Eventos premium | L100: Agente autorizado oficial On Location para FIFA WC26 en territorio México desde jul-2025. Compra inventario hospitality, suma aereo+hotel 5*+logística+concierge y revende a corporativos y HNWI. | M100: Único canal oficial FIFA-26 hospitality en México. Once Mundiales consecutivos como agente (desde México 86). | N100: Agente oficial FIFA WC26 México; 11 Mundiales consecutivos; monopolio territorial hospitality | O100: Hospitalidad WC26 territorio México (vía sub-agreement con On Location) | P100: Sub-agente local de On Location para hospitalidad mundialista en sedes mexicanas (CDMX, Monterrey, Guadalajara). | Q100: mundomex.com.mx | R100: Verificado | T100: =IF(G102="","",IF(OR(G102="Tier 3"),"No",IF(AND(S102<>"",OR(ISNUMBER(SEARCH("OFAC",S102)),ISNUMBER(SEARCH("penal",S102)),ISNUMBER(SEARCH("rojo pendiente",S102)))),"Revisar","Sí"))) -> No
A101: A-067 | B101: V5-007 | C101: GS Sports Management | D101: V5 | E101: V1 · V2 | F101: Operador de eventos / experiencias | G101: Tier 2 | H101: México | I101: Guadalajara | J101: Controla experiencia | K101: Tenis | L101: Opera Guadalajara Open Akron (WTA 500); Mérida Open Akron (WTA 250); WTA 125 Vallarta y SLP; UTS Guadalajara (2025). Contrato GDL hasta 2029 con opción a 2034. | M101: Canal alterno a Mextenis; único licenciatario WTA elite activo en LatAm. Opera en números rojos pero sin sustituto. | N101: GS Sports Management · Acuerdos hospitality · Sport events Mexico operations · Representación talento sport | O101: Guadalajara Open Akron (operación · co-promotor Mextenis) | P101: Operador local del WTA Guadalajara Open Akron. Co-promueve con Mextenis y patrocinadores locales (Akron). [v1.00.29: operación mediana en CDMX, alianzas con marcas para activaciones puntuales.] | Q101: wtatennis.com | R101: Verificado | T101: =IF(G102="","",IF(OR(G102="Tier 3"),"No",IF(AND(S102<>"",OR(ISNUMBER(SEARCH("OFAC",S102)),ISNUMBER(SEARCH("penal",S102)),ISNUMBER(SEARCH("rojo pendiente",S102)))),"Revisar","Sí"))) -> No
...

Sheet MAPA DE CONEXIONES
A1: ◼ PLAYBOOK | B1: MAPA DE CONEXIONES
A2: Playbook Sports Intelligence | B2: Relaciones entre actores · Una fila por relación · Actor A activo, Actor B receptor (ver M-01)
A3: Playbook_Mapeo_v1.00.xlsx · Mapa del Ecosistema Deportivo Mexicano 2026 · CONFIDENCIAL · Uso interno
A5: ID Relación | B5: Actor A (ID Maestro) | C5: Actor A (nombre) | D5: Vertical A | E5: Actor B (ID Maestro) | F5: Actor B (nombre) | G5: Vertical B | H5: Tipo de relación | I5: Nivel | J5: Dirección | K5: Descripción | L5: Por qué importa | M5: Fuente / Evidencia | N5: Cross-vertical | O5: Visualizable
A6: R-237 | B6: A-029 | C6: =IF(B6="","",IFERROR(INDEX('UNIVERSO MAESTRO'!$C$6:$C$497,MATCH(B6,'UNIVERSO MAESTRO'!$A$6:$A$497,0)),"⚠ ID no encontrado")) -> Cruz Azul FC | D6: =IF(B6="","",IFERROR(INDEX('UNIVERSO MAESTRO'!$D$6:$D$497,MATCH(B6,'UNIVERSO MAESTRO'!$A$6:$A$497,0)),"")) -> V1 | E6: A-105 | F6: =IF(E6="","",IFERROR(INDEX('UNIVERSO MAESTRO'!$C$6:$C$497,MATCH(E6,'UNIVERSO MAESTRO'!$A$6:$A$497,0)),"⚠ ID no encontrado")) -> Ollamani, S.A.B. / Grupo Águilas (Club América + Estadio Banorte) | G6: =IF(E6="","",IFERROR(INDEX('UNIVERSO MAESTRO'!$D$6:$D$497,MATCH(E6,'UNIVERSO MAESTRO'!$A$6:$A$497,0)),"")) -> V9 | H6: Venue / Operations | I6: R2 | J6: A→B | K6: Cruz Azul regresó al Estadio Banorte (operado por Ollamani vía FDF SA, propiedad Grupo Televisa) el 26-abr-2026 para Jornada 17 vs Necaxa y para la Liguilla del Clausura 2026 (Cuartos de Final vs Atlas), tras casi 3 años sin jugar como local en el Coloso de Santa Úrsula. Régimen es alquiler temporal por partido, no contrato permanente; FIFA exige liberar el venue antes del Mundial 2026. | L6: Regreso parcial Cruz Azul al Banorte: el Coloso de Santa Úrsula deja de ser exclusivo del América durante remodelación; abre patrón de uso compartido del venue WC26 entre clubes Liga MX en transición. | M6: tudn.com; espn.com.mx; record.com.mx; mediotiempo.com; comunicado oficial Cruz Azul 21-abr-2026 | N6: =IF(OR(B6="",E6=""),"",IF(D6=G6,"No","Sí")) -> Sí | O6: =IF(I6="","",IF(I6="R3","No","Sí")) -> Sí
A7: R-037 | B7: A-021 | C7: =IF(B7="","",IFERROR(INDEX('UNIVERSO MAESTRO'!$C$6:$C$497,MATCH(B7,'UNIVERSO MAESTRO'!$A$6:$A$497,0)),"⚠ ID no encontrado")) -> Club Necaxa | D7: =IF(B7="","",IFERROR(INDEX('UNIVERSO MAESTRO'!$D$6:$D$497,MATCH(B7,'UNIVERSO MAESTRO'!$A$6:$A$497,0)),"")) -> V1 | E7: A-041 | F7: =IF(E7="","",IFERROR(INDEX('UNIVERSO MAESTRO'!$C$6:$C$497,MATCH(E7,'UNIVERSO MAESTRO'!$A$6:$A$497,0)),"⚠ ID no encontrado")) -> Familia Slim / Grupo Carso | G7: =IF(E7="","",IFERROR(INDEX('UNIVERSO MAESTRO'!$D$6:$D$497,MATCH(E7,'UNIVERSO MAESTRO'!$A$6:$A$497,0)),"")) -> V9 | H7: Rights / Media | I7: R3 | J7: A→B | K7: Claro Sports tiene derechos compartidos de Necaxa en Liga MX. Nexo América Móvil como broadcaster del club. | M7: clarosports.com; ficha V2-007 | N7: =IF(OR(B7="",E7=""),"",IF(D7=G7,"No","Sí")) -> Sí | O7: =IF(I7="","",IF(I7="R3","No","Sí")) -> No
A8: R-042 | B8: A-026 | C8: =IF(B8="","",IFERROR(INDEX('UNIVERSO MAESTRO'!$C$6:$C$497,MATCH(B8,'UNIVERSO MAESTRO'!$A$6:$A$497,0)),"⚠ ID no encontrado")) -> Consejo Municipal del Deporte de Guadalajara (COMUDE GDL) | D8: =IF(B8="","",IFERROR(INDEX('UNIVERSO MAESTRO'!$D$6:$D$497,MATCH(B8,'UNIVERSO MAESTRO'!$A$6:$A$497,0)),"")) -> V1 | E8: A-093 | F8: =IF(E8="","",IFERROR(INDEX('UNIVERSO MAESTRO'!$C$6:$C$497,MATCH(E8,'UNIVERSO MAESTRO'!$A$6:$A$497,0)),"⚠ ID no encontrado")) -> Medio Maratón Internacional Guadalajara Electrolit | G8: =IF(E8="","",IFERROR(INDEX('UNIVERSO MAESTRO'!$D$6:$D$497,MATCH(E8,'UNIVERSO MAESTRO'!$A$6:$A$497,0)),"")) -> V1 | H8: Institutional / Regulatory | I8: R1 | J8: A→B | K8: COMUDE es el rights holder institucional del evento: sin su convocatoria oficial no existe jurídicamente. | L8: COMUDE GDL es el gatekeeper público del único evento WA Platinum Label de México. | M8: marcate.com.mx convocatoria XL 2026 | N8: =IF(OR(B8="",E8=""),"",IF(D8=G8,"No","Sí")) -> No | O8: =IF(I8="","",IF(I8="R3","No","Sí")) -> Sí
A9: R-043 | B9: A-027 | C9: =IF(B9="","",IFERROR(INDEX('UNIVERSO MAESTRO'!$C$6:$C$497,MATCH(B9,'UNIVERSO MAESTRO'!$A$6:$A$497,0)),"⚠ ID no encontrado")) -> Copa Mundial FIFA 2026 en México | D9: =IF(B9="","",IFERROR(INDEX('UNIVERSO MAESTRO'!$D$6:$D$497,MATCH(B9,'UNIVERSO MAESTRO'!$A$6:$A$497,0)),"")) -> V1 | E9: A-035 | F9: =IF(E9="","",IFERROR(INDEX('UNIVERSO MAESTRO'!$C$6:$C$497,MATCH(E9,'UNIVERSO MAESTRO'!$A$6:$A$497,0)),"⚠ ID no encontrado")) -> Endeavor / WME Group | G9: =IF(E9="","",IFERROR(INDEX('UNIVERSO MAESTRO'!$D$6:$D$497,MATCH(E9,'UNIVERSO MAESTRO'!$A$6:$A$497,0)),"")) -> V9 | H9: Hospitality | I9: R1 | J9: A→B | K9: On Location es el operador oficial exclusivo de hospitalidad FIFA para WC26, incluyendo los 3 venues mexicanos (Banorte, BBVA, Akron). Monopolio global de hospitalidad mundialista. | L9: On Location es el operador exclusivo de hospitality FIFA WC26 en los 3 venues mexicanos: la puerta de entrada única para cualquier marca que quiera hospitality premium en el Mundial. | M9: onlocationexp.com; fifa.com/hospitality | N9: =IF(OR(B9="",E9=""),"",IF(D9=G9,"No","Sí")) -> Sí | O9: =IF(I9="","",IF(I9="R3","No","Sí")) -> Sí
A10: R-044 | B10: A-027 | C10: =IF(B10="","",IFERROR(INDEX('UNIVERSO MAESTRO'!$C$6:$C$497,MATCH(B10,'UNIVERSO MAESTRO'!$A$6:$A$497,0)),"⚠ ID no encontrado")) -> Copa Mundial FIFA 2026 en México | D10: =IF(B10="","",IFERROR(INDEX('UNIVERSO MAESTRO'!$D$6:$D$497,MATCH(B10,'UNIVERSO MAESTRO'!$A$6:$A$497,0)),"")) -> V1 | E10: A-043 | F10: =IF(E10="","",IFERROR(INDEX('UNIVERSO MAESTRO'!$C$6:$C$497,MATCH(E10,'UNIVERSO MAESTRO'!$A$6:$A$497,0)),"⚠ ID no encontrado")) -> Federación Mexicana de Fútbol | G10: =IF(E10="","",IFERROR(INDEX('UNIVERSO MAESTRO'!$D$6:$D$497,MATCH(E10,'UNIVERSO MAESTRO'!$A$6:$A$497,0)),"")) -> V1 | H10: Institutional / Regulatory | I10: R1 | J10: A→B | K10: La FMF es el ente co-anfitrión del WC26 en México junto con USSF y Canada Soccer. Gestiona la relación con FIFA y coordina los comités organizadores en las 3 sedes mexicanas. | M10: fmf.mx; fifa.com/worldcup | N10: =IF(OR(B10="",E10=""),"",IF(D10=G10,"No","Sí")) -> No | O10: =IF(I10="","",IF(I10="R3","No","Sí")) -> Sí
A11: R-045 | B11: A-027 | C11: =IF(B11="","",IFERROR(INDEX('UNIVERSO MAESTRO'!$C$6:$C$497,MATCH(B11,'UNIVERSO MAESTRO'!$A$6:$A$497,0)),"⚠ ID no encontrado")) -> Copa Mundial FIFA 2026 en México | D11: =IF(B11="","",IFERROR(INDEX('UNIVERSO MAESTRO'!$D$6:$D$497,MATCH(B11,'UNIVERSO MAESTRO'!$A$6:$A$497,0)),"")) -> V1 | E11: A-044 | F11: =IF(E11="","",IFERROR(INDEX('UNIVERSO MAESTRO'!$C$6:$C$497,MATCH(E11,'UNIVERSO MAESTRO'!$A$6:$A$497,0)),"⚠ ID no encontrado")) -> FEMSA / Club de Fútbol Monterrey Rayados | G11: =IF(E11="","",IFERROR(INDEX('UNIVERSO MAESTRO'!$D$6:$D$497,MATCH(E11,'UNIVERSO MAESTRO'!$A$6:$A$497,0)),"")) -> V9 | H11: Venue / Operations | I11: R1 | J11: A→B | K11: El Estadio BBVA es la sede WC26 en Monterrey. Alberga 4 partidos del Mundial (3 grupos + 1/16). | L11: BBVA es la sede WC26 en Monterrey (4 partidos): el único venue propiedad del mismo grupo que lo patrocina (FEMSA). | M11: fifa.com; espn.com.mx | N11: =IF(OR(B11="",E11=""),"",IF(D11=G11,"No","Sí")) -> Sí | O11: =IF(I11="","",IF(I11="R3","No","Sí")) -> Sí
A12: R-046 | B12: A-027 | C12: =IF(B12="","",IFERROR(INDEX('UNIVERSO MAESTRO'!$C$6:$C$497,MATCH(B12,'UNIVERSO MAESTRO'!$A$6:$A$497,0)),"⚠ ID no encontrado")) -> Copa Mundial FIFA 2026 en México | D12: =IF(B12="","",IFERROR(INDEX('UNIVERSO MAESTRO'!$D$6:$D$497,MATCH(B12,'UNIVERSO MAESTRO'!$A$6:$A$497,0)),"")) -> V1 | E12: A-061 | F12: =IF(E12="","",IFERROR(INDEX('UNIVERSO MAESTRO'!$C$6:$C$497,MATCH(E12,'UNIVERSO MAESTRO'!$A$6:$A$497,0)),"⚠ ID no encontrado")) -> Grupo Omnilife / Amaury Vergara / Chivas | G12: =IF(E12="","",IFERROR(INDEX('UNIVERSO MAESTRO'!$D$6:$D$497,MATCH(E12,'UNIVERSO MAESTRO'!$A$6:$A$497,0)),"")) -> V9 | H12: Venue / Operations | I12: R1 | J12: A→B | K12: El Estadio Akron es la sede WC26 en Guadalajara. Alberga 4 partidos del Mundial. | M12: fifa.com; espn.com.mx | N12: =IF(OR(B12="",E12=""),"",IF(D12=G12,"No","Sí")) -> Sí | O12: =IF(I12="","",IF(I12="R3","No","Sí")) -> Sí
A13: R-047 | B13: A-027 | C13: =IF(B13="","",IFERROR(INDEX('UNIVERSO MAESTRO'!$C$6:$C$497,MATCH(B13,'UNIVERSO MAESTRO'!$A$6:$A$497,0)),"⚠ ID no encontrado")) -> Copa Mundial FIFA 2026 en México | D13: =IF(B13="","",IFERROR(INDEX('UNIVERSO MAESTRO'!$D$6:$D$497,MATCH(B13,'UNIVERSO MAESTRO'!$A$6:$A$497,0)),"")) -> V1 | E13: A-069 | F13: =IF(E13="","",IFERROR(INDEX('UNIVERSO MAESTRO'!$C$6:$C$497,MATCH(E13,'UNIVERSO MAESTRO'!$A$6:$A$497,0)),"⚠ ID no encontrado")) -> Hawk-Eye Innovations (Sony) | G13: =IF(E13="","",IFERROR(INDEX('UNIVERSO MAESTRO'!$D$6:$D$497,MATCH(E13,'UNIVERSO MAESTRO'!$A$6:$A$497,0)),"")) -> V8 | H13: Data / Fan Intelligence | I13: R1 | J13: A→B | K13: Hawk-Eye es el VAR Technology Provider oficial de FIFA para los 16 venues WC26, incluyendo los 3 mexicanos (Banorte, BBVA, Akron). Provee SAOT y Goal-Line Technology. | L13: Hawk-Eye es el VAR Technology Provider oficial de FIFA para los 16 venues WC26 incluyendo los 3 mexicanos: el mandato tecnológico de integridad deportiva más amplio del evento. | M13: inside.fifa.com; news.lenovo.com | N13: =IF(OR(B13="",E13=""),"",IF(D13=G13,"No","Sí")) -> Sí | O13: =IF(I13="","",IF(I13="R3","No","Sí")) -> Sí
A14: R-048 | B14: A-027 | C14: =IF(B14="","",IFERROR(INDEX('UNIVERSO MAESTRO'!$C$6:$C$497,MATCH(B14,'UNIVERSO MAESTRO'!$A$6:$A$497,0)),"⚠ ID no encontrado")) -> Copa Mundial FIFA 2026 en México | D14: =IF(B14="","",IFERROR(INDEX('UNIVERSO MAESTRO'!$D$6:$D$497,MATCH(B14,'UNIVERSO MAESTRO'!$A$6:$A$497,0)),"")) -> V1 | E14: A-081 | F14: =IF(E14="","",IFERROR(INDEX('UNIVERSO MAESTRO'!$C$6:$C$497,MATCH(E14,'UNIVERSO MAESTRO'!$A$6:$A$497,0)),"⚠ ID no encontrado")) -> Lenovo | G14: =IF(E14="","",IFERROR(INDEX('UNIVERSO MAESTRO'!$D$6:$D$497,MATCH(E14,'UNIVERSO MAESTRO'!$A$6:$A$497,0)),"")) -> V8 | H14: Venue / Operations | I14: R1 | J14: A→B | K14: Lenovo es el Official Technology Partner de FIFA WC26. Provee infraestructura, Football AI Pro y soporte a Hawk-Eye en los 3 venues mexicanos. | L14: Lenovo es Official Technology Partner FIFA WC26 global: provee Football AI Pro y soporte a Hawk-Eye en todos los venues mexicanos. | M14: lenovo.com; news.lenovo.com | N14: =IF(OR(B14="",E14=""),"",IF(D14=G14,"No","Sí")) -> Sí | O14: =IF(I14="","",IF(I14="R3","No","Sí")) -> Sí
A15: R-049 | B15: A-027 | C15: =IF(B15="","",IFERROR(INDEX('UNIVERSO MAESTRO'!$C$6:$C$497,MATCH(B15,'UNIVERSO MAESTRO'!$A$6:$A$497,0)),"⚠ ID no encontrado")) -> Copa Mundial FIFA 2026 en México | D15: =IF(B15="","",IFERROR(INDEX('UNIVERSO MAESTRO'!$D$6:$D$497,MATCH(B15,'UNIVERSO MAESTRO'!$A$6:$A$497,0)),"")) -> V1 | E15: A-105 | F15: =IF(E15="","",IFERROR(INDEX('UNIVERSO MAESTRO'!$C$6:$C$497,MATCH(E15,'UNIVERSO MAESTRO'!$A$6:$A$497,0)),"⚠ ID no encontrado")) -> Ollamani, S.A.B. / Grupo Águilas (Club América + Estadio Banorte) | G15: =IF(E15="","",IFERROR(INDEX('UNIVERSO MAESTRO'!$D$6:$D$497,MATCH(E15,'UNIVERSO MAESTRO'!$A$6:$A$497,0)),"")) -> V9 | H15: Venue / Operations | I15: R1 | J15: A→B | K15: El Estadio Banorte es la sede del partido inaugural WC26 (México vs Sudáfrica, 11-jun-2026). Alberga 5 partidos del Mundial. Durante WC26 se denomina oficialmente 'Estadio Ciudad de México' (reglas FIFA). | L15: Banorte es sede inaugural WC26 (5 partidos, incluyendo México vs Sudáfrica): el evento más alto de la pirámide. | M15: fifa.com; espn.com.mx | N15: =IF(OR(B15="",E15=""),"",IF(D15=G15,"No","Sí")) -> Sí | O15: =IF(I15="","",IF(I15="R3","No","Sí")) -> Sí
A16: R-051 | B16: A-029 | C16: =IF(B16="","",IFERROR(INDEX('UNIVERSO MAESTRO'!$C$6:$C$497,MATCH(B16,'UNIVERSO MAESTRO'!$A$6:$A$497,0)),"⚠ ID no encontrado")) -> Cruz Azul FC | D16: =IF(B16="","",IFERROR(INDEX('UNIVERSO MAESTRO'!$D$6:$D$497,MATCH(B16,'UNIVERSO MAESTRO'!$A$6:$A$497,0)),"")) -> V1 | E16: A-037 | F16: =IF(E16="","",IFERROR(INDEX('UNIVERSO MAESTRO'!$C$6:$C$497,MATCH(E16,'UNIVERSO MAESTRO'!$A$6:$A$497,0)),"⚠ ID no encontrado")) -> Estadio Ciudad de los Deportes | G16: =IF(E16="","",IFERROR(INDEX('UNIVERSO MAESTRO'!$D$6:$D$497,MATCH(E16,'UNIVERSO MAESTRO'!$A$6:$A$497,0)),"")) -> V7 | H16: Venue / Operations | I16: R1 | J16: A→B | K16: Estadio Ciudad de los Deportes (ex Estadio Azul) fue casa de Cruz Azul desde 2024 hasta ene-2026 (clausurado por Protección Civil nov-2024 durante remodelación Banorte). En el Clausura 2026 Cruz Azul jugó la mayoría de partidos como local en Estadio Cuauhtémoc Puebla por contrato con Salinas/Puebla vigente hasta jun-2026, con regreso parcial al Estadio Banorte para Jornada 17 (26-abr-2026) y Liguilla. | L16: P6-E. Cierra orfandad V7-014. Cruz Azul en estadio temporal mientras define proyecto de estadio propio. Situación volátil que afecta cualquier proyección comercial 3+ años. | M16: tudn.com; espn.com.mx; record.com.mx; comunicado oficial Cruz Azul 21-abr-2026 | N16: =IF(OR(B16="",E16=""),"",IF(D16=G16,"No","Sí")) -> Sí | O16: =IF(I16="","",IF(I16="R3","No","Sí")) -> Sí
A17: R-081 | B17: A-043 | C17: =IF(B17="","",IFERROR(INDEX('UNIVERSO MAESTRO'!$C$6:$C$497,MATCH(B17,'UNIVERSO MAESTRO'!$A$6:$A$497,0)),"⚠ ID no encontrado")) -> Federación Mexicana de Fútbol | D17: =IF(B17="","",IFERROR(INDEX('UNIVERSO MAESTRO'!$D$6:$D$497,MATCH(B17,'UNIVERSO MAESTRO'!$A$6:$A$497,0)),"")) -> V1 | E17: A-084 | F17: =IF(E17="","",IFERROR(INDEX('UNIVERSO MAESTRO'!$C$6:$C$497,MATCH(E17,'UNIVERSO MAESTRO'!$A$6:$A$497,0)),"⚠ ID no encontrado")) -> Liga MX | G17: =IF(E17="","",IFERROR(INDEX('UNIVERSO MAESTRO'!$D$6:$D$497,MATCH(E17,'UNIVERSO MAESTRO'!$A$6:$A$497,0)),"")) -> V1 | H17: Institutional / Regulatory | I17: R1 | J17: A→B | K17: La separación jurídica FMF-Liga MX aprobada el 23-abr-2026 redefinió la relación: de dependencia jerárquica a entidades autónomas. FMF retiene el control de selecciones; Liga MX gestiona el torneo. Antes de abr-2026, Liga MX era una subdivisión de FMF. | L17: La separación jurídica abr-2026 es el hecho estructural más importante del ecosistema en 2026: dos entes, dos lógicas comerciales. | M17: ligamx.net; espn.com.mx; mediotiempo.com abr-2026 | N17: =IF(OR(B17="",E17=""),"",IF(D17=G17,"No","Sí")) -> No | O17: =IF(I17="","",IF(I17="R3","No","Sí")) -> Sí
A18: R-082 | B18: A-043 | C18: =IF(B18="","",IFERROR(INDEX('UNIVERSO MAESTRO'!$C$6:$C$497,MATCH(B18,'UNIVERSO MAESTRO'!$A$6:$A$497,0)),"⚠ ID no encontrado")) -> Federación Mexicana de Fútbol | D18: =IF(B18="","",IFERROR(INDEX('UNIVERSO MAESTRO'!$D$6:$D$497,MATCH(B18,'UNIVERSO MAESTRO'!$A$6:$A$497,0)),"")) -> V1 | E18: A-123 | F18: =IF(E18="","",IFERROR(INDEX('UNIVERSO MAESTRO'!$C$6:$C$497,MATCH(E18,'UNIVERSO MAESTRO'!$A$6:$A$497,0)),"⚠ ID no encontrado")) -> Selección Mexicana de Fútbol | G18: =IF(E18="","",IFERROR(INDEX('UNIVERSO MAESTRO'!$D$6:$D$497,MATCH(E18,'UNIVERSO MAESTRO'!$A$6:$A$497,0)),"")) -> V1 | H18: Ownership / Control | I18: R1 | J18: A→B | K18: La FMF es el rights holder y ente rector de la Selección Mexicana de Fútbol. El Tri no tiene personalidad jurídica propia: es una entidad bajo la FMF. | L18: FMF es el rights holder de El Tri: sin entender esta relación no se entiende quién vende los derechos. | M18: fmf.mx; fifa.com | N18: =IF(OR(B18="",E18=""),"",IF(D18=G18,"No","Sí")) -> No | O18: =IF(I18="","",IF(I18="R3","No","Sí")) -> Sí
A19: R-083 | B19: A-043 | C19: =IF(B19="","",IFERROR(INDEX('UNIVERSO MAESTRO'!$C$6:$C$497,MATCH(B19,'UNIVERSO MAESTRO'!$A$6:$A$497,0)),"⚠ ID no encontrado")) -> Federación Mexicana de Fútbol | D19: =IF(B19="","",IFERROR(INDEX('UNIVERSO MAESTRO'!$D$6:$D$497,MATCH(B19,'UNIVERSO MAESTRO'!$A$6:$A$497,0)),"")) -> V1 | E19: A-124 | F19: =IF(E19="","",IFERROR(INDEX('UNIVERSO MAESTRO'!$C$6:$C$497,MATCH(E19,'UNIVERSO MAESTRO'!$A$6:$A$497,0)),"⚠ ID no encontrado")) -> Selección Mexicana Femenil | G19: =IF(E19="","",IFERROR(INDEX('UNIVERSO MAESTRO'!$D$6:$D$497,MATCH(E19,'UNIVERSO MAESTRO'!$A$6:$A$497,0)),"")) -> V1 | H19: Ownership / Control | I19: R1 | J19: A→B | K19: La FMF es el ente rector de la Selección Mexicana Femenil. El triple deal Amazon incluye a la Liga MX Femenil y la Selección Femenil. | L19: FMF es el ente rector de la Femenil: el triple deal Amazon y los sponsors femeniles pasan por aquí. | M19: fmf.mx | N19: =IF(OR(B19="",E19=""),"",IF(D19=G19,"No","Sí")) -> No | O19: =IF(I19="","",IF(I19="R3","No","Sí")) -> Sí
A20: R-099 | B20: A-052 | C20: =IF(B20="","",IFERROR(INDEX('UNIVERSO MAESTRO'!$C$6:$C$497,MATCH(B20,'UNIVERSO MAESTRO'!$A$6:$A$497,0)),"⚠ ID no encontrado")) -> Global Champions Tour — LGCT México | D20: =IF(B20="","",IFERROR(INDEX('UNIVERSO MAESTRO'!$D$6:$D$497,MATCH(B20,'UNIVERSO MAESTRO'!$A$6:$A$497,0)),"")) -> V1 | E20: A-020 | F20: =IF(E20="","",IFERROR(INDEX('UNIVERSO MAESTRO'!$C$6:$C$497,MATCH(E20,'UNIVERSO MAESTRO'!$A$6:$A$497,0)),"⚠ ID no encontrado")) -> CIE / OCESA (V5 Experiencias) | G20: =IF(E20="","",IFERROR(INDEX('UNIVERSO MAESTRO'!$D$6:$D$497,MATCH(E20,'UNIVERSO MAESTRO'!$A$6:$A$497,0)),"")) -> V5 | H20: Venue / Operations | I20: R2 | J20: A→B | K20: LGCT México usa el Estadio GNP Seguros (operado por OCESA) para su etapa mexicana. GNP Seguros es presenting partner del evento. | L20: LGCT México usa el GNP Seguros para su etapa: el segmento ecuestre premium que convive con F1 y conciertos en la misma concesión OCESA. | M20: globalchampionsseries.com; ficha V1-017 | N20: =IF(OR(B20="",E20=""),"",IF(D20=G20,"No","Sí")) -> Sí | O20: =IF(I20="","",IF(I20="R3","No","Sí")) -> Sí
A21: R-103 | B21: A-055 | C21: =IF(B21="","",IFERROR(INDEX('UNIVERSO MAESTRO'!$C$6:$C$497,MATCH(B21,'UNIVERSO MAESTRO'!$A$6:$A$497,0)),"⚠ ID no encontrado")) -> Gran Premio de México — Fórmula 1 | D21: =IF(B21="","",IFERROR(INDEX('UNIVERSO MAESTRO'!$D$6:$D$497,MATCH(B21,'UNIVERSO MAESTRO'!$A$6:$A$497,0)),"")) -> V1 | E21: A-020 | F21: =IF(E21="","",IFERROR(INDEX('UNIVERSO MAESTRO'!$C$6:$C$497,MATCH(E21,'UNIVERSO MAESTRO'!$A$6:$A$497,0)),"⚠ ID no encontrado")) -> CIE / OCESA (V5 Experiencias) | G21: =IF(E21="","",IFERROR(INDEX('UNIVERSO MAESTRO'!$D$6:$D$497,MATCH(E21,'UNIVERSO MAESTRO'!$A$6:$A$497,0)),"")) -> V5 | H21: Venue / Operations | I21: R1 | J21: A→B | K21: El GP México se celebra en el AHR bajo concesión OCESA del Gobierno CDMX. El evento es la razón de ser del circuito. | L21: El GP México es la razón de ser del circuito: el evento más rentable del ecosistema deportivo mexicano no existe sin este venue. | M21: cie.com.mx; expansión.mx | N21: =IF(OR(B21="",E21=""),"",IF(D21=G21,"No","Sí")) -> Sí | O21: =IF(I21="","",IF(I21="R3","No","Sí")) -> Sí
A22: R-140 | B22: A-075 | C22: =IF(B22="","",IFERROR(INDEX('UNIVERSO MAESTRO'!$C$6:$C$497,MATCH(B22,'UNIVERSO MAESTRO'!$A$6:$A$497,0)),"⚠ ID no encontrado")) -> INDEPORTE — Instituto del Deporte de la Ciudad de México | D22: =IF(B22="","",IFERROR(INDEX('UNIVERSO MAESTRO'!$D$6:$D$497,MATCH(B22,'UNIVERSO MAESTRO'!$A$6:$A$497,0)),"")) -> V1 | E22: A-087 | F22: =IF(E22="","",IFERROR(INDEX('UNIVERSO MAESTRO'!$C$6:$C$497,MATCH(E22,'UNIVERSO MAESTRO'!$A$6:$A$497,0)),"⚠ ID no encontrado")) -> Maratón de la Ciudad de México Telcel | G22: =IF(E22="","",IFERROR(INDEX('UNIVERSO MAESTRO'!$D$6:$D$497,MATCH(E22,'UNIVERSO MAESTRO'!$A$6:$A$497,0)),"")) -> V1 | H22: Institutional / Regulatory | I22: R1 | J22: A→B | K22: INDEPORTE es el rights holder institucional y presidente del comité organizador: la convocatoria no tiene validez jurídica sin su sello y firma. | L22: INDEPORTE es el gatekeeper público: ninguna marca obtiene el naming del Maratón CDMX sin negociar con el gobierno de la ciudad. | M22: emociondeportiva.com convocatoria XLIII 2026 (nota jurídica) | N22: =IF(OR(B22="",E22=""),"",IF(D22=G22,"No","Sí")) -> No | O22: =IF(I22="","",IF(I22="R3","No","Sí")) -> Sí
A23: R-141 | B23: A-075 | C23: =IF(B23="","",IFERROR(INDEX('UNIVERSO MAESTRO'!$C$6:$C$497,MATCH(B23,'UNIVERSO MAESTRO'!$A$6:$A$497,0)),"⚠ ID no encontrado")) -> INDEPORTE — Instituto del Deporte de la Ciudad de México | D23: =IF(B23="","",IFERROR(INDEX('UNIVERSO MAESTRO'!$D$6:$D$497,MATCH(B23,'UNIVERSO MAESTRO'!$A$6:$A$497,0)),"")) -> V1 | E23: A-092 | F23: =IF(E23="","",IFERROR(INDEX('UNIVERSO MAESTRO'!$C$6:$C$497,MATCH(E23,'UNIVERSO MAESTRO'!$A$6:$A$497,0)),"⚠ ID no encontrado")) -> Medio Maratón de la Ciudad de México BBVA | G23: =IF(E23="","",IFERROR(INDEX('UNIVERSO MAESTRO'!$D$6:$D$497,MATCH(E23,'UNIVERSO MAESTRO'!$A$6:$A$497,0)),"")) -> V1 | H23: Institutional / Regulatory | I23: R1 | J23: A→B | K23: Ídem para el Medio Maratón BBVA. | L23: Ídem: gatekeeper público del naming del Medio Maratón CDMX. | M23: emociondeportiva.com convocatoria XIX 2026 (nota jurídica) | N23: =IF(OR(B23="",E23=""),"",IF(D23=G23,"No","Sí")) -> No | O23: =IF(I23="","",IF(I23="R3","No","Sí")) -> Sí
A24: R-150 | B24: A-084 | C24: =IF(B24="","",IFERROR(INDEX('UNIVERSO MAESTRO'!$C$6:$C$497,MATCH(B24,'UNIVERSO MAESTRO'!$A$6:$A$497,0)),"⚠ ID no encontrado")) -> Liga MX | D24: =IF(B24="","",IFERROR(INDEX('UNIVERSO MAESTRO'!$D$6:$D$497,MATCH(B24,'UNIVERSO MAESTRO'!$A$6:$A$497,0)),"")) -> V1 | E24: A-005 | F24: =IF(E24="","",IFERROR(INDEX('UNIVERSO MAESTRO'!$C$6:$C$497,MATCH(E24,'UNIVERSO MAESTRO'!$A$6:$A$497,0)),"⚠ ID no encontrado")) -> Apollo Sports Capital | G24: =IF(E24="","",IFERROR(INDEX('UNIVERSO MAESTRO'!$D$6:$D$497,MATCH(E24,'UNIVERSO MAESTRO'!$A$6:$A$497,0)),"")) -> V9 | H24: Institutional / Regulatory | I24: R3 | J24: A→B | K24: Atlético de San Luis (Apollo Sports Capital vía Atlético de Madrid) es club miembro de Liga MX AC. | M24: ligamx.net | N24: =IF(OR(B24="",E24=""),"",IF(D24=G24,"No","Sí")) -> Sí | O24: =IF(I24="","",IF(I24="R3","No","Sí")) -> No
A25: R-151 | B25: A-084 | C25: =IF(B25="","",IFERROR(INDEX('UNIVERSO MAESTRO'!$C$6:$C$497,MATCH(B25,'UNIVERSO MAESTRO'!$A$6:$A$497,0)),"⚠ ID no encontrado")) -> Liga MX | D25: =IF(B25="","",IFERROR(INDEX('UNIVERSO MAESTRO'!$D$6:$D$497,MATCH(B25,'UNIVERSO MAESTRO'!$A$6:$A$497,0)),"")) -> V1 | E25: A-018 | F25: =IF(E25="","",IFERROR(INDEX('UNIVERSO MAESTRO'!$C$6:$C$497,MATCH(E25,'UNIVERSO MAESTRO'!$A$6:$A$497,0)),"⚠ ID no encontrado")) -> CEMEX / Sinergia Deportiva | G25: =IF(E25="","",IFERROR(INDEX('UNIVERSO MAESTRO'!$D$6:$D$497,MATCH(E25,'UNIVERSO MAESTRO'!$A$6:$A$497,0)),"")) -> V9 | H25: Institutional / Regulatory | I25: R1 | J25: A→B | K25: Tigres UANL es uno de los 18 clubes miembros de Liga MX AC. Votó en la asamblea del 23-abr-2026. | L25: Tigres como miembro con voto relevante y relaciones comerciales propias. | M25: ligamx.net | N25: =IF(OR(B25="",E25=""),"",IF(D25=G25,"No","Sí")) -> Sí | O25: =IF(I25="","",IF(I25="R3","No","Sí")) -> Sí
A26: R-152 | B26: A-084 | C26: =IF(B26="","",IFERROR(INDEX('UNIVERSO MAESTRO'!$C$6:$C$497,MATCH(B26,'UNIVERSO MAESTRO'!$A$6:$A$497,0)),"⚠ ID no encontrado")) -> Liga MX | D26: =IF(B26="","",IFERROR(INDEX('UNIVERSO MAESTRO'!$D$6:$D$497,MATCH(B26,'UNIVERSO MAESTRO'!$A$6:$A$497,0)),"")) -> V1 | E26: A-021 | F26: =IF(E26="","",IFERROR(INDEX('UNIVERSO MAESTRO'!$C$6:$C$497,MATCH(E26,'UNIVERSO MAESTRO'!$A$6:$A$497,0)),"⚠ ID no encontrado")) -> Club Necaxa | G26: =IF(E26="","",IFERROR(INDEX('UNIVERSO MAESTRO'!$D$6:$D$497,MATCH(E26,'UNIVERSO MAESTRO'!$A$6:$A$497,0)),"")) -> V1 | H26: Institutional / Regulatory | I26: R3 | J26: A→B | K26: Necaxa es club miembro de Liga MX AC con accionistas norteamericanos. | M26: ligamx.net | N26: =IF(OR(B26="",E26=""),"",IF(D26=G26,"No","Sí")) -> No | O26: =IF(I26="","",IF(I26="R3","No","Sí")) -> No
A27: R-153 | B27: A-084 | C27: =IF(B27="","",IFERROR(INDEX('UNIVERSO MAESTRO'!$C$6:$C$497,MATCH(B27,'UNIVERSO MAESTRO'!$A$6:$A$497,0)),"⚠ ID no encontrado")) -> Liga MX | D27: =IF(B27="","",IFERROR(INDEX('UNIVERSO MAESTRO'!$D$6:$D$497,MATCH(B27,'UNIVERSO MAESTRO'!$A$6:$A$497,0)),"")) -> V1 | E27: A-022 | F27: =IF(E27="","",IFERROR(INDEX('UNIVERSO MAESTRO'!$C$6:$C$497,MATCH(E27,'UNIVERSO MAESTRO'!$A$6:$A$497,0)),"⚠ ID no encontrado")) -> Club Toluca | G27: =IF(E27="","",IFERROR(INDEX('UNIVERSO MAESTRO'!$D$6:$D$497,MATCH(E27,'UNIVERSO MAESTRO'!$A$6:$A$497,0)),"")) -> V1 | H27: Institutional / Regulatory | I27: R1 | J27: A→B | K27: Toluca es club miembro de Liga MX AC. La asamblea del 23-abr-2026 donde se aprobó la separación jurídica se celebró precisamente en Toluca. | L27: Toluca bicampeón 2025: miembro con relevancia comercial activa (Caliente jersey, New Balance). | M27: ligamx.net; asamblea Toluca abr-2026 | N27: =IF(OR(B27="",E27=""),"",IF(D27=G27,"No","Sí")) -> No | O27: =IF(I27="","",IF(I27="R3","No","Sí")) -> Sí
A28: R-154 | B28: A-084 | C28: =IF(B28="","",IFERROR(INDEX('UNIVERSO MAESTRO'!$C$6:$C$497,MATCH(B28,'UNIVERSO MAESTRO'!$A$6:$A$497,0)),"⚠ ID no encontrado")) -> Liga MX | D28: =IF(B28="","",IFERROR(INDEX('UNIVERSO MAESTRO'!$D$6:$D$497,MATCH(B28,'UNIVERSO MAESTRO'!$A$6:$A$497,0)),"")) -> V1 | E28: A-029 | F28: =IF(E28="","",IFERROR(INDEX('UNIVERSO MAESTRO'!$C$6:$C$497,MATCH(E28,'UNIVERSO MAESTRO'!$A$6:$A$497,0)),"⚠ ID no encontrado")) -> Cruz Azul FC | G28: =IF(E28="","",IFERROR(INDEX('UNIVERSO MAESTRO'!$D$6:$D$497,MATCH(E28,'UNIVERSO MAESTRO'!$A$6:$A$497,0)),"")) -> V1 | H28: Institutional / Regulatory | I28: R2 | J28: A→B | K28: Cruz Azul FC (sociedad cooperativa) es uno de los 18 clubes miembros de Liga MX AC. | M28: ligamx.net | N28: =IF(OR(B28="",E28=""),"",IF(D28=G28,"No","Sí")) -> No | O28: =IF(I28="","",IF(I28="R3","No","Sí")) -> Sí
A29: R-155 | B29: A-084 | C29: =IF(B29="","",IFERROR(INDEX('UNIVERSO MAESTRO'!$C$6:$C$497,MATCH(B29,'UNIVERSO MAESTRO'!$A$6:$A$497,0)),"⚠ ID no encontrado")) -> Liga MX | D29: =IF(B29="","",IFERROR(INDEX('UNIVERSO MAESTRO'!$D$6:$D$497,MATCH(B29,'UNIVERSO MAESTRO'!$A$6:$A$497,0)),"")) -> V1 | E29: A-044 | F29: =IF(E29="","",IFERROR(INDEX('UNIVERSO MAESTRO'!$C$6:$C$497,MATCH(E29,'UNIVERSO MAESTRO'!$A$6:$A$497,0)),"⚠ ID no encontrado")) -> FEMSA / Club de Fútbol Monterrey Rayados | G29: =IF(E29="","",IFERROR(INDEX('UNIVERSO MAESTRO'!$D$6:$D$497,MATCH(E29,'UNIVERSO MAESTRO'!$A$6:$A$497,0)),"")) -> V9 | H29: Institutional / Regulatory | I29: R1 | J29: A→B | K29: Rayados es uno de los 18 clubes miembros de Liga MX AC. FEMSA representa a Rayados en las asambleas de propietarios. | L29: Rayados como voto institucional con peso en asambleas y venue WC26. | M29: ligamx.net | N29: =IF(OR(B29="",E29=""),"",IF(D29=G29,"No","Sí")) -> Sí | O29: =IF(I29="","",IF(I29="R3","No","Sí")) -> Sí
A30: R-156 | B30: A-084 | C30: =IF(B30="","",IFERROR(INDEX('UNIVERSO MAESTRO'!$C$6:$C$497,MATCH(B30,'UNIVERSO MAESTRO'!$A$6:$A$497,0)),"⚠ ID no encontrado")) -> Liga MX | D30: =IF(B30="","",IFERROR(INDEX('UNIVERSO MAESTRO'!$D$6:$D$497,MATCH(B30,'UNIVERSO MAESTRO'!$A$6:$A$497,0)),"")) -> V1 | E30: A-058 | F30: =IF(E30="","",IFERROR(INDEX('UNIVERSO MAESTRO'!$C$6:$C$497,MATCH(E30,'UNIVERSO MAESTRO'!$A$6:$A$497,0)),"⚠ ID no encontrado")) -> Grupo Caliente / Corporación Caliente, S.A. de C.V. | G30: =IF(E30="","",IFERROR(INDEX('UNIVERSO MAESTRO'!$D$6:$D$497,MATCH(E30,'UNIVERSO MAESTRO'!$A$6:$A$497,0)),"")) -> V9 | H30: Institutional / Regulatory | I30: R3 | J30: A→B | K30: FC Juárez (Grupo Caliente) es club miembro de Liga MX AC. | M30: ligamx.net | N30: =IF(OR(B30="",E30=""),"",IF(D30=G30,"No","Sí")) -> Sí | O30: =IF(I30="","",IF(I30="R3","No","Sí")) -> No
A31: R-157 | B31: A-084 | C31: =IF(B31="","",IFERROR(INDEX('UNIVERSO MAESTRO'!$C$6:$C$497,MATCH(B31,'UNIVERSO MAESTRO'!$A$6:$A$497,0)),"⚠ ID no encontrado")) -> Liga MX | D31: =IF(B31="","",IFERROR(INDEX('UNIVERSO MAESTRO'!$D$6:$D$497,MATCH(B31,'UNIVERSO MAESTRO'!$A$6:$A$497,0)),"")) -> V1 | E31: A-061 | F31: =IF(E31="","",IFERROR(INDEX('UNIVERSO MAESTRO'!$C$6:$C$497,MATCH(E31,'UNIVERSO MAESTRO'!$A$6:$A$497,0)),"⚠ ID no encontrado")) -> Grupo Omnilife / Amaury Vergara / Chivas | G31: =IF(E31="","",IFERROR(INDEX('UNIVERSO MAESTRO'!$D$6:$D$497,MATCH(E31,'UNIVERSO MAESTRO'!$A$6:$A$497,0)),"")) -> V9 | H31: Institutional / Regulatory | I31: R1 | J31: A→B | K31: Chivas es uno de los 18 clubes miembros fundadores de Liga MX AC. Votó a favor de la separación jurídica FMF en la asamblea del 23-abr-2026. | M31: ligamx.net; asamblea abr-2026 | N31: =IF(OR(B31="",E31=""),"",IF(D31=G31,"No","Sí")) -> Sí | O31: =IF(I31="","",IF(I31="R3","No","Sí")) -> Sí
A32: R-158 | B32: A-084 | C32: =IF(B32="","",IFERROR(INDEX('UNIVERSO MAESTRO'!$C$6:$C$497,MATCH(B32,'UNIVERSO MAESTRO'!$A$6:$A$497,0)),"⚠ ID no encontrado")) -> Liga MX | D32: =IF(B32="","",IFERROR(INDEX('UNIVERSO MAESTRO'!$D$6:$D$497,MATCH(B32,'UNIVERSO MAESTRO'!$A$6:$A$497,0)),"")) -> V1 | E32: A-062 | F32: =IF(E32="","",IFERROR(INDEX('UNIVERSO MAESTRO'!$C$6:$C$497,MATCH(E32,'UNIVERSO MAESTRO'!$A$6:$A$497,0)),"⚠ ID no encontrado")) -> Grupo Orlegi | G32: =IF(E32="","",IFERROR(INDEX('UNIVERSO MAESTRO'!$D$6:$D$497,MATCH(E32,'UNIVERSO MAESTRO'!$A$6:$A$497,0)),"")) -> V9 | H32: Institutional / Regulatory | I32: R2 | J32: A→B | K32: Santos Laguna (Grupo Orlegi) es club miembro de Liga MX AC. | M32: ligamx.net | N32: =IF(OR(B32="",E32=""),"",IF(D32=G32,"No","Sí")) -> Sí | O32: =IF(I32="","",IF(I32="R3","No","Sí")) -> Sí
A33: R-159 | B33: A-084 | C33: =IF(B33="","",IFERROR(INDEX('UNIVERSO MAESTRO'!$C$6:$C$497,MATCH(B33,'UNIVERSO MAESTRO'!$A$6:$A$497,0)),"⚠ ID no encontrado")) -> Liga MX | D33: =IF(B33="","",IFERROR(INDEX('UNIVERSO MAESTRO'!$D$6:$D$497,MATCH(B33,'UNIVERSO MAESTRO'!$A$6:$A$497,0)),"")) -> V1 | E33: A-063 | F33: =IF(E33="","",IFERROR(INDEX('UNIVERSO MAESTRO'!$C$6:$C$497,MATCH(E33,'UNIVERSO MAESTRO'!$A$6:$A$497,0)),"⚠ ID no encontrado")) -> Grupo Pachuca | G33: =IF(E33="","",IFERROR(INDEX('UNIVERSO MAESTRO'!$D$6:$D$497,MATCH(E33,'UNIVERSO MAESTRO'!$A$6:$A$497,0)),"")) -> V9 | H33: Institutional / Regulatory | I33: R2 | J33: A→B | K33: Pachuca es club miembro de Liga MX AC, aunque la crisis judicial de Jesús Martínez introduce incertidumbre sobre la estabilidad de su voto. | M33: ligamx.net | N33: =IF(OR(B33="",E33=""),"",IF(D33=G33,"No","Sí")) -> Sí | O33: =IF(I33="","",IF(I33="R3","No","Sí")) -> Sí
A34: R-160 | B34: A-084 | C34: =IF(B34="","",IFERROR(INDEX('UNIVERSO MAESTRO'!$C$6:$C$497,MATCH(B34,'UNIVERSO MAESTRO'!$A$6:$A$497,0)),"⚠ ID no encontrado")) -> Liga MX | D34: =IF(B34="","",IFERROR(INDEX('UNIVERSO MAESTRO'!$D$6:$D$497,MATCH(B34,'UNIVERSO MAESTRO'!$A$6:$A$497,0)),"")) -> V1 | E34: A-064 | F34: =IF(E34="","",IFERROR(INDEX('UNIVERSO MAESTRO'!$C$6:$C$497,MATCH(E34,'UNIVERSO MAESTRO'!$A$6:$A$497,0)),"⚠ ID no encontrado")) -> Grupo PRODI / José Miguel Bejos | G34: =IF(E34="","",IFERROR(INDEX('UNIVERSO MAESTRO'!$D$6:$D$497,MATCH(E34,'UNIVERSO MAESTRO'!$A$6:$A$497,0)),"")) -> V9 | H34: Institutional / Regulatory | I34: R2 | J34: A→B | K34: Atlas FC (Grupo PRODI desde abr-2026) es club miembro de Liga MX AC. | M34: ligamx.net | N34: =IF(OR(B34="",E34=""),"",IF(D34=G34,"No","Sí")) -> Sí | O34: =IF(I34="","",IF(I34="R3","No","Sí")) -> Sí
A35: R-161 | B35: A-084 | C35: =IF(B35="","",IFERROR(INDEX('UNIVERSO MAESTRO'!$C$6:$C$497,MATCH(B35,'UNIVERSO MAESTRO'!$A$6:$A$497,0)),"⚠ ID no encontrado")) -> Liga MX | D35: =IF(B35="","",IFERROR(INDEX('UNIVERSO MAESTRO'!$D$6:$D$497,MATCH(B35,'UNIVERSO MAESTRO'!$A$6:$A$497,0)),"")) -> V1 | E35: A-065 | F35: =IF(E35="","",IFERROR(INDEX('UNIVERSO MAESTRO'!$C$6:$C$497,MATCH(E35,'UNIVERSO MAESTRO'!$A$6:$A$497,0)),"⚠ ID no encontrado")) -> Grupo Salinas / TV Azteca | G35: =IF(E35="","",IFERROR(INDEX('UNIVERSO MAESTRO'!$D$6:$D$497,MATCH(E35,'UNIVERSO MAESTRO'!$A$6:$A$497,0)),"")) -> V9 | H35: Institutional / Regulatory | I35: R3 | J35: A→B | K35: Club Puebla (Grupo Salinas, en venta) es club miembro de Liga MX AC. | M35: ligamx.net | N35: =IF(OR(B35="",E35=""),"",IF(D35=G35,"No","Sí")) -> Sí | O35: =IF(I35="","",IF(I35="R3","No","Sí")) -> No
A36: R-162 | B36: A-084 | C36: =IF(B36="","",IFERROR(INDEX('UNIVERSO MAESTRO'!$C$6:$C$497,MATCH(B36,'UNIVERSO MAESTRO'!$A$6:$A$497,0)),"⚠ ID no encontrado")) -> Liga MX | D36: =IF(B36="","",IFERROR(INDEX('UNIVERSO MAESTRO'!$D$6:$D$497,MATCH(B36,'UNIVERSO MAESTRO'!$A$6:$A$497,0)),"")) -> V1 | E36: A-076 | F36: =IF(E36="","",IFERROR(INDEX('UNIVERSO MAESTRO'!$C$6:$C$497,MATCH(E36,'UNIVERSO MAESTRO'!$A$6:$A$497,0)),"⚠ ID no encontrado")) -> Innovatio Capital / Club Querétaro | G36: =IF(E36="","",IFERROR(INDEX('UNIVERSO MAESTRO'!$D$6:$D$497,MATCH(E36,'UNIVERSO MAESTRO'!$A$6:$A$497,0)),"")) -> V9 | H36: Institutional / Regulatory | I36: R3 | J36: A→B | K36: Club Querétaro (Innovatio Capital/Marc Spiegel) es club miembro de Liga MX AC. | M36: ligamx.net | N36: =IF(OR(B36="",E36=""),"",IF(D36=G36,"No","Sí")) -> Sí | O36: =IF(I36="","",IF(I36="R3","No","Sí")) -> No
A37: R-163 | B37: A-084 | C37: =IF(B37="","",IFERROR(INDEX('UNIVERSO MAESTRO'!$C$6:$C$497,MATCH(B37,'UNIVERSO MAESTRO'!$A$6:$A$497,0)),"⚠ ID no encontrado")) -> Liga MX | D37: =IF(B37="","",IFERROR(INDEX('UNIVERSO MAESTRO'!$D$6:$D$497,MATCH(B37,'UNIVERSO MAESTRO'!$A$6:$A$497,0)),"")) -> V1 | E37: A-105 | F37: =IF(E37="","",IFERROR(INDEX('UNIVERSO MAESTRO'!$C$6:$C$497,MATCH(E37,'UNIVERSO MAESTRO'!$A$6:$A$497,0)),"⚠ ID no encontrado")) -> Ollamani, S.A.B. / Grupo Águilas (Club América + Estadio Banorte) | G37: =IF(E37="","",IFERROR(INDEX('UNIVERSO MAESTRO'!$D$6:$D$497,MATCH(E37,'UNIVERSO MAESTRO'!$A$6:$A$497,0)),"")) -> V9 | H37: Institutional / Regulatory | I37: R1 | J37: A→B | K37: Club América es uno de los 18 clubes miembros de Liga MX AC. Paga cuotas, participa en asambleas de dueños y somete al club a la reglamentación de la liga. | L37: América como miembro estructural de Liga MX AC: la relación constitutiva que otorga voz en asambleas y derechos de participación. | M37: ligamx.net; estatutos Liga MX | N37: =IF(OR(B37="",E37=""),"",IF(D37=G37,"No","Sí")) -> Sí | O37: =IF(I37="","",IF(I37="R3","No","Sí")) -> Sí
A38: R-164 | B38: A-084 | C38: =IF(B38="","",IFERROR(INDEX('UNIVERSO MAESTRO'!$C$6:$C$497,MATCH(B38,'UNIVERSO MAESTRO'!$A$6:$A$497,0)),"⚠ ID no encontrado")) -> Liga MX | D38: =IF(B38="","",IFERROR(INDEX('UNIVERSO MAESTRO'!$D$6:$D$497,MATCH(B38,'UNIVERSO MAESTRO'!$A$6:$A$497,0)),"")) -> V1 | E38: A-115 | F38: =IF(E38="","",IFERROR(INDEX('UNIVERSO MAESTRO'!$C$6:$C$497,MATCH(E38,'UNIVERSO MAESTRO'!$A$6:$A$497,0)),"⚠ ID no encontrado")) -> Pumas UNAM | G38: =IF(E38="","",IFERROR(INDEX('UNIVERSO MAESTRO'!$D$6:$D$497,MATCH(E38,'UNIVERSO MAESTRO'!$A$6:$A$497,0)),"")) -> V1 | H38: Institutional / Regulatory | I38: R2 | J38: A→B | K38: Pumas UNAM es club miembro de Liga MX AC. La UNAM vota en representación del club en las asambleas. | M38: ligamx.net | N38: =IF(OR(B38="",E38=""),"",IF(D38=G38,"No","Sí")) -> No | O38: =IF(I38="","",IF(I38="R3","No","Sí")) -> Sí
A39: R-177 | B39: A-102 | C39: =IF(B39="","",IFERROR(INDEX('UNIVERSO MAESTRO'!$C$6:$C$497,MATCH(B39,'UNIVERSO MAESTRO'!$A$6:$A$497,0)),"⚠ ID no encontrado")) -> NFL México City Games | D39: =IF(B39="","",IFERROR(INDEX('UNIVERSO MAESTRO'!$D$6:$D$497,MATCH(B39,'UNIVERSO MAESTRO'!$A$6:$A$497,0)),"")) -> V1 | E39: A-105 | F39: =IF(E39="","",IFERROR(INDEX('UNIVERSO MAESTRO'!$C$6:$C$497,MATCH(E39,'UNIVERSO MAESTRO'!$A$6:$A$497,0)),"⚠ ID no encontrado")) -> Ollamani, S.A.B. / Grupo Águilas (Club América + Estadio Banorte) | G39: =IF(E39="","",IFERROR(INDEX('UNIVERSO MAESTRO'!$D$6:$D$497,MATCH(E39,'UNIVERSO MAESTRO'!$A$6:$A$497,0)),"")) -> V9 | H39: Venue / Operations | I39: R2 | J39: A→B | K39: Acuerdo 2026-2028 NFL-Ollamani con 49ers como equipo local en Estadio Banorte. Primer NFL en el venue reabierto. | L39: Acuerdo 2026-2028 con 49ers como local: confirma Banorte como venue multi-liga, no solo fútbol mexicano. | M39: NFL.com; espn.com.mx | N39: =IF(OR(B39="",E39=""),"",IF(D39=G39,"No","Sí")) -> Sí | O39: =IF(I39="","",IF(I39="R3","No","Sí")) -> Sí
A40: R-194 | B40: A-115 | C40: =IF(B40="","",IFERROR(INDEX('UNIVERSO MAESTRO'!$C$6:$C$497,MATCH(B40,'UNIVERSO MAESTRO'!$A$6:$A$497,0)),"⚠ ID no encontrado")) -> Pumas UNAM | D40: =IF(B40="","",IFERROR(INDEX('UNIVERSO MAESTRO'!$D$6:$D$497,MATCH(B40,'UNIVERSO MAESTRO'!$A$6:$A$497,0)),"")) -> V1 | E40: A-039 | F40: =IF(E40="","",IFERROR(INDEX('UNIVERSO MAESTRO'!$C$6:$C$497,MATCH(E40,'UNIVERSO MAESTRO'!$A$6:$A$497,0)),"⚠ ID no encontrado")) -> Estadio Olímpico Universitario | G40: =IF(E40="","",IFERROR(INDEX('UNIVERSO MAESTRO'!$D$6:$D$497,MATCH(E40,'UNIVERSO MAESTRO'!$A$6:$A$497,0)),"")) -> V7 | H40: Ownership / Control | I40: R2 | J40: A→B | K40: UNAM propietaria del OEU y de Pumas. Mismo holding institucional. Estatus UNESCO impide adaptaciones mundialistas. | L40: UNAM propietaria del OEU y del club: integración venue-club sin deuda pero con restricciones institucionales que limitan la activación comercial. | M40: UNAM sitio oficial; ficha V7-010 | N40: =IF(OR(B40="",E40=""),"",IF(D40=G40,"No","Sí")) -> Sí | O40: =IF(I40="","",IF(I40="R3","No","Sí")) -> Sí
A41: R-195 | B41: A-115 | C41: =IF(B41="","",IFERROR(INDEX('UNIVERSO MAESTRO'!$C$6:$C$497,MATCH(B41,'UNIVERSO MAESTRO'!$A$6:$A$497,0)),"⚠ ID no encontrado")) -> Pumas UNAM | D41: =IF(B41="","",IFERROR(INDEX('UNIVERSO MAESTRO'!$D$6:$D$497,MATCH(B41,'UNIVERSO MAESTRO'!$A$6:$A$497,0)),"")) -> V1 | E41: A-039 | F41: =IF(E41="","",IFERROR(INDEX('UNIVERSO MAESTRO'!$C$6:$C$497,MATCH(E41,'UNIVERSO MAESTRO'!$A$6:$A$497,0)),"⚠ ID no encontrado")) -> Estadio Olímpico Universitario | G41: =IF(E41="","",IFERROR(INDEX('UNIVERSO MAESTRO'!$D$6:$D$497,MATCH(E41,'UNIVERSO MAESTRO'!$A$6:$A$497,0)),"")) -> V7 | H41: Venue / Operations | I41: R1 | J41: A→B | K41: Estadio Olímpico Universitario CU es la casa de Pumas UNAM, propiedad de la UNAM (entidad pública educativa). Estadio histórico de la Olimpiada 1968. Pumas opera como club universitario sin propiedad sobre el inmueble. | L41: P6-E. Cierra orfandad V7-010. Único caso Liga MX con estadio de propiedad universitaria pública. Sin posibilidad de naming rights ni desarrollo comercial agresivo (restricción institucional UNAM). | M41: [P6-E] Carga conceptual P6 para cerrar orfandad de actor Visualizable=Sí | N41: =IF(OR(B41="",E41=""),"",IF(D41=G41,"No","Sí")) -> Sí | O41: =IF(I41="","",IF(I41="R3","No","Sí")) -> Sí
A42: R-207 | B42: A-123 | C42: =IF(B42="","",IFERROR(INDEX('UNIVERSO MAESTRO'!$C$6:$C$497,MATCH(B42,'UNIVERSO MAESTRO'!$A$6:$A$497,0)),"⚠ ID no encontrado")) -> Selección Mexicana de Fútbol | D42: =IF(B42="","",IFERROR(INDEX('UNIVERSO MAESTRO'!$D$6:$D$497,MATCH(B42,'UNIVERSO MAESTRO'!$A$6:$A$497,0)),"")) -> V1 | E42: A-027 | F42: =IF(E42="","",IFERROR(INDEX('UNIVERSO MAESTRO'!$C$6:$C$497,MATCH(E42,'UNIVERSO MAESTRO'!$A$6:$A$497,0)),"⚠ ID no encontrado")) -> Copa Mundial FIFA 2026 en México | G42: =IF(E42="","",IFERROR(INDEX('UNIVERSO MAESTRO'!$D$6:$D$497,MATCH(E42,'UNIVERSO MAESTRO'!$A$6:$A$497,0)),"")) -> V1 | H42: Institutional / Regulatory | I42: R1 | J42: A→B | K42: México co-anfitrión del WC26. La Selección Mexicana juega su partido inaugural vs Sudáfrica el 11-jun-2026 en el Estadio Banorte. El Tri es el principal activo deportivo del evento en suelo mexicano. | M42: fmf.mx; fifa.com | N42: =IF(OR(B42="",E42=""),"",IF(D42=G42,"No","Sí")) -> No | O42: =IF(I42="","",IF(I42="R3","No","Sí")) -> Sí
A43: R-234 | B43: A-147 | C43: =IF(B43="","",IFERROR(INDEX('UNIVERSO MAESTRO'!$C$6:$C$497,MATCH(B43,'UNIVERSO MAESTRO'!$A$6:$A$497,0)),"⚠ ID no encontrado")) -> World Boxing Council (WBC) — sede CDMX | D43: =IF(B43="","",IFERROR(INDEX('UNIVERSO MAESTRO'!$D$6:$D$497,MATCH(B43,'UNIVERSO MAESTRO'!$A$6:$A$497,0)),"")) -> V1 | E43: A-016 | F43: =IF(E43="","",IFERROR(INDEX('UNIVERSO MAESTRO'!$C$6:$C$497,MATCH(E43,'UNIVERSO MAESTRO'!$A$6:$A$497,0)),"⚠ ID no encontrado")) -> Canelo Promotions / Saúl Álvarez | G43: =IF(E43="","",IFERROR(INDEX('UNIVERSO MAESTRO'!$D$6:$D$497,MATCH(E43,'UNIVERSO MAESTRO'!$A$6:$A$497,0)),"")) -> V1 | H43: Rights / Media | I43: R2 | J43: A→B | K43: WBC sanciona peleas Canelo Álvarez (cinturón verde WBC). Canelo histórico WBC champion múltiples categorías. | L43: WBC + Canelo: alianza simbólica del boxeo mexicano. Activo central narrativo. | M43: wbcboxing.com | canelo.com | N43: =IF(OR(B43="",E43=""),"",IF(D43=G43,"No","Sí")) -> No | O43: =IF(I43="","",IF(I43="R3","No","Sí")) -> Sí
A44: R-246 | B44: A-043 | C44: =IF(B44="","",IFERROR(INDEX('UNIVERSO MAESTRO'!$C$6:$C$497,MATCH(B44,'UNIVERSO MAESTRO'!$A$6:$A$497,0)),"⚠ ID no encontrado")) -> Federación Mexicana de Fútbol | D44: =IF(B44="","",IFERROR(INDEX('UNIVERSO MAESTRO'!$D$6:$D$497,MATCH(B44,'UNIVERSO MAESTRO'!$A$6:$A$497,0)),"")) -> V1 | E44: A-151 | F44: =IF(E44="","",IFERROR(INDEX('UNIVERSO MAESTRO'!$C$6:$C$497,MATCH(E44,'UNIVERSO MAESTRO'!$A$6:$A$497,0)),"⚠ ID no encontrado")) -> Liga BBVA MX Femenil | G44: =IF(E44="","",IFERROR(INDEX('UNIVERSO MAESTRO'!$D$6:$D$497,MATCH(E44,'UNIVERSO MAESTRO'!$A$6:$A$497,0)),"")) -> V1 | H44: Institutional / Regulatory | I44: R1 | J44: A→B | K44: Liga BBVA MX Femenil opera bajo el paraguas institucional de la FMF, similar a la relación FMF-Liga MX varonil. Mikel Arriola (Comisionado Presidente FMF) es decisor último de su agenda regulatoria y comercial. | L44: Cierra la cadena institucional FMF → Liga MX (varonil) + Liga MX Femenil; Mikel Arriola unifica gobernanza dual. | M44: fmf.mx; ligamxfemenil.net | N44: =IF(OR(B44="",E44=""),"",IF(D44=G44,"No","Sí")) -> No | O44: =IF(I44="","",IF(I44="R3","No","Sí")) -> Sí
A45: R-248 | B45: A-151 | C45: =IF(B45="","",IFERROR(INDEX('UNIVERSO MAESTRO'!$C$6:$C$497,MATCH(B45,'UNIVERSO MAESTRO'!$A$6:$A$497,0)),"⚠ ID no encontrado")) -> Liga BBVA MX Femenil | D45: =IF(B45="","",IFERROR(INDEX('UNIVERSO MAESTRO'!$D$6:$D$497,MATCH(B45,'UNIVERSO MAESTRO'!$A$6:$A$497,0)),"")) -> V1 | E45: A-124 | F45: =IF(E45="","",IFERROR(INDEX('UNIVERSO MAESTRO'!$C$6:$C$497,MATCH(E45,'UNIVERSO MAESTRO'!$A$6:$A$497,0)),"⚠ ID no encontrado")) -> Selección Mexicana Femenil | G45: =IF(E45="","",IFERROR(INDEX('UNIVERSO MAESTRO'!$D$6:$D$497,MATCH(E45,'UNIVERSO MAESTRO'!$A$6:$A$497,0)),"")) -> V1 | H45: Institutional / Regulatory | I45: R2 | J45: A→B | K45: Liga BBVA MX Femenil es la cantera estructural de la Selección Mexicana Femenil: las 18 plantillas alimentan al Tri Femenil de cara al Mundial Femenino 2027 (MX co-anfitrión). | L45: Activación dual con vista al Mundial 2027: el activo se valoriza tanto operativa como comercialmente en el ciclo 2026-2027. | M45: fmf.mx; concacaf.com | N45: =IF(OR(B45="",E45=""),"",IF(D45=G45,"No","Sí")) -> No | O45: =IF(I45="","",IF(I45="R3","No","Sí")) -> Sí
A46: R-249 | B46: A-151 | C46: =IF(B46="","",IFERROR(INDEX('UNIVERSO MAESTRO'!$C$6:$C$497,MATCH(B46,'UNIVERSO MAESTRO'!$A$6:$A$497,0)),"⚠ ID no encontrado")) -> Liga BBVA MX Femenil | D46: =IF(B46="","",IFERROR(INDEX('UNIVERSO MAESTRO'!$D$6:$D$497,MATCH(B46,'UNIVERSO MAESTRO'!$A$6:$A$497,0)),"")) -> V1 | E46: A-105 | F46: =IF(E46="","",IFERROR(INDEX('UNIVERSO MAESTRO'!$C$6:$C$497,MATCH(E46,'UNIVERSO MAESTRO'!$A$6:$A$497,0)),"⚠ ID no encontrado")) -> Ollamani, S.A.B. / Grupo Águilas (Club América + Estadio Banorte) | G46: =IF(E46="","",IFERROR(INDEX('UNIVERSO MAESTRO'!$D$6:$D$497,MATCH(E46,'UNIVERSO MAESTRO'!$A$6:$A$497,0)),"")) -> V9 | H46: Institutional / Regulatory | I46: R2 | J46: A→B | K46: América Femenil es club miembro de Liga BBVA MX Femenil (vía Ollamani, mismo holding que Club América varonil). Bicampeón Apertura 2023 + Apertura 2024. | L46: Modelo de membresía constitutiva: el holding padre (Ollamani) opera tanto el club varonil como el femenil, y Liga MX Femenil regula a ambos por separado. | M46: ligamxfemenil.net | N46: =IF(OR(B46="",E46=""),"",IF(D46=G46,"No","Sí")) -> Sí | O46: =IF(I46="","",IF(I46="R3","No","Sí")) -> Sí
A47: R-250 | B47: A-151 | C47: =IF(B47="","",IFERROR(INDEX('UNIVERSO MAESTRO'!$C$6:$C$497,MATCH(B47,'UNIVERSO MAESTRO'!$A$6:$A$497,0)),"⚠ ID no encontrado")) -> Liga BBVA MX Femenil | D47: =IF(B47="","",IFERROR(INDEX('UNIVERSO MAESTRO'!$D$6:$D$497,MATCH(B47,'UNIVERSO MAESTRO'!$A$6:$A$497,0)),"")) -> V1 | E47: A-018 | F47: =IF(E47="","",IFERROR(INDEX('UNIVERSO MAESTRO'!$C$6:$C$497,MATCH(E47,'UNIVERSO MAESTRO'!$A$6:$A$497,0)),"⚠ ID no encontrado")) -> CEMEX / Sinergia Deportiva | G47: =IF(E47="","",IFERROR(INDEX('UNIVERSO MAESTRO'!$D$6:$D$497,MATCH(E47,'UNIVERSO MAESTRO'!$A$6:$A$497,0)),"")) -> V9 | H47: Institutional / Regulatory | I47: R2 | J47: A→B | K47: Tigres UANL Femenil es club miembro de Liga BBVA MX Femenil (vía CEMEX/Sinergia Deportiva). Hexacampeón histórico de la liga (más títulos que cualquier otro club femenil). | L47: Tigres Femenil es el club más exitoso en historia de la liga: 6 títulos. CEMEX consolida franquicia femenil bajo el mismo holding del varonil. | M47: ligamxfemenil.net | N47: =IF(OR(B47="",E47=""),"",IF(D47=G47,"No","Sí")) -> Sí | O47: =IF(I47="","",IF(I47="R3","No","Sí")) -> Sí
A48: R-251 | B48: A-151 | C48: =IF(B48="","",IFERROR(INDEX('UNIVERSO MAESTRO'!$C$6:$C$497,MATCH(B48,'UNIVERSO MAESTRO'!$A$6:$A$497,0)),"⚠ ID no encontrado")) -> Liga BBVA MX Femenil | D48: =IF(B48="","",IFERROR(INDEX('UNIVERSO MAESTRO'!$D$6:$D$497,MATCH(B48,'UNIVERSO MAESTRO'!$A$6:$A$497,0)),"")) -> V1 | E48: A-044 | F48: =IF(E48="","",IFERROR(INDEX('UNIVERSO MAESTRO'!$C$6:$C$497,MATCH(E48,'UNIVERSO MAESTRO'!$A$6:$A$497,0)),"⚠ ID no encontrado")) -> FEMSA / Club de Fútbol Monterrey Rayados | G48: =IF(E48="","",IFERROR(INDEX('UNIVERSO MAESTRO'!$D$6:$D$497,MATCH(E48,'UNIVERSO MAESTRO'!$A$6:$A$497,0)),"")) -> V9 | H48: Institutional / Regulatory | I48: R2 | J48: A→B | K48: Rayadas de Monterrey es club miembro de Liga BBVA MX Femenil (vía FEMSA, mismo holding que Rayados varonil). Tetracampeón histórico de la liga. | L48: Rayadas son uno de los tres clubes con mayor inversión deportiva femenil en MX. Operación bajo FEMSA replica modelo industrial Rayados. | M48: ligamxfemenil.net | N48: =IF(OR(B48="",E48=""),"",IF(D48=G48,"No","Sí")) -> Sí | O48: =IF(I48="","",IF(I48="R3","No","Sí")) -> Sí
A49: R-252 | B49: A-151 | C49: =IF(B49="","",IFERROR(INDEX('UNIVERSO MAESTRO'!$C$6:$C$497,MATCH(B49,'UNIVERSO MAESTRO'!$A$6:$A$497,0)),"⚠ ID no encontrado")) -> Liga BBVA MX Femenil | D49: =IF(B49="","",IFERROR(INDEX('UNIVERSO MAESTRO'!$D$6:$D$497,MATCH(B49,'UNIVERSO MAESTRO'!$A$6:$A$497,0)),"")) -> V1 | E49: A-061 | F49: =IF(E49="","",IFERROR(INDEX('UNIVERSO MAESTRO'!$C$6:$C$497,MATCH(E49,'UNIVERSO MAESTRO'!$A$6:$A$497,0)),"⚠ ID no encontrado")) -> Grupo Omnilife / Amaury Vergara / Chivas | G49: =IF(E49="","",IFERROR(INDEX('UNIVERSO MAESTRO'!$D$6:$D$497,MATCH(E49,'UNIVERSO MAESTRO'!$A$6:$A$497,0)),"")) -> V9 | H49: Institutional / Regulatory | I49: R2 | J49: A→B | K49: Chivas Femenil es club miembro de Liga BBVA MX Femenil (vía Omnilife/Vergara). Bicampeón histórico (Clausura 2017 inaugural y Apertura 2022). | L49: Chivas Femenil es el club fundador de la era profesional (Clausura 2017 fue el primer torneo). Activo histórico bajo Omnilife. | M49: ligamxfemenil.net | N49: =IF(OR(B49="",E49=""),"",IF(D49=G49,"No","Sí")) -> Sí | O49: =IF(I49="","",IF(I49="R3","No","Sí")) -> Sí
A50: R-253 | B50: A-151 | C50: =IF(B50="","",IFERROR(INDEX('UNIVERSO MAESTRO'!$C$6:$C$497,MATCH(B50,'UNIVERSO MAESTRO'!$A$6:$A$497,0)),"⚠ ID no encontrado")) -> Liga BBVA MX Femenil | D50: =IF(B50="","",IFERROR(INDEX('UNIVERSO MAESTRO'!$D$6:$D$497,MATCH(B50,'UNIVERSO MAESTRO'!$A$6:$A$497,0)),"")) -> V1 | E50: A-063 | F50: =IF(E50="","",IFERROR(INDEX('UNIVERSO MAESTRO'!$C$6:$C$497,MATCH(E50,'UNIVERSO MAESTRO'!$A$6:$A$497,0)),"⚠ ID no encontrado")) -> Grupo Pachuca | G50: =IF(E50="","",IFERROR(INDEX('UNIVERSO MAESTRO'!$D$6:$D$497,MATCH(E50,'UNIVERSO MAESTRO'!$A$6:$A$497,0)),"")) -> V9 | H50: Institutional / Regulatory | I50: R2 | J50: A→B | K50: Pachuca Femenil es club miembro de Liga BBVA MX Femenil (vía Grupo Pachuca). Tetracampeón histórico, club bandera del proyecto Pachuca con cobertura deportiva integral. | L50: Pachuca Femenil es uno de los clubes más exitosos. Grupo Pachuca demuestra mayor inversión cross-género del ecosistema, con academias y rendimiento sostenido en ambas ramas. | M50: ligamxfemenil.net | N50: =IF(OR(B50="",E50=""),"",IF(D50=G50,"No","Sí")) -> Sí | O50: =IF(I50="","",IF(I50="R3","No","Sí")) -> Sí
A51: R-254 | B51: A-151 | C51: =IF(B51="","",IFERROR(INDEX('UNIVERSO MAESTRO'!$C$6:$C$497,MATCH(B51,'UNIVERSO MAESTRO'!$A$6:$A$497,0)),"⚠ ID no encontrado")) -> Liga BBVA MX Femenil | D51: =IF(B51="","",IFERROR(INDEX('UNIVERSO MAESTRO'!$D$6:$D$497,MATCH(B51,'UNIVERSO MAESTRO'!$A$6:$A$497,0)),"")) -> V1 | E51: A-064 | F51: =IF(E51="","",IFERROR(INDEX('UNIVERSO MAESTRO'!$C$6:$C$497,MATCH(E51,'UNIVERSO MAESTRO'!$A$6:$A$497,0)),"⚠ ID no encontrado")) -> Grupo PRODI / José Miguel Bejos | G51: =IF(E51="","",IFERROR(INDEX('UNIVERSO MAESTRO'!$D$6:$D$497,MATCH(E51,'UNIVERSO MAESTRO'!$A$6:$A$497,0)),"")) -> V9 | H51: Institutional / Regulatory | I51: R2 | J51: A→B | K51: Atlas Femenil es club miembro de Liga BBVA MX Femenil (vía Grupo PRODI / familia Bejos, mismo holding que Atlas varonil). | L51: R-13: la cobertura femenil se mapea como propiedad cross-género del holding/club padre ya cargado; relación membresía Liga MX Femenil ↔ propietario sin duplicar ficha standalone del equipo femenil. Cierra paridad metodológica con Liga MX varonil bajo E-02. | M51: ligamxfemenil.net; ligamx.net (clubes miembros oficiales Clausura 2026) | N51: =IF(OR(B51="",E51=""),"",IF(D51=G51,"No","Sí")) -> Sí | O51: =IF(I51="","",IF(I51="R3","No","Sí")) -> Sí
A52: R-255 | B52: A-151 | C52: =IF(B52="","",IFERROR(INDEX('UNIVERSO MAESTRO'!$C$6:$C$497,MATCH(B52,'UNIVERSO MAESTRO'!$A$6:$A$497,0)),"⚠ ID no encontrado")) -> Liga BBVA MX Femenil | D52: =IF(B52="","",IFERROR(INDEX('UNIVERSO MAESTRO'!$D$6:$D$497,MATCH(B52,'UNIVERSO MAESTRO'!$A$6:$A$497,0)),"")) -> V1 | E52: A-005 | F52: =IF(E52="","",IFERROR(INDEX('UNIVERSO MAESTRO'!$C$6:$C$497,MATCH(E52,'UNIVERSO MAESTRO'!$A$6:$A$497,0)),"⚠ ID no encontrado")) -> Apollo Sports Capital | G52: =IF(E52="","",IFERROR(INDEX('UNIVERSO MAESTRO'!$D$6:$D$497,MATCH(E52,'UNIVERSO MAESTRO'!$A$6:$A$497,0)),"")) -> V9 | H52: Institutional / Regulatory | I52: R2 | J52: A→B | K52: Atlético San Luis Femenil es club miembro de Liga BBVA MX Femenil (vía Apollo Sports Capital, mismo fondo que opera ASL varonil). Estadio Libertad Financiera (rebrand 2026) compartido con varonil. | L52: R-13: la cobertura femenil se mapea como propiedad cross-género del holding/club padre ya cargado; relación membresía Liga MX Femenil ↔ propietario sin duplicar ficha standalone del equipo femenil. Cierra paridad metodológica con Liga MX varonil bajo E-02. | M52: ligamxfemenil.net; ligamx.net (clubes miembros oficiales Clausura 2026) | N52: =IF(OR(B52="",E52=""),"",IF(D52=G52,"No","Sí")) -> Sí | O52: =IF(I52="","",IF(I52="R3","No","Sí")) -> Sí
A53: R-256 | B53: A-151 | C53: =IF(B53="","",IFERROR(INDEX('UNIVERSO MAESTRO'!$C$6:$C$497,MATCH(B53,'UNIVERSO MAESTRO'!$A$6:$A$497,0)),"⚠ ID no encontrado")) -> Liga BBVA MX Femenil | D53: =IF(B53="","",IFERROR(INDEX('UNIVERSO MAESTRO'!$D$6:$D$497,MATCH(B53,'UNIVERSO MAESTRO'!$A$6:$A$497,0)),"")) -> V1 | E53: A-029 | F53: =IF(E53="","",IFERROR(INDEX('UNIVERSO MAESTRO'!$C$6:$C$497,MATCH(E53,'UNIVERSO MAESTRO'!$A$6:$A$497,0)),"⚠ ID no encontrado")) -> Cruz Azul FC | G53: =IF(E53="","",IFERROR(INDEX('UNIVERSO MAESTRO'!$D$6:$D$497,MATCH(E53,'UNIVERSO MAESTRO'!$A$6:$A$497,0)),"")) -> V1 | H53: Institutional / Regulatory | I53: R2 | J53: A→B | K53: Cruz Azul Femenil es club miembro de Liga BBVA MX Femenil. Desde Clausura 2026 disputa partidos como local en Estadio Centenario de Cuernavaca (mientras varonil rota Banorte-Cuauhtémoc Puebla). | L53: R-13: la cobertura femenil se mapea como propiedad cross-género del holding/club padre ya cargado; relación membresía Liga MX Femenil ↔ propietario sin duplicar ficha standalone del equipo femenil. Cierra paridad metodológica con Liga MX varonil bajo E-02. | M53: ligamxfemenil.net; ligamx.net (clubes miembros oficiales Clausura 2026) | N53: =IF(OR(B53="",E53=""),"",IF(D53=G53,"No","Sí")) -> No | O53: =IF(I53="","",IF(I53="R3","No","Sí")) -> Sí
A54: R-257 | B54: A-151 | C54: =IF(B54="","",IFERROR(INDEX('UNIVERSO MAESTRO'!$C$6:$C$497,MATCH(B54,'UNIVERSO MAESTRO'!$A$6:$A$497,0)),"⚠ ID no encontrado")) -> Liga BBVA MX Femenil | D54: =IF(B54="","",IFERROR(INDEX('UNIVERSO MAESTRO'!$D$6:$D$497,MATCH(B54,'UNIVERSO MAESTRO'!$A$6:$A$497,0)),"")) -> V1 | E54: A-062 | F54: =IF(E54="","",IFERROR(INDEX('UNIVERSO MAESTRO'!$C$6:$C$497,MATCH(E54,'UNIVERSO MAESTRO'!$A$6:$A$497,0)),"⚠ ID no encontrado")) -> Grupo Orlegi | G54: =IF(E54="","",IFERROR(INDEX('UNIVERSO MAESTRO'!$D$6:$D$497,MATCH(E54,'UNIVERSO MAESTRO'!$A$6:$A$497,0)),"")) -> V9 | H54: Institutional / Regulatory | I54: R2 | J54: A→B | K54: Guerreras Santos Laguna Femenil es club miembro de Liga BBVA MX Femenil (vía Grupo Orlegi, mismo holding que Santos varonil + Atlas + Mazatlán). Verificar si Mazatlán Femenil también cae bajo Orlegi. | L54: R-13: la cobertura femenil se mapea como propiedad cross-género del holding/club padre ya cargado; relación membresía Liga MX Femenil ↔ propietario sin duplicar ficha standalone del equipo femenil. Cierra paridad metodológica con Liga MX varonil bajo E-02. | M54: ligamxfemenil.net; ligamx.net (clubes miembros oficiales Clausura 2026) | N54: =IF(OR(B54="",E54=""),"",IF(D54=G54,"No","Sí")) -> Sí | O54: =IF(I54="","",IF(I54="R3","No","Sí")) -> Sí
... A66: R-068 | B66: A-036 | C66: =IF(B66="","",IFERROR(INDEX('UNIVERSO MAESTRO'!$C$6:$C$497,MATCH(B66,'UNIVERSO MAESTRO'!$A$6:$A$497,0)),"⚠ ID no encontrado")) -> ESPN / Disney+ México | D66: =IF(B66="","",IFERROR(INDEX('UNIVERSO MAESTRO'!$D$6:$D$497,MATCH(B66,'UNIVERSO MAESTRO'!$A$6:$A$497,0)),"")) -> V2 | E66: A-084 | F66: =IF(E66="","",IFERROR(INDEX('UNIVERSO MAESTRO'!$C$6:$C$497,MATCH(E66,'UNIVERSO MAESTRO'!$A$6:$A$497,0)),"⚠ ID no encontrado")) -> Liga MX | G66: =IF(E66="","",IFERROR(INDEX('UNIVERSO MAESTRO'!$D$6:$D$497,MATCH(E66,'UNIVERSO MAESTRO'!$A$6:$A$497,0)),"")) -> V1 | H66: Rights / Media | I66: R2 | J66: A→B | K66: ESPN tiene derechos de transmisión de algunos clubes Liga MX (parciales), NBA México, NFL y Champions League en México. Bundle ViX+Disney+ desde jun-2025 (MXN 199/mes). | L66: ESPN tiene derechos parciales Liga MX más NBA/NFL/Champions: el bundle ViX+Disney+ hace esta relación más estratégica. | M66: espn.com.mx; disneyplus.com | N66: =IF(OR(B66="",E66=""),"",IF(D66=G66,"No","Sí")) -> Sí | O66: =IF(I66="","",IF(I66="R3","No","Sí")) -> Sí
A67: R-069 | B67: A-036 | C67: =IF(B67="","",IFERROR(INDEX('UNIVERSO MAESTRO'!$C$6:$C$497,MATCH(B67,'UNIVERSO MAESTRO'!$A$6:$A$497,0)),"⚠ ID no encontrado")) -> ESPN / Disney+ México | D67: =IF(B67="","",IFERROR(INDEX('UNIVERSO MAESTRO'!$D$6:$D$497,MATCH(B67,'UNIVERSO MAESTRO'!$A$6:$A$497,0)),"")) -> V2 | E67: A-137 | F67: =IF(E67="","",IFERROR(INDEX('UNIVERSO MAESTRO'!$C$6:$C$497,MATCH(E67,'UNIVERSO MAESTRO'!$A$6:$A$497,0)),"⚠ ID no encontrado")) -> TelevisaUnivision | G67: =IF(E67="","",IFERROR(INDEX('UNIVERSO MAESTRO'!$D$6:$D$497,MATCH(E67,'UNIVERSO MAESTRO'!$A$6:$A$497,0)),"")) -> V2 | H67: Rights / Media | I67: R3 | J67: A→B | K67: Bundle ViX+Disney+ desde jun-2025 (MXN 199/mes) crea alianza de distribución streaming entre competidores. La alianza es la más relevante del mercado streaming en 2025-26. | M67: espn.com.mx; expansión.mx | N67: =IF(OR(B67="",E67=""),"",IF(D67=G67,"No","Sí")) -> No | O67: =IF(I67="","",IF(I67="R3","No","Sí")) -> No
A68: R-070 | B68: A-036 | C68: =IF(B68="","",IFERROR(INDEX('UNIVERSO MAESTRO'!$C$6:$C$497,MATCH(B68,'UNIVERSO MAESTRO'!$A$6:$A$497,0)),"⚠ ID no encontrado")) -> ESPN / Disney+ México | D68: =IF(B68="","",IFERROR(INDEX('UNIVERSO MAESTRO'!$D$6:$D$497,MATCH(B68,'UNIVERSO MAESTRO'!$A$6:$A$497,0)),"")) -> V2 | E68: A-137 | F68: =IF(E68="","",IFERROR(INDEX('UNIVERSO MAESTRO'!$C$6:$C$497,MATCH(E68,'UNIVERSO MAESTRO'!$A$6:$A$497,0)),"⚠ ID no encontrado")) -> TelevisaUnivision | G68: =IF(E68="","",IFERROR(INDEX('UNIVERSO MAESTRO'!$D$6:$D$497,MATCH(E68,'UNIVERSO MAESTRO'!$A$6:$A$497,0)),"")) -> V2 | H68: Agency / Intermediation | I68: R2 | J68: A→B | K68: Bundle ViX+Disney+ lanzado jun-2025 (MXN 199/mes). La alianza de distribución más relevante del ecosistema streaming deportivo en México 2025-2026. Complementan portafolios: ViX (Liga MX, WC26) + Disney+ (NBA, NFL, Champions). | L68: Bundle ViX+Disney+ lanzado jun-2025: la alianza de distribución más relevante del ecosistema streaming en México. | M68: televisaunivision.com; disneyplus.com; expansión.mx | N68: =IF(OR(B68="",E68=""),"",IF(D68=G68,"No","Sí")) -> No | O68: =IF(I68="","",IF(I68="R3","No","Sí")) -> Sí
A69: R-090 | B69: A-047 | C69: =IF(B69="","",IFERROR(INDEX('UNIVERSO MAESTRO'!$C$6:$C$497,MATCH(B69,'UNIVERSO MAESTRO'!$A$6:$A$497,0)),"⚠ ID no encontrado")) -> Fox Corporation / FOX One / Tubi México | D69: =IF(B69="","",IFERROR(INDEX('UNIVERSO MAESTRO'!$D$6:$D$497,MATCH(B69,'UNIVERSO MAESTRO'!$A$6:$A$497,0)),"")) -> V2 | E69: A-018 | F69: =IF(E69="","",IFERROR(INDEX('UNIVERSO MAESTRO'!$C$6:$C$497,MATCH(E69,'UNIVERSO MAESTRO'!$A$6:$A$497,0)),"⚠ ID no encontrado")) -> CEMEX / Sinergia Deportiva | G69: =IF(E69="","",IFERROR(INDEX('UNIVERSO MAESTRO'!$D$6:$D$497,MATCH(E69,'UNIVERSO MAESTRO'!$A$6:$A$497,0)),"")) -> V9 | H69: Rights / Media | I69: R2 | J69: A→B | K69: Fox Corporation transmite Tigres via FOX One tras compra de Caliente TV jun-2025. | L69: Fox transmite Tigres vía Caliente TV: los dos clubs del norte más grandes bajo el mismo broadcaster post-adquisición. | M69: fastcompany.mx; ficha V2-003 | N69: =IF(OR(B69="",E69=""),"",IF(D69=G69,"No","Sí")) -> Sí | O69: =IF(I69="","",IF(I69="R3","No","Sí")) -> Sí
A70: R-091 | B70: A-047 | C70: =IF(B70="","",IFERROR(INDEX('UNIVERSO MAESTRO'!$C$6:$C$497,MATCH(B70,'UNIVERSO MAESTRO'!$A$6:$A$497,0)),"⚠ ID no encontrado")) -> Fox Corporation / FOX One / Tubi México | D70: =IF(B70="","",IFERROR(INDEX('UNIVERSO MAESTRO'!$D$6:$D$497,MATCH(B70,'UNIVERSO MAESTRO'!$A$6:$A$497,0)),"")) -> V2 | E70: A-044 | F70: =IF(E70="","",IFERROR(INDEX('UNIVERSO MAESTRO'!$C$6:$C$497,MATCH(E70,'UNIVERSO MAESTRO'!$A$6:$A$497,0)),"⚠ ID no encontrado")) -> FEMSA / Club de Fútbol Monterrey Rayados | G70: =IF(E70="","",IFERROR(INDEX('UNIVERSO MAESTRO'!$D$6:$D$497,MATCH(E70,'UNIVERSO MAESTRO'!$A$6:$A$497,0)),"")) -> V9 | H70: Rights / Media | I70: R2 | J70: A→B | K70: Fox Corporation heredó derechos de Rayados via compra Caliente TV jun-2025. FOX One transmite partidos de Rayados en casa. | L70: Fox heredó derechos de Rayados vía Caliente TV jun-2025: el club más valioso del norte bajo el nuevo broadcaster que desplazó a Televisa. | M70: fastcompany.mx; ficha V2-003 | N70: =IF(OR(B70="",E70=""),"",IF(D70=G70,"No","Sí")) -> Sí | O70: =IF(I70="","",IF(I70="R3","No","Sí")) -> Sí
A71: R-092 | B71: A-047 | C71: =IF(B71="","",IFERROR(INDEX('UNIVERSO MAESTRO'!$C$6:$C$497,MATCH(B71,'UNIVERSO MAESTRO'!$A$6:$A$497,0)),"⚠ ID no encontrado")) -> Fox Corporation / FOX One / Tubi México | D71: =IF(B71="","",IFERROR(INDEX('UNIVERSO MAESTRO'!$D$6:$D$497,MATCH(B71,'UNIVERSO MAESTRO'!$A$6:$A$497,0)),"")) -> V2 | E71: A-058 | F71: =IF(E71="","",IFERROR(INDEX('UNIVERSO MAESTRO'!$C$6:$C$497,MATCH(E71,'UNIVERSO MAESTRO'!$A$6:$A$497,0)),"⚠ ID no encontrado")) -> Grupo Caliente / Corporación Caliente, S.A. de C.V. | G71: =IF(E71="","",IFERROR(INDEX('UNIVERSO MAESTRO'!$D$6:$D$497,MATCH(E71,'UNIVERSO MAESTRO'!$A$6:$A$497,0)),"")) -> V9 | H71: Ownership / Control | I71: R1 | J71: A→B | K71: Fox Corporation adquirió Caliente TV (la señal de TV de Grupo Caliente) en jun-2025. La compra fue la vía de entrada de Fox Corp al mercado mexicano de medios deportivos, adquiriendo simultáneamente derechos Liga MX de varios clubes. [M-01 nota: A=Fox como adquirente; B=Grupo Caliente como vendedor del activo Caliente TV. Excepción a M-01 estándar de Ownership porque la transacción es venta de subsidiaria, no relación de propiedad permanente.] | L71: Fox adquirió Caliente TV jun-2025: la vía de entrada de Fox al ecosistema de derechos Liga MX. | M71: fastcompany.mx; foxcorporation.com jun-2025 | N71: =IF(OR(B71="",E71=""),"",IF(D71=G71,"No","Sí")) -> Sí | O71: =IF(I71="","",IF(I71="R3","No","Sí")) -> Sí
A72: R-093 | B72: A-047 | C72: =IF(B72="","",IFERROR(INDEX('UNIVERSO MAESTRO'!$C$6:$C$497,MATCH(B72,'UNIVERSO MAESTRO'!$A$6:$A$497,0)),"⚠ ID no encontrado")) -> Fox Corporation / FOX One / Tubi México | D72: =IF(B72="","",IFERROR(INDEX('UNIVERSO MAESTRO'!$D$6:$D$497,MATCH(B72,'UNIVERSO MAESTRO'!$A$6:$A$497,0)),"")) -> V2 | E72: A-063 | F72: =IF(E72="","",IFERROR(INDEX('UNIVERSO MAESTRO'!$C$6:$C$497,MATCH(E72,'UNIVERSO MAESTRO'!$A$6:$A$497,0)),"⚠ ID no encontrado")) -> Grupo Pachuca | G72: =IF(E72="","",IFERROR(INDEX('UNIVERSO MAESTRO'!$D$6:$D$497,MATCH(E72,'UNIVERSO MAESTRO'!$A$6:$A$497,0)),"")) -> V9 | H72: Rights / Media | I72: R2 | J72: A→B | K72: Fox One/Tubi transmite a Pachuca desde adquisición de Caliente TV por Fox Corp en jun-2025. | M72: ficha V1-011; fastcompany.mx | N72: =IF(OR(B72="",E72=""),"",IF(D72=G72,"No","Sí")) -> Sí | O72: =IF(I72="","",IF(I72="R3","No","Sí")) -> Sí
A73: R-094 | B73: A-047 | C73: =IF(B73="","",IFERROR(INDEX('UNIVERSO MAESTRO'!$C$6:$C$497,MATCH(B73,'UNIVERSO MAESTRO'!$A$6:$A$497,0)),"⚠ ID no encontrado")) -> Fox Corporation / FOX One / Tubi México | D73: =IF(B73="","",IFERROR(INDEX('UNIVERSO MAESTRO'!$D$6:$D$497,MATCH(B73,'UNIVERSO MAESTRO'!$A$6:$A$497,0)),"")) -> V2 | E73: A-137 | F73: =IF(E73="","",IFERROR(INDEX('UNIVERSO MAESTRO'!$C$6:$C$497,MATCH(E73,'UNIVERSO MAESTRO'!$A$6:$A$497,0)),"⚠ ID no encontrado")) -> TelevisaUnivision | G73: =IF(E73="","",IFERROR(INDEX('UNIVERSO MAESTRO'!$D$6:$D$497,MATCH(E73,'UNIVERSO MAESTRO'!$A$6:$A$497,0)),"")) -> V2 | H73: Rights / Media | I73: R2 | J73: A→B | K73: Fox Corp y TelevisaUnivision compiten directamente por los derechos de transmisión de Liga MX en México. Fox Corp entró al mercado comprando Caliente TV (jun-2025), disrruptiendo la histórica distribución TUDN-dominada. | M73: fastcompany.mx; espn.com.mx | N73: =IF(OR(B73="",E73=""),"",IF(D73=G73,"No","Sí")) -> No | O73: =IF(I73="","",IF(I73="R3","No","Sí")) -> Sí
A74: R-095 | B74: A-048 | C74: =IF(B74="","",IFERROR(INDEX('UNIVERSO MAESTRO'!$C$6:$C$497,MATCH(B74,'UNIVERSO MAESTRO'!$A$6:$A$497,0)),"⚠ ID no encontrado")) -> Fox Sports México / Grupo Lauman | D74: =IF(B74="","",IFERROR(INDEX('UNIVERSO MAESTRO'!$D$6:$D$497,MATCH(B74,'UNIVERSO MAESTRO'!$A$6:$A$497,0)),"")) -> V2 | E74: A-047 | F74: =IF(E74="","",IFERROR(INDEX('UNIVERSO MAESTRO'!$C$6:$C$497,MATCH(E74,'UNIVERSO MAESTRO'!$A$6:$A$497,0)),"⚠ ID no encontrado")) -> Fox Corporation / FOX One / Tubi México | G74: =IF(E74="","",IFERROR(INDEX('UNIVERSO MAESTRO'!$D$6:$D$497,MATCH(E74,'UNIVERSO MAESTRO'!$A$6:$A$497,0)),"")) -> V2 | H74: Ownership / Control | I74: R1 | J74: A→B | K74: Fox Sports México (Grupo Lauman) es el licenciatario en colapso de la marca Fox Sports en México. Fox Corporation entró directamente (Tubi + FOX One) desplazando a Lauman. Relación: desplazamiento del licenciatario por el licenciante. | L74: Fox Sports México (Lauman) en colapso como licenciatario: Fox Corp opera directamente desplazando al licenciatario local. La transición broadcaster más relevante del mercado en 2026. | M74: expansión.mx; mediotiempo.com | N74: =IF(OR(B74="",E74=""),"",IF(D74=G74,"No","Sí")) -> No | O74: =IF(I74="","",IF(I74="R3","No","Sí")) -> Sí
A75: R-167 | B75: A-090 | C75: =IF(B75="","",IFERROR(INDEX('UNIVERSO MAESTRO'!$C$6:$C$497,MATCH(B75,'UNIVERSO MAESTRO'!$A$6:$A$497,0)),"⚠ ID no encontrado")) -> Max / HBO Max Warner Bros. Discovery | D75: =IF(B75="","",IFERROR(INDEX('UNIVERSO MAESTRO'!$D$6:$D$497,MATCH(B75,'UNIVERSO MAESTRO'!$A$6:$A$497,0)),"")) -> V2 | E75: A-084 | F75: =IF(E75="","",IFERROR(INDEX('UNIVERSO MAESTRO'!$C$6:$C$497,MATCH(E75,'UNIVERSO MAESTRO'!$A$6:$A$497,0)),"⚠ ID no encontrado")) -> Liga MX | G75: =IF(E75="","",IFERROR(INDEX('UNIVERSO MAESTRO'!$D$6:$D$497,MATCH(E75,'UNIVERSO MAESTRO'!$A$6:$A$497,0)),"")) -> V1 | H75: Rights / Media | I75: R2 | J75: A→B | K75: Max es uno de los broadcasters de la UEFA Champions League en México (compartida con ESPN/Disney+). La Champions League es el producto europeo con mayor audiencia en México. | L75: Max tiene derechos compartidos de Champions League en México (con ESPN): el tercer broadcaster premium de fútbol internacional en el ecosistema. Señal de fragmentación de derechos. | M75: max.com; espn.com.mx | N75: =IF(OR(B75="",E75=""),"",IF(D75=G75,"No","Sí")) -> Sí | O75: =IF(I75="","",IF(I75="R3","No","Sí")) -> Sí
A76: R-174 | B76: A-100 | C76: =IF(B76="","",IFERROR(INDEX('UNIVERSO MAESTRO'!$C$6:$C$497,MATCH(B76,'UNIVERSO MAESTRO'!$A$6:$A$497,0)),"⚠ ID no encontrado")) -> Netflix México | D76: =IF(B76="","",IFERROR(INDEX('UNIVERSO MAESTRO'!$D$6:$D$497,MATCH(B76,'UNIVERSO MAESTRO'!$A$6:$A$497,0)),"")) -> V2 | E76: A-043 | F76: =IF(E76="","",IFERROR(INDEX('UNIVERSO MAESTRO'!$C$6:$C$497,MATCH(E76,'UNIVERSO MAESTRO'!$A$6:$A$497,0)),"⚠ ID no encontrado")) -> Federación Mexicana de Fútbol | G76: =IF(E76="","",IFERROR(INDEX('UNIVERSO MAESTRO'!$D$6:$D$497,MATCH(E76,'UNIVERSO MAESTRO'!$A$6:$A$497,0)),"")) -> V1 | H76: Rights / Media | I76: R1 | J76: A→B | K76: Netflix firmó primer acuerdo exclusivo Concacaf-México (Copa Oro + Nations League Finals 2027-29) el 14-abr-2026. El Tri detrás de paywall CONCACAF por primera vez. | L76: Netflix firmó primer acuerdo exclusivo CONCACAF/México (Copa Oro + Nations League 2027-29): el streaming puro ya entró al fútbol mexicano. | M76: ESPN; mediotiempo.com; concacaf.com — abr-2026 | N76: =IF(OR(B76="",E76=""),"",IF(D76=G76,"No","Sí")) -> Sí | O76: =IF(I76="","",IF(I76="R3","No","Sí")) -> Sí
A77: R-175 | B77: A-100 | C77: =IF(B77="","",IFERROR(INDEX('UNIVERSO MAESTRO'!$C$6:$C$497,MATCH(B77,'UNIVERSO MAESTRO'!$A$6:$A$497,0)),"⚠ ID no encontrado")) -> Netflix México | D77: =IF(B77="","",IFERROR(INDEX('UNIVERSO MAESTRO'!$D$6:$D$497,MATCH(B77,'UNIVERSO MAESTRO'!$A$6:$A$497,0)),"")) -> V2 | E77: A-137 | F77: =IF(E77="","",IFERROR(INDEX('UNIVERSO MAESTRO'!$C$6:$C$497,MATCH(E77,'UNIVERSO MAESTRO'!$A$6:$A$497,0)),"⚠ ID no encontrado")) -> TelevisaUnivision | G77: =IF(E77="","",IFERROR(INDEX('UNIVERSO MAESTRO'!$D$6:$D$497,MATCH(E77,'UNIVERSO MAESTRO'!$A$6:$A$497,0)),"")) -> V2 | H77: Rights / Media | I77: R2 | J77: A→B | K77: Netflix compite con TUDN/ViX por el mercado de streaming deportivo mexicano. El deal Netflix-Concacaf (abr-2026) pone torneos de El Tri detrás de paywall Netflix, erosionando la exclusividad histórica de TUDN. | M77: espn.com.mx; netflix.com; mediotiempo.com | N77: =IF(OR(B77="",E77=""),"",IF(D77=G77,"No","Sí")) -> No | O77: =IF(I77="","",IF(I77="R3","No","Sí")) -> Sí
A78: R-184 | B78: A-109 | C78: =IF(B78="","",IFERROR(INDEX('UNIVERSO MAESTRO'!$C$6:$C$497,MATCH(B78,'UNIVERSO MAESTRO'!$A$6:$A$497,0)),"⚠ ID no encontrado")) -> Paramount+ / Pluto TV | D78: =IF(B78="","",IFERROR(INDEX('UNIVERSO MAESTRO'!$D$6:$D$497,MATCH(B78,'UNIVERSO MAESTRO'!$A$6:$A$497,0)),"")) -> V2 | E78: A-035 | F78: =IF(E78="","",IFERROR(INDEX('UNIVERSO MAESTRO'!$C$6:$C$497,MATCH(E78,'UNIVERSO MAESTRO'!$A$6:$A$497,0)),"⚠ ID no encontrado")) -> Endeavor / WME Group | G78: =IF(E78="","",IFERROR(INDEX('UNIVERSO MAESTRO'!$D$6:$D$497,MATCH(E78,'UNIVERSO MAESTRO'!$A$6:$A$497,0)),"")) -> V9 | H78: Rights / Media | I78: R2 | J78: A→B | K78: Paramount+ es broadcaster exclusivo de UFC en Latinoamérica desde oct-2025. El deal desplazó a ESPN/Disney. Pluto TV como canal AVOD gratuito complementario. | L78: Paramount+ es broadcaster exclusivo de UFC en LatAm desde oct-2025: señal de que el streaming puro ya controla derechos MMA en México. | M78: ufc.com; paramountplus.com | N78: =IF(OR(B78="",E78=""),"",IF(D78=G78,"No","Sí")) -> Sí | O78: =IF(I78="","",IF(I78="R3","No","Sí")) -> Sí
A79: R-210 | B79: A-127 | C79: =IF(B79="","",IFERROR(INDEX('UNIVERSO MAESTRO'!$C$6:$C$497,MATCH(B79,'UNIVERSO MAESTRO'!$A$6:$A$497,0)),"⚠ ID no encontrado")) -> Sky Sports México / NBCUniversal | D79: =IF(B79="","",IFERROR(INDEX('UNIVERSO MAESTRO'!$D$6:$D$497,MATCH(B79,'UNIVERSO MAESTRO'!$A$6:$A$497,0)),"")) -> V2 | E79: A-055 | F79: =IF(E79="","",IFERROR(INDEX('UNIVERSO MAESTRO'!$C$6:$C$497,MATCH(E79,'UNIVERSO MAESTRO'!$A$6:$A$497,0)),"⚠ ID no encontrado")) -> Gran Premio de México — Fórmula 1 | G79: =IF(E79="","",IFERROR(INDEX('UNIVERSO MAESTRO'!$D$6:$D$497,MATCH(E79,'UNIVERSO MAESTRO'!$A$6:$A$497,0)),"")) -> V1 | H79: Rights / Media | I79: R2 | J79: A→B | K79: Sky Sports tiene derechos F1 en México 2025-2028 (desde GP Singapur 2025). Único broadcaster TV paga con cobertura completa del GP México. | L79: Sky Sports tiene derechos F1 en México 2025-2028: el único broadcaster TV paga con cobertura completa del GP. | M79: sky.com.mx; formula1.com | N79: =IF(OR(B79="",E79=""),"",IF(D79=G79,"No","Sí")) -> Sí | O79: =IF(I79="","",IF(I79="R3","No","Sí")) -> Sí
A80: R-218 | B80: A-137 | C80: =IF(B80="","",IFERROR(INDEX('UNIVERSO MAESTRO'!$C$6:$C$497,MATCH(B80,'UNIVERSO MAESTRO'!$A$6:$A$497,0)),"⚠ ID no encontrado")) -> TelevisaUnivision | D80: =IF(B80="","",IFERROR(INDEX('UNIVERSO MAESTRO'!$D$6:$D$497,MATCH(B80,'UNIVERSO MAESTRO'!$A$6:$A$497,0)),"")) -> V2 | E80: A-002 | F80: =IF(E80="","",IFERROR(INDEX('UNIVERSO MAESTRO'!$C$6:$C$497,MATCH(E80,'UNIVERSO MAESTRO'!$A$6:$A$497,0)),"⚠ ID no encontrado")) -> Akta Cloud Video Platform | G80: =IF(E80="","",IFERROR(INDEX('UNIVERSO MAESTRO'!$D$6:$D$497,MATCH(E80,'UNIVERSO MAESTRO'!$A$6:$A$497,0)),"")) -> V8 | H80: Data / Fan Intelligence | I80: R1 | J80: A→B | K80: Akta es el stack OTT real que opera ViX (TelevisaUnivision). Construido en 9 meses con ~150 ingenieros y Google Cloud bajo Michael Cerda. | L80: Akta es el stack OTT real que opera ViX: construido en 9 meses sobre Google Cloud. Quien quiera entender cómo Liga MX llega al streaming en México entiende primero a Akta. | M80: businesswire.com oct-2023; akta.tech | N80: =IF(OR(B80="",E80=""),"",IF(D80=G80,"No","Sí")) -> Sí | O80: =IF(I80="","",IF(I80="R3","No","Sí")) -> Sí
A81: R-219 | B81: A-137 | C81: =IF(B81="","",IFERROR(INDEX('UNIVERSO MAESTRO'!$C$6:$C$497,MATCH(B81,'UNIVERSO MAESTRO'!$A$6:$A$497,0)),"⚠ ID no encontrado")) -> TelevisaUnivision | D81: =IF(B81="","",IFERROR(INDEX('UNIVERSO MAESTRO'!$D$6:$D$497,MATCH(B81,'UNIVERSO MAESTRO'!$A$6:$A$497,0)),"")) -> V2 | E81: A-027 | F81: =IF(E81="","",IFERROR(INDEX('UNIVERSO MAESTRO'!$C$6:$C$497,MATCH(E81,'UNIVERSO MAESTRO'!$A$6:$A$497,0)),"⚠ ID no encontrado")) -> Copa Mundial FIFA 2026 en México | G81: =IF(E81="","",IFERROR(INDEX('UNIVERSO MAESTRO'!$D$6:$D$497,MATCH(E81,'UNIVERSO MAESTRO'!$A$6:$A$497,0)),"")) -> V1 | H81: Rights / Media | I81: R1 | J81: A→B | K81: TelevisaUnivision/ViX Premium tiene los derechos exclusivos de los 104 partidos WC26 en territorio mexicano. El deal más importante de derechos deportivos en la historia de México. | L81: TUDN/ViX Premium tiene los derechos exclusivos de los 104 partidos WC26 en territorio mexicano: el deal de broadcasting más valioso del ecosistema en 2026. | M81: televisaunivision.com; fifa.com; dpln.news | N81: =IF(OR(B81="",E81=""),"",IF(D81=G81,"No","Sí")) -> Sí | O81: =IF(I81="","",IF(I81="R3","No","Sí")) -> Sí
A82: R-220 | B82: A-137 | C82: =IF(B82="","",IFERROR(INDEX('UNIVERSO MAESTRO'!$C$6:$C$497,MATCH(B82,'UNIVERSO MAESTRO'!$A$6:$A$497,0)),"⚠ ID no encontrado")) -> TelevisaUnivision | D82: =IF(B82="","",IFERROR(INDEX('UNIVERSO MAESTRO'!$D$6:$D$497,MATCH(B82,'UNIVERSO MAESTRO'!$A$6:$A$497,0)),"")) -> V2 | E82: A-061 | F82: =IF(E82="","",IFERROR(INDEX('UNIVERSO MAESTRO'!$C$6:$C$497,MATCH(E82,'UNIVERSO MAESTRO'!$A$6:$A$497,0)),"⚠ ID no encontrado")) -> Grupo Omnilife / Amaury Vergara / Chivas | G82: =IF(E82="","",IFERROR(INDEX('UNIVERSO MAESTRO'!$D$6:$D$497,MATCH(E82,'UNIVERSO MAESTRO'!$A$6:$A$497,0)),"")) -> V9 | H82: Rights / Media | I82: R1 | J82: A→B | K82: TUDN tiene derechos de Chivas en señal abierta. Amazon Prime Video tiene los partidos en casa de Chivas exclusivos. | L82: TUDN tiene señal abierta de Chivas: coexiste con Amazon creando un modelo dual único en Liga MX. | M82: tudn.com; televisaunivision.com | N82: =IF(OR(B82="",E82=""),"",IF(D82=G82,"No","Sí")) -> Sí | O82: =IF(I82="","",IF(I82="R3","No","Sí")) -> Sí
A83: R-221 | B83: A-137 | C83: =IF(B83="","",IFERROR(INDEX('UNIVERSO MAESTRO'!$C$6:$C$497,MATCH(B83,'UNIVERSO MAESTRO'!$A$6:$A$497,0)),"⚠ ID no encontrado")) -> TelevisaUnivision | D83: =IF(B83="","",IFERROR(INDEX('UNIVERSO MAESTRO'!$D$6:$D$497,MATCH(B83,'UNIVERSO MAESTRO'!$A$6:$A$497,0)),"")) -> V2 | E83: A-084 | F83: =IF(E83="","",IFERROR(INDEX('UNIVERSO MAESTRO'!$C$6:$C$497,MATCH(E83,'UNIVERSO MAESTRO'!$A$6:$A$497,0)),"⚠ ID no encontrado")) -> Liga MX | G83: =IF(E83="","",IFERROR(INDEX('UNIVERSO MAESTRO'!$D$6:$D$497,MATCH(E83,'UNIVERSO MAESTRO'!$A$6:$A$497,0)),"")) -> V1 | H83: Rights / Media | I83: R1 | J83: A→B | K83: TUDN/ViX retiene derechos de transmisión de 7-8 clubes Liga MX en México. TelevisaUnivision es también el broadcaster de los 104 partidos WC26 en México vía ViX Premium (exclusivo). | L83: TUDN/ViX tiene derechos de 7-8 clubs Liga MX en México: el broadcaster histórico que coexiste con Amazon, Netflix y Fox. | M83: televisaunivision.com; espn.com.mx; dpln.news | N83: =IF(OR(B83="",E83=""),"",IF(D83=G83,"No","Sí")) -> Sí | O83: =IF(I83="","",IF(I83="R3","No","Sí")) -> Sí
A84: R-222 | B84: A-137 | C84: =IF(B84="","",IFERROR(INDEX('UNIVERSO MAESTRO'!$C$6:$C$497,MATCH(B84,'UNIVERSO MAESTRO'!$A$6:$A$497,0)),"⚠ ID no encontrado")) -> TelevisaUnivision | D84: =IF(B84="","",IFERROR(INDEX('UNIVERSO MAESTRO'!$D$6:$D$497,MATCH(B84,'UNIVERSO MAESTRO'!$A$6:$A$497,0)),"")) -> V2 | E84: A-105 | F84: =IF(E84="","",IFERROR(INDEX('UNIVERSO MAESTRO'!$C$6:$C$497,MATCH(E84,'UNIVERSO MAESTRO'!$A$6:$A$497,0)),"⚠ ID no encontrado")) -> Ollamani, S.A.B. / Grupo Águilas (Club América + Estadio Banorte) | G84: =IF(E84="","",IFERROR(INDEX('UNIVERSO MAESTRO'!$D$6:$D$497,MATCH(E84,'UNIVERSO MAESTRO'!$A$6:$A$497,0)),"")) -> V9 | H84: Rights / Media | I84: R1 | J84: A→B | K84: TUDN/ViX tiene los derechos de transmisión del Club América en México (junto con otros clubes del grupo TUDN/Canal 5). | L84: TUDN/ViX tiene derechos de América en México: el broadcaster y el club más valioso comparten el universo corporativo Azcárraga. | M84: tudn.com; televisaunivision.com | N84: =IF(OR(B84="",E84=""),"",IF(D84=G84,"No","Sí")) -> Sí | O84: =IF(I84="","",IF(I84="R3","No","Sí")) -> Sí
A85: R-223 | B85: A-137 | C85: =IF(B85="","",IFERROR(INDEX('UNIVERSO MAESTRO'!$C$6:$C$497,MATCH(B85,'UNIVERSO MAESTRO'!$A$6:$A$497,0)),"⚠ ID no encontrado")) -> TelevisaUnivision | D85: =IF(B85="","",IFERROR(INDEX('UNIVERSO MAESTRO'!$D$6:$D$497,MATCH(B85,'UNIVERSO MAESTRO'!$A$6:$A$497,0)),"")) -> V2 | E85: A-123 | F85: =IF(E85="","",IFERROR(INDEX('UNIVERSO MAESTRO'!$C$6:$C$497,MATCH(E85,'UNIVERSO MAESTRO'!$A$6:$A$497,0)),"⚠ ID no encontrado")) -> Selección Mexicana de Fútbol | G85: =IF(E85="","",IFERROR(INDEX('UNIVERSO MAESTRO'!$D$6:$D$497,MATCH(E85,'UNIVERSO MAESTRO'!$A$6:$A$497,0)),"")) -> V1 | H85: Rights / Media | I85: R1 | J85: A→B | K85: TUDN es el broadcaster histórico de la Selección Mexicana en México. Comparte ciclo con Netflix (CONCACAF) desde abr-2026. | L85: TUDN es el broadcaster histórico de El Tri: comparte ciclo con Netflix desde abr-2025. | M85: tudn.com; fmf.mx | N85: =IF(OR(B85="",E85=""),"",IF(D85=G85,"No","Sí")) -> Sí | O85: =IF(I85="","",IF(I85="R3","No","Sí")) -> Sí
